Workbook

Sheet Strength
A2: Competitive strength
A3: Draft competitive strength: scale plus client/partner network. ETF positioning remains a separate diagnostic.
A5: Universe status | B5: Cap-eligible issuers | C5: Revenue-ready issuers | D5: Eligible cap USD bn | E5: Relevant revenue USD bn | G5: Passive funds | H5: Active funds | I5: Passive AUM USD bn | J5: Active AUM USD bn
A6: =IF(Rules!$B$7="Not selected","Choose research scope",IF(Rules!$B$15<>"Yes","Confirm issuer universe",IF(B6<Rules!$B$12,"Too few comparable issuers",IF(B6<>C6,"Revenue inputs incomplete",IF(E6<=0,"Revenue denominator missing",IF(OR(Rules!$B$13<0,Rules!$B$14<0,ABS(SUM(Rules!$B$13:$B$14)-1)>0.000001),"Check score weights","Ready")))))) -> Choose research scope | B6: =COUNTIFS(Companies!$R$6:$R$55,1) -> 0 | C6: =COUNTIFS(Companies!$S$6:$S$55,1) -> 0 | D6: =SUMIFS(Companies!$I$6:$I$55,Companies!$R$6:$R$55,1) -> 0 | E6: =SUMIFS(Companies!$K$6:$K$55,Companies!$S$6:$S$55,1) -> 0 | G6: =COUNTIFS(ETFs!$K$6:$K$25,1,ETFs!$D$6:$D$25,"Passive") -> 0 | H6: =COUNTIFS(ETFs!$K$6:$K$25,1,ETFs!$D$6:$D$25,"Active") -> 0 | I6: =SUMIFS(ETFs!$G$6:$G$25,ETFs!$K$6:$K$25,1,ETFs!$D$6:$D$25,"Passive") -> 0 | J6: =SUMIFS(ETFs!$G$6:$G$25,ETFs!$K$6:$K$25,1,ETFs!$D$6:$D$25,"Active") -> 0
A9: Issuer ID | B9: Company | C9: Cap rank | D9: Cap share | E9: Revenue share | F9: Cap/revenue share ratio | G9: Cap percentile | H9: Revenue percentile | I9: Scale score /100 | J9: Competitor count | K9: Larger competitors | L9: Cap / avg competitor cap | M9: Passive pairs ready | N9: Active pairs ready | O9: Passive ETF weight | P9: Active ETF weight | Q9: Passive ownership proxy | R9: Active ownership proxy | S9: ETF coverage | T9: Network score /100 | U9: Competitive strength /100 | V9: Combined status
A10: =IF(Companies!R6=1,Companies!A6,"") | B10: =IF(A10="","",Companies!C6) | C10: =IF(A10="","",1+COUNTIFS(Companies!$R$6:$R$55,1,Companies!$I$6:$I$55,">"&Companies!I6)) | D10: =IF(A10="","",Companies!I6/$D$6) | E10: =IF(A10="","",IF($A$6<>"Ready","n.a.",Companies!K6/$E$6)) | F10: =IF(A10="","",IF(OR($A$6<>"Ready",E10=0),"n.a.",D10/E10)) | G10: =IF(A10="","",IF($B$6<Rules!$B$12,"n.a.",100*(COUNTIFS(Companies!$R$6:$R$55,1,Companies!$I$6:$I$55,"<"&Companies!I6)+0.5*(COUNTIFS(Companies!$R$6:$R$55,1,Companies!$I$6:$I$55,Companies!I6)-1))/($B$6-1))) | H10: =IF(A10="","",IF($A$6<>"Ready","n.a.",100*(COUNTIFS(Companies!$S$6:$S$55,1,Companies!$K$6:$K$55,"<"&Companies!K6)+0.5*(COUNTIFS(Companies!$S$6:$S$55,1,Companies!$K$6:$K$55,Companies!K6)-1))/($C$6-1))) | I10: =IF(A10="","",IF($A$6<>"Ready","n.a.",Rules!$B$13*H10+Rules!$B$14*G10)) | J10: =IF(A10="","",$B$6-1) | K10: =IF(A10="","",C10-1) | L10: =IF(A10="","",IF(OR($B$6<2,$D$6<=Companies!I6),"n.a.",Companies!I6/(($D$6-Companies!I6)/($B$6-1)))) | M10: =IF(A10="","",COUNTIFS(Holdings!$A$6:$A$205,A10,Holdings!$H$6:$H$205,"Passive",Holdings!$K$6:$K$205,1)) | N10: =IF(A10="","",COUNTIFS(Holdings!$A$6:$A$205,A10,Holdings!$H$6:$H$205,"Active",Holdings!$K$6:$K$205,1)) | O10: =IF(A10="","",IF(OR($G$6=0,M10<>$G$6),"n.a.",SUMIFS(Holdings!$D$6:$D$205,Holdings!$A$6:$A$205,A10,Holdings!$H$6:$H$205,"Passive",Holdings!$K$6:$K$205,1)/$I$6)) | P10: =IF(A10="","",IF(OR($H$6=0,N10<>$H$6),"n.a.",SUMIFS(Holdings!$D$6:$D$205,Holdings!$A$6:$A$205,A10,Holdings!$H$6:$H$205,"Active",Holdings!$K$6:$K$205,1)/$J$6)) | Q10: =IF(A10="","",IF(OR($G$6=0,M10<>$G$6),"n.a.",SUMIFS(Holdings!$D$6:$D$205,Holdings!$A$6:$A$205,A10,Holdings!$H$6:$H$205,"Passive",Holdings!$K$6:$K$205,1)/Companies!I6)) | R10: =IF(A10="","",IF(OR($H$6=0,N10<>$H$6),"n.a.",SUMIFS(Holdings!$D$6:$D$205,Holdings!$A$6:$A$205,A10,Holdings!$H$6:$H$205,"Active",Holdings!$K$6:$K$205,1)/Companies!I6)) | S10: =IF(A10="","",IF($G$6+$H$6=0,"No ETF panel",IF(M10+N10=$G$6+$H$6,"Complete selected panel","Missing ETF pairs"))) | T10: {=IF(A10="","",IFNA(INDEX(Network!$L$14:$L$63,MATCH(A10,Network!$A$14:$A$63,0)),"n.a."))} | U10: =IF(A10="","",IF(OR(OR(COUNT(Rules!$B$45:$B$46)<>2,MIN(Rules!$B$45:$B$46)<0,ABS(SUM(Rules!$B$45:$B$46)-1)>0.000001),AND(Rules!$B$45>0,NOT(ISNUMBER(I10))),AND(Rules!$B$46>0,NOT(ISNUMBER(T10)))),"n.a.",IF(Rules!$B$45=0,0,Rules!$B$45*I10)+IF(Rules!$B$46=0,0,Rules!$B$46*T10))) | V10: =IF(A10="","",IF(OR(COUNT(Rules!$B$45:$B$46)<>2,MIN(Rules!$B$45:$B$46)<0,ABS(SUM(Rules!$B$45:$B$46)-1)>0.000001),"Check combined weights",IF(AND(Rules!$B$45>0,NOT(ISNUMBER(I10))),"Scale score unavailable",IF(AND(Rules!$B$46>0,NOT(ISNUMBER(T10))),"Network review/score unavailable","Ready"))))
A11: =IF(Companies!R7=1,Companies!A7,"") | B11: =IF(A11="","",Companies!C7) | C11: =IF(A11="","",1+COUNTIFS(Companies!$R$6:$R$55,1,Companies!$I$6:$I$55,">"&Companies!I7)) | D11: =IF(A11="","",Companies!I7/$D$6) | E11: =IF(A11="","",IF($A$6<>"Ready","n.a.",Companies!K7/$E$6)) | F11: =IF(A11="","",IF(OR($A$6<>"Ready",E11=0),"n.a.",D11/E11)) | G11: =IF(A11="","",IF($B$6<Rules!$B$12,"n.a.",100*(COUNTIFS(Companies!$R$6:$R$55,1,Companies!$I$6:$I$55,"<"&Companies!I7)+0.5*(COUNTIFS(Companies!$R$6:$R$55,1,Companies!$I$6:$I$55,Companies!I7)-1))/($B$6-1))) | H11: =IF(A11="","",IF($A$6<>"Ready","n.a.",100*(COUNTIFS(Companies!$S$6:$S$55,1,Companies!$K$6:$K$55,"<"&Companies!K7)+0.5*(COUNTIFS(Companies!$S$6:$S$55,1,Companies!$K$6:$K$55,Companies!K7)-1))/($C$6-1))) | I11: =IF(A11="","",IF($A$6<>"Ready","n.a.",Rules!$B$13*H11+Rules!$B$14*G11)) | J11: =IF(A11="","",$B$6-1) | K11: =IF(A11="","",C11-1) | L11: =IF(A11="","",IF(OR($B$6<2,$D$6<=Companies!I7),"n.a.",Companies!I7/(($D$6-Companies!I7)/($B$6-1)))) | M11: =IF(A11="","",COUNTIFS(Holdings!$A$6:$A$205,A11,Holdings!$H$6:$H$205,"Passive",Holdings!$K$6:$K$205,1)) | N11: =IF(A11="","",COUNTIFS(Holdings!$A$6:$A$205,A11,Holdings!$H$6:$H$205,"Active",Holdings!$K$6:$K$205,1)) | O11: =IF(A11="","",IF(OR($G$6=0,M11<>$G$6),"n.a.",SUMIFS(Holdings!$D$6:$D$205,Holdings!$A$6:$A$205,A11,Holdings!$H$6:$H$205,"Passive",Holdings!$K$6:$K$205,1)/$I$6)) | P11: =IF(A11="","",IF(OR($H$6=0,N11<>$H$6),"n.a.",SUMIFS(Holdings!$D$6:$D$205,Holdings!$A$6:$A$205,A11,Holdings!$H$6:$H$205,"Active",Holdings!$K$6:$K$205,1)/$J$6)) | Q11: =IF(A11="","",IF(OR($G$6=0,M11<>$G$6),"n.a.",SUMIFS(Holdings!$D$6:$D$205,Holdings!$A$6:$A$205,A11,Holdings!$H$6:$H$205,"Passive",Holdings!$K$6:$K$205,1)/Companies!I7)) | R11: =IF(A11="","",IF(OR($H$6=0,N11<>$H$6),"n.a.",SUMIFS(Holdings!$D$6:$D$205,Holdings!$A$6:$A$205,A11,Holdings!$H$6:$H$205,"Active",Holdings!$K$6:$K$205,1)/Companies!I7)) | S11: =IF(A11="","",IF($G$6+$H$6=0,"No ETF panel",IF(M11+N11=$G$6+$H$6,"Complete selected panel","Missing ETF pairs"))) | T11: {=IF(A11="","",IFNA(INDEX(Network!$L$14:$L$63,MATCH(A11,Network!$A$14:$A$63,0)),"n.a."))} | U11: =IF(A11="","",IF(OR(OR(COUNT(Rules!$B$45:$B$46)<>2,MIN(Rules!$B$45:$B$46)<0,ABS(SUM(Rules!$B$45:$B$46)-1)>0.000001),AND(Rules!$B$45>0,NOT(ISNUMBER(I11))),AND(Rules!$B$46>0,NOT(ISNUMBER(T11)))),"n.a.",IF(Rules!$B$45=0,0,Rules!$B$45*I11)+IF(Rules!$B$46=0,0,Rules!$B$46*T11))) | V11: =IF(A11="","",IF(OR(COUNT(Rules!$B$45:$B$46)<>2,MIN(Rules!$B$45:$B$46)<0,ABS(SUM(Rules!$B$45:$B$46)-1)>0.000001),"Check combined weights",IF(AND(Rules!$B$45>0,NOT(ISNUMBER(I11))),"Scale score unavailable",IF(AND(Rules!$B$46>0,NOT(ISNUMBER(T11))),"Network review/score unavailable","Ready"))))
A12: =IF(Companies!R8=1,Companies!A8,"") | B12: =IF(A12="","",Companies!C8) | C12: =IF(A12="","",1+COUNTIFS(Companies!$R$6:$R$55,1,Companies!$I$6:$I$55,">"&Companies!I8)) | D12: =IF(A12="","",Companies!I8/$D$6) | E12: =IF(A12="","",IF($A$6<>"Ready","n.a.",Companies!K8/$E$6)) | F12: =IF(A12="","",IF(OR($A$6<>"Ready",E12=0),"n.a.",D12/E12)) | G12: =IF(A12="","",IF($B$6<Rules!$B$12,"n.a.",100*(COUNTIFS(Companies!$R$6:$R$55,1,Companies!$I$6:$I$55,"<"&Companies!I8)+0.5*(COUNTIFS(Companies!$R$6:$R$55,1,Companies!$I$6:$I$55,Companies!I8)-1))/($B$6-1))) | H12: =IF(A12="","",IF($A$6<>"Ready","n.a.",100*(COUNTIFS(Companies!$S$6:$S$55,1,Companies!$K$6:$K$55,"<"&Companies!K8)+0.5*(COUNTIFS(Companies!$S$6:$S$55,1,Companies!$K$6:$K$55,Companies!K8)-1))/($C$6-1))) | I12: =IF(A12="","",IF($A$6<>"Ready","n.a.",Rules!$B$13*H12+Rules!$B$14*G12)) | J12: =IF(A12="","",$B$6-1) | K12: =IF(A12="","",C12-1) | L12: =IF(A12="","",IF(OR($B$6<2,$D$6<=Companies!I8),"n.a.",Companies!I8/(($D$6-Companies!I8)/($B$6-1)))) | M12: =IF(A12="","",COUNTIFS(Holdings!$A$6:$A$205,A12,Holdings!$H$6:$H$205,"Passive",Holdings!$K$6:$K$205,1)) | N12: =IF(A12="","",COUNTIFS(Holdings!$A$6:$A$205,A12,Holdings!$H$6:$H$205,"Active",Holdings!$K$6:$K$205,1)) | O12: =IF(A12="","",IF(OR($G$6=0,M12<>$G$6),"n.a.",SUMIFS(Holdings!$D$6:$D$205,Holdings!$A$6:$A$205,A12,Holdings!$H$6:$H$205,"Passive",Holdings!$K$6:$K$205,1)/$I$6)) | P12: =IF(A12="","",IF(OR($H$6=0,N12<>$H$6),"n.a.",SUMIFS(Holdings!$D$6:$D$205,Holdings!$A$6:$A$205,A12,Holdings!$H$6:$H$205,"Active",Holdings!$K$6:$K$205,1)/$J$6)) | Q12: =IF(A12="","",IF(OR($G$6=0,M12<>$G$6),"n.a.",SUMIFS(Holdings!$D$6:$D$205,Holdings!$A$6:$A$205,A12,Holdings!$H$6:$H$205,"Passive",Holdings!$K$6:$K$205,1)/Companies!I8)) | R12: =IF(A12="","",IF(OR($H$6=0,N12<>$H$6),"n.a.",SUMIFS(Holdings!$D$6:$D$205,Holdings!$A$6:$A$205,A12,Holdings!$H$6:$H$205,"Active",Holdings!$K$6:$K$205,1)/Companies!I8)) | S12: =IF(A12="","",IF($G$6+$H$6=0,"No ETF panel",IF(M12+N12=$G$6+$H$6,"Complete selected panel","Missing ETF pairs"))) | T12: {=IF(A12="","",IFNA(INDEX(Network!$L$14:$L$63,MATCH(A12,Network!$A$14:$A$63,0)),"n.a."))} | U12: =IF(A12="","",IF(OR(OR(COUNT(Rules!$B$45:$B$46)<>2,MIN(Rules!$B$45:$B$46)<0,ABS(SUM(Rules!$B$45:$B$46)-1)>0.000001),AND(Rules!$B$45>0,NOT(ISNUMBER(I12))),AND(Rules!$B$46>0,NOT(ISNUMBER(T12)))),"n.a.",IF(Rules!$B$45=0,0,Rules!$B$45*I12)+IF(Rules!$B$46=0,0,Rules!$B$46*T12))) | V12: =IF(A12="","",IF(OR(COUNT(Rules!$B$45:$B$46)<>2,MIN(Rules!$B$45:$B$46)<0,ABS(SUM(Rules!$B$45:$B$46)-1)>0.000001),"Check combined weights",IF(AND(Rules!$B$45>0,NOT(ISNUMBER(I12))),"Scale score unavailable",IF(AND(Rules!$B$46>0,NOT(ISNUMBER(T12))),"Network review/score unavailable","Ready"))))
A13: =IF(Companies!R9=1,Companies!A9,"") | B13: =IF(A13="","",Companies!C9) | C13: =IF(A13="","",1+COUNTIFS(Companies!$R$6:$R$55,1,Companies!$I$6:$I$55,">"&Companies!I9)) | D13: =IF(A13="","",Companies!I9/$D$6) | E13: =IF(A13="","",IF($A$6<>"Ready","n.a.",Companies!K9/$E$6)) | F13: =IF(A13="","",IF(OR($A$6<>"Ready",E13=0),"n.a.",D13/E13)) | G13: =IF(A13="","",IF($B$6<Rules!$B$12,"n.a.",100*(COUNTIFS(Companies!$R$6:$R$55,1,Companies!$I$6:$I$55,"<"&Companies!I9)+0.5*(COUNTIFS(Companies!$R$6:$R$55,1,Companies!$I$6:$I$55,Companies!I9)-1))/($B$6-1))) | H13: =IF(A13="","",IF($A$6<>"Ready","n.a.",100*(COUNTIFS(Companies!$S$6:$S$55,1,Companies!$K$6:$K$55,"<"&Companies!K9)+0.5*(COUNTIFS(Companies!$S$6:$S$55,1,Companies!$K$6:$K$55,Companies!K9)-1))/($C$6-1))) | I13: =IF(A13="","",IF($A$6<>"Ready","n.a.",Rules!$B$13*H13+Rules!$B$14*G13)) | J13: =IF(A13="","",$B$6-1) | K13: =IF(A13="","",C13-1) | L13: =IF(A13="","",IF(OR($B$6<2,$D$6<=Companies!I9),"n.a.",Companies!I9/(($D$6-Companies!I9)/($B$6-1)))) | M13: =IF(A13="","",COUNTIFS(Holdings!$A$6:$A$205,A13,Holdings!$H$6:$H$205,"Passive",Holdings!$K$6:$K$205,1)) | N13: =IF(A13="","",COUNTIFS(Holdings!$A$6:$A$205,A13,Holdings!$H$6:$H$205,"Active",Holdings!$K$6:$K$205,1)) | O13: =IF(A13="","",IF(OR($G$6=0,M13<>$G$6),"n.a.",SUMIFS(Holdings!$D$6:$D$205,Holdings!$A$6:$A$205,A13,Holdings!$H$6:$H$205,"Passive",Holdings!$K$6:$K$205,1)/$I$6)) | P13: =IF(A13="","",IF(OR($H$6=0,N13<>$H$6),"n.a.",SUMIFS(Holdings!$D$6:$D$205,Holdings!$A$6:$A$205,A13,Holdings!$H$6:$H$205,"Active",Holdings!$K$6:$K$205,1)/$J$6)) | Q13: =IF(A13="","",IF(OR($G$6=0,M13<>$G$6),"n.a.",SUMIFS(Holdings!$D$6:$D$205,Holdings!$A$6:$A$205,A13,Holdings!$H$6:$H$205,"Passive",Holdings!$K$6:$K$205,1)/Companies!I9)) | R13: =IF(A13="","",IF(OR($H$6=0,N13<>$H$6),"n.a.",SUMIFS(Holdings!$D$6:$D$205,Holdings!$A$6:$A$205,A13,Holdings!$H$6:$H$205,"Active",Holdings!$K$6:$K$205,1)/Companies!I9)) | S13: =IF(A13="","",IF($G$6+$H$6=0,"No ETF panel",IF(M13+N13=$G$6+$H$6,"Complete selected panel","Missing ETF pairs"))) | T13: {=IF(A13="","",IFNA(INDEX(Network!$L$14:$L$63,MATCH(A13,Network!$A$14:$A$63,0)),"n.a."))} | U13: =IF(A13="","",IF(OR(OR(COUNT(Rules!$B$45:$B$46)<>2,MIN(Rules!$B$45:$B$46)<0,ABS(SUM(Rules!$B$45:$B$46)-1)>0.000001),AND(Rules!$B$45>0,NOT(ISNUMBER(I13))),AND(Rules!$B$46>0,NOT(ISNUMBER(T13)))),"n.a.",IF(Rules!$B$45=0,0,Rules!$B$45*I13)+IF(Rules!$B$46=0,0,Rules!$B$46*T13))) | V13: =IF(A13="","",IF(OR(COUNT(Rules!$B$45:$B$46)<>2,MIN(Rules!$B$45:$B$46)<0,ABS(SUM(Rules!$B$45:$B$46)-1)>0.000001),"Check combined weights",IF(AND(Rules!$B$45>0,NOT(ISNUMBER(I13))),"Scale score unavailable",IF(AND(Rules!$B$46>0,NOT(ISNUMBER(T13))),"Network review/score unavailable","Ready"))))
A14: =IF(Companies!R10=1,Companies!A10,"") | B14: =IF(A14="","",Companies!C10) | C14: =IF(A14="","",1+COUNTIFS(Companies!$R$6:$R$55,1,Companies!$I$6:$I$55,">"&Companies!I10)) | D14: =IF(A14="","",Companies!I10/$D$6) | E14: =IF(A14="","",IF($A$6<>"Ready","n.a.",Companies!K10/$E$6)) | F14: =IF(A14="","",IF(OR($A$6<>"Ready",E14=0),"n.a.",D14/E14)) | G14: =IF(A14="","",IF($B$6<Rules!$B$12,"n.a.",100*(COUNTIFS(Companies!$R$6:$R$55,1,Companies!$I$6:$I$55,"<"&Companies!I10)+0.5*(COUNTIFS(Companies!$R$6:$R$55,1,Companies!$I$6:$I$55,Companies!I10)-1))/($B$6-1))) | H14: =IF(A14="","",IF($A$6<>"Ready","n.a.",100*(COUNTIFS(Companies!$S$6:$S$55,1,Companies!$K$6:$K$55,"<"&Companies!K10)+0.5*(COUNTIFS(Companies!$S$6:$S$55,1,Companies!$K$6:$K$55,Companies!K10)-1))/($C$6-1))) | I14: =IF(A14="","",IF($A$6<>"Ready","n.a.",Rules!$B$13*H14+Rules!$B$14*G14)) | J14: =IF(A14="","",$B$6-1) | K14: =IF(A14="","",C14-1) | L14: =IF(A14="","",IF(OR($B$6<2,$D$6<=Companies!I10),"n.a.",Companies!I10/(($D$6-Companies!I10)/($B$6-1)))) | M14: =IF(A14="","",COUNTIFS(Holdings!$A$6:$A$205,A14,Holdings!$H$6:$H$205,"Passive",Holdings!$K$6:$K$205,1)) | N14: =IF(A14="","",COUNTIFS(Holdings!$A$6:$A$205,A14,Holdings!$H$6:$H$205,"Active",Holdings!$K$6:$K$205,1)) | O14: =IF(A14="","",IF(OR($G$6=0,M14<>$G$6),"n.a.",SUMIFS(Holdings!$D$6:$D$205,Holdings!$A$6:$A$205,A14,Holdings!$H$6:$H$205,"Passive",Holdings!$K$6:$K$205,1)/$I$6)) | P14: =IF(A14="","",IF(OR($H$6=0,N14<>$H$6),"n.a.",SUMIFS(Holdings!$D$6:$D$205,Holdings!$A$6:$A$205,A14,Holdings!$H$6:$H$205,"Active",Holdings!$K$6:$K$205,1)/$J$6)) | Q14: =IF(A14="","",IF(OR($G$6=0,M14<>$G$6),"n.a.",SUMIFS(Holdings!$D$6:$D$205,Holdings!$A$6:$A$205,A14,Holdings!$H$6:$H$205,"Passive",Holdings!$K$6:$K$205,1)/Companies!I10)) | R14: =IF(A14="","",IF(OR($H$6=0,N14<>$H$6),"n.a.",SUMIFS(Holdings!$D$6:$D$205,Holdings!$A$6:$A$205,A14,Holdings!$H$6:$H$205,"Active",Holdings!$K$6:$K$205,1)/Companies!I10)) | S14: =IF(A14="","",IF($G$6+$H$6=0,"No ETF panel",IF(M14+N14=$G$6+$H$6,"Complete selected panel","Missing ETF pairs"))) | T14: {=IF(A14="","",IFNA(INDEX(Network!$L$14:$L$63,MATCH(A14,Network!$A$14:$A$63,0)),"n.a."))} | U14: =IF(A14="","",IF(OR(OR(COUNT(Rules!$B$45:$B$46)<>2,MIN(Rules!$B$45:$B$46)<0,ABS(SUM(Rules!$B$45:$B$46)-1)>0.000001),AND(Rules!$B$45>0,NOT(ISNUMBER(I14))),AND(Rules!$B$46>0,NOT(ISNUMBER(T14)))),"n.a.",IF(Rules!$B$45=0,0,Rules!$B$45*I14)+IF(Rules!$B$46=0,0,Rules!$B$46*T14))) | V14: =IF(A14="","",IF(OR(COUNT(Rules!$B$45:$B$46)<>2,MIN(Rules!$B$45:$B$46)<0,ABS(SUM(Rules!$B$45:$B$46)-1)>0.000001),"Check combined weights",IF(AND(Rules!$B$45>0,NOT(ISNUMBER(I14))),"Scale score unavailable",IF(AND(Rules!$B$46>0,NOT(ISNUMBER(T14))),"Network review/score unavailable","Ready"))))
A15: =IF(Companies!R11=1,Companies!A11,"") | B15: =IF(A15="","",Companies!C11) | C15: =IF(A15="","",1+COUNTIFS(Companies!$R$6:$R$55,1,Companies!$I$6:$I$55,">"&Companies!I11)) | D15: =IF(A15="","",Companies!I11/$D$6) | E15: =IF(A15="","",IF($A$6<>"Ready","n.a.",Companies!K11/$E$6)) | F15: =IF(A15="","",IF(OR($A$6<>"Ready",E15=0),"n.a.",D15/E15)) | G15: =IF(A15="","",IF($B$6<Rules!$B$12,"n.a.",100*(COUNTIFS(Companies!$R$6:$R$55,1,Companies!$I$6:$I$55,"<"&Companies!I11)+0.5*(COUNTIFS(Companies!$R$6:$R$55,1,Companies!$I$6:$I$55,Companies!I11)-1))/($B$6-1))) | H15: =IF(A15="","",IF($A$6<>"Ready","n.a.",100*(COUNTIFS(Companies!$S$6:$S$55,1,Companies!$K$6:$K$55,"<"&Companies!K11)+0.5*(COUNTIFS(Companies!$S$6:$S$55,1,Companies!$K$6:$K$55,Companies!K11)-1))/($C$6-1))) | I15: =IF(A15="","",IF($A$6<>"Ready","n.a.",Rules!$B$13*H15+Rules!$B$14*G15)) | J15: =IF(A15="","",$B$6-1) | K15: =IF(A15="","",C15-1) | L15: =IF(A15="","",IF(OR($B$6<2,$D$6<=Companies!I11),"n.a.",Companies!I11/(($D$6-Companies!I11)/($B$6-1)))) | M15: =IF(A15="","",COUNTIFS(Holdings!$A$6:$A$205,A15,Holdings!$H$6:$H$205,"Passive",Holdings!$K$6:$K$205,1)) | N15: =IF(A15="","",COUNTIFS(Holdings!$A$6:$A$205,A15,Holdings!$H$6:$H$205,"Active",Holdings!$K$6:$K$205,1)) | O15: =IF(A15="","",IF(OR($G$6=0,M15<>$G$6),"n.a.",SUMIFS(Holdings!$D$6:$D$205,Holdings!$A$6:$A$205,A15,Holdings!$H$6:$H$205,"Passive",Holdings!$K$6:$K$205,1)/$I$6)) | P15: =IF(A15="","",IF(OR($H$6=0,N15<>$H$6),"n.a.",SUMIFS(Holdings!$D$6:$D$205,Holdings!$A$6:$A$205,A15,Holdings!$H$6:$H$205,"Active",Holdings!$K$6:$K$205,1)/$J$6)) | Q15: =IF(A15="","",IF(OR($G$6=0,M15<>$G$6),"n.a.",SUMIFS(Holdings!$D$6:$D$205,Holdings!$A$6:$A$205,A15,Holdings!$H$6:$H$205,"Passive",Holdings!$K$6:$K$205,1)/Companies!I11)) | R15: =IF(A15="","",IF(OR($H$6=0,N15<>$H$6),"n.a.",SUMIFS(Holdings!$D$6:$D$205,Holdings!$A$6:$A$205,A15,Holdings!$H$6:$H$205,"Active",Holdings!$K$6:$K$205,1)/Companies!I11)) | S15: =IF(A15="","",IF($G$6+$H$6=0,"No ETF panel",IF(M15+N15=$G$6+$H$6,"Complete selected panel","Missing ETF pairs"))) | T15: {=IF(A15="","",IFNA(INDEX(Network!$L$14:$L$63,MATCH(A15,Network!$A$14:$A$63,0)),"n.a."))} | U15: =IF(A15="","",IF(OR(OR(COUNT(Rules!$B$45:$B$46)<>2,MIN(Rules!$B$45:$B$46)<0,ABS(SUM(Rules!$B$45:$B$46)-1)>0.000001),AND(Rules!$B$45>0,NOT(ISNUMBER(I15))),AND(Rules!$B$46>0,NOT(ISNUMBER(T15)))),"n.a.",IF(Rules!$B$45=0,0,Rules!$B$45*I15)+IF(Rules!$B$46=0,0,Rules!$B$46*T15))) | V15: =IF(A15="","",IF(OR(COUNT(Rules!$B$45:$B$46)<>2,MIN(Rules!$B$45:$B$46)<0,ABS(SUM(Rules!$B$45:$B$46)-1)>0.000001),"Check combined weights",IF(AND(Rules!$B$45>0,NOT(ISNUMBER(I15))),"Scale score unavailable",IF(AND(Rules!$B$46>0,NOT(ISNUMBER(T15))),"Network review/score unavailable","Ready"))))
A16: =IF(Companies!R12=1,Companies!A12,"") | B16: =IF(A16="","",Companies!C12) | C16: =IF(A16="","",1+COUNTIFS(Companies!$R$6:$R$55,1,Companies!$I$6:$I$55,">"&Companies!I12)) | D16: =IF(A16="","",Companies!I12/$D$6) | E16: =IF(A16="","",IF($A$6<>"Ready","n.a.",Companies!K12/$E$6)) | F16: =IF(A16="","",IF(OR($A$6<>"Ready",E16=0),"n.a.",D16/E16)) | G16: =IF(A16="","",IF($B$6<Rules!$B$12,"n.a.",100*(COUNTIFS(Companies!$R$6:$R$55,1,Companies!$I$6:$I$55,"<"&Companies!I12)+0.5*(COUNTIFS(Companies!$R$6:$R$55,1,Companies!$I$6:$I$55,Companies!I12)-1))/($B$6-1))) | H16: =IF(A16="","",IF($A$6<>"Ready","n.a.",100*(COUNTIFS(Companies!$S$6:$S$55,1,Companies!$K$6:$K$55,"<"&Companies!K12)+0.5*(COUNTIFS(Companies!$S$6:$S$55,1,Companies!$K$6:$K$55,Companies!K12)-1))/($C$6-1))) | I16: =IF(A16="","",IF($A$6<>"Ready","n.a.",Rules!$B$13*H16+Rules!$B$14*G16)) | J16: =IF(A16="","",$B$6-1) | K16: =IF(A16="","",C16-1) | L16: =IF(A16="","",IF(OR($B$6<2,$D$6<=Companies!I12),"n.a.",Companies!I12/(($D$6-Companies!I12)/($B$6-1)))) | M16: =IF(A16="","",COUNTIFS(Holdings!$A$6:$A$205,A16,Holdings!$H$6:$H$205,"Passive",Holdings!$K$6:$K$205,1)) | N16: =IF(A16="","",COUNTIFS(Holdings!$A$6:$A$205,A16,Holdings!$H$6:$H$205,"Active",Holdings!$K$6:$K$205,1)) | O16: =IF(A16="","",IF(OR($G$6=0,M16<>$G$6),"n.a.",SUMIFS(Holdings!$D$6:$D$205,Holdings!$A$6:$A$205,A16,Holdings!$H$6:$H$205,"Passive",Holdings!$K$6:$K$205,1)/$I$6)) | P16: =IF(A16="","",IF(OR($H$6=0,N16<>$H$6),"n.a.",SUMIFS(Holdings!$D$6:$D$205,Holdings!$A$6:$A$205,A16,Holdings!$H$6:$H$205,"Active",Holdings!$K$6:$K$205,1)/$J$6)) | Q16: =IF(A16="","",IF(OR($G$6=0,M16<>$G$6),"n.a.",SUMIFS(Holdings!$D$6:$D$205,Holdings!$A$6:$A$205,A16,Holdings!$H$6:$H$205,"Passive",Holdings!$K$6:$K$205,1)/Companies!I12)) | R16: =IF(A16="","",IF(OR($H$6=0,N16<>$H$6),"n.a.",SUMIFS(Holdings!$D$6:$D$205,Holdings!$A$6:$A$205,A16,Holdings!$H$6:$H$205,"Active",Holdings!$K$6:$K$205,1)/Companies!I12)) | S16: =IF(A16="","",IF($G$6+$H$6=0,"No ETF panel",IF(M16+N16=$G$6+$H$6,"Complete selected panel","Missing ETF pairs"))) | T16: {=IF(A16="","",IFNA(INDEX(Network!$L$14:$L$63,MATCH(A16,Network!$A$14:$A$63,0)),"n.a."))} | U16: =IF(A16="","",IF(OR(OR(COUNT(Rules!$B$45:$B$46)<>2,MIN(Rules!$B$45:$B$46)<0,ABS(SUM(Rules!$B$45:$B$46)-1)>0.000001),AND(Rules!$B$45>0,NOT(ISNUMBER(I16))),AND(Rules!$B$46>0,NOT(ISNUMBER(T16)))),"n.a.",IF(Rules!$B$45=0,0,Rules!$B$45*I16)+IF(Rules!$B$46=0,0,Rules!$B$46*T16))) | V16: =IF(A16="","",IF(OR(COUNT(Rules!$B$45:$B$46)<>2,MIN(Rules!$B$45:$B$46)<0,ABS(SUM(Rules!$B$45:$B$46)-1)>0.000001),"Check combined weights",IF(AND(Rules!$B$45>0,NOT(ISNUMBER(I16))),"Scale score unavailable",IF(AND(Rules!$B$46>0,NOT(ISNUMBER(T16))),"Network review/score unavailable","Ready"))))
A17: =IF(Companies!R13=1,Companies!A13,"") | B17: =IF(A17="","",Companies!C13) | C17: =IF(A17="","",1+COUNTIFS(Companies!$R$6:$R$55,1,Companies!$I$6:$I$55,">"&Companies!I13)) | D17: =IF(A17="","",Companies!I13/$D$6) | E17: =IF(A17="","",IF($A$6<>"Ready","n.a.",Companies!K13/$E$6)) | F17: =IF(A17="","",IF(OR($A$6<>"Ready",E17=0),"n.a.",D17/E17)) | G17: =IF(A17="","",IF($B$6<Rules!$B$12,"n.a.",100*(COUNTIFS(Companies!$R$6:$R$55,1,Companies!$I$6:$I$55,"<"&Companies!I13)+0.5*(COUNTIFS(Companies!$R$6:$R$55,1,Companies!$I$6:$I$55,Companies!I13)-1))/($B$6-1))) | H17: =IF(A17="","",IF($A$6<>"Ready","n.a.",100*(COUNTIFS(Companies!$S$6:$S$55,1,Companies!$K$6:$K$55,"<"&Companies!K13)+0.5*(COUNTIFS(Companies!$S$6:$S$55,1,Companies!$K$6:$K$55,Companies!K13)-1))/($C$6-1))) | I17: =IF(A17="","",IF($A$6<>"Ready","n.a.",Rules!$B$13*H17+Rules!$B$14*G17)) | J17: =IF(A17="","",$B$6-1) | K17: =IF(A17="","",C17-1) | L17: =IF(A17="","",IF(OR($B$6<2,$D$6<=Companies!I13),"n.a.",Companies!I13/(($D$6-Companies!I13)/($B$6-1)))) | M17: =IF(A17="","",COUNTIFS(Holdings!$A$6:$A$205,A17,Holdings!$H$6:$H$205,"Passive",Holdings!$K$6:$K$205,1)) | N17: =IF(A17="","",COUNTIFS(Holdings!$A$6:$A$205,A17,Holdings!$H$6:$H$205,"Active",Holdings!$K$6:$K$205,1)) | O17: =IF(A17="","",IF(OR($G$6=0,M17<>$G$6),"n.a.",SUMIFS(Holdings!$D$6:$D$205,Holdings!$A$6:$A$205,A17,Holdings!$H$6:$H$205,"Passive",Holdings!$K$6:$K$205,1)/$I$6)) | P17: =IF(A17="","",IF(OR($H$6=0,N17<>$H$6),"n.a.",SUMIFS(Holdings!$D$6:$D$205,Holdings!$A$6:$A$205,A17,Holdings!$H$6:$H$205,"Active",Holdings!$K$6:$K$205,1)/$J$6)) | Q17: =IF(A17="","",IF(OR($G$6=0,M17<>$G$6),"n.a.",SUMIFS(Holdings!$D$6:$D$205,Holdings!$A$6:$A$205,A17,Holdings!$H$6:$H$205,"Passive",Holdings!$K$6:$K$205,1)/Companies!I13)) | R17: =IF(A17="","",IF(OR($H$6=0,N17<>$H$6),"n.a.",SUMIFS(Holdings!$D$6:$D$205,Holdings!$A$6:$A$205,A17,Holdings!$H$6:$H$205,"Active",Holdings!$K$6:$K$205,1)/Companies!I13)) | S17: =IF(A17="","",IF($G$6+$H$6=0,"No ETF panel",IF(M17+N17=$G$6+$H$6,"Complete selected panel","Missing ETF pairs"))) | T17: {=IF(A17="","",IFNA(INDEX(Network!$L$14:$L$63,MATCH(A17,Network!$A$14:$A$63,0)),"n.a."))} | U17: =IF(A17="","",IF(OR(OR(COUNT(Rules!$B$45:$B$46)<>2,MIN(Rules!$B$45:$B$46)<0,ABS(SUM(Rules!$B$45:$B$46)-1)>0.000001),AND(Rules!$B$45>0,NOT(ISNUMBER(I17))),AND(Rules!$B$46>0,NOT(ISNUMBER(T17)))),"n.a.",IF(Rules!$B$45=0,0,Rules!$B$45*I17)+IF(Rules!$B$46=0,0,Rules!$B$46*T17))) | V17: =IF(A17="","",IF(OR(COUNT(Rules!$B$45:$B$46)<>2,MIN(Rules!$B$45:$B$46)<0,ABS(SUM(Rules!$B$45:$B$46)-1)>0.000001),"Check combined weights",IF(AND(Rules!$B$45>0,NOT(ISNUMBER(I17))),"Scale score unavailable",IF(AND(Rules!$B$46>0,NOT(ISNUMBER(T17))),"Network review/score unavailable","Ready"))))
A18: =IF(Companies!R14=1,Companies!A14,"") | B18: =IF(A18="","",Companies!C14) | C18: =IF(A18="","",1+COUNTIFS(Companies!$R$6:$R$55,1,Companies!$I$6:$I$55,">"&Companies!I14)) | D18: =IF(A18="","",Companies!I14/$D$6) | E18: =IF(A18="","",IF($A$6<>"Ready","n.a.",Companies!K14/$E$6)) | F18: =IF(A18="","",IF(OR($A$6<>"Ready",E18=0),"n.a.",D18/E18)) | G18: =IF(A18="","",IF($B$6<Rules!$B$12,"n.a.",100*(COUNTIFS(Companies!$R$6:$R$55,1,Companies!$I$6:$I$55,"<"&Companies!I14)+0.5*(COUNTIFS(Companies!$R$6:$R$55,1,Companies!$I$6:$I$55,Companies!I14)-1))/($B$6-1))) | H18: =IF(A18="","",IF($A$6<>"Ready","n.a.",100*(COUNTIFS(Companies!$S$6:$S$55,1,Companies!$K$6:$K$55,"<"&Companies!K14)+0.5*(COUNTIFS(Companies!$S$6:$S$55,1,Companies!$K$6:$K$55,Companies!K14)-1))/($C$6-1))) | I18: =IF(A18="","",IF($A$6<>"Ready","n.a.",Rules!$B$13*H18+Rules!$B$14*G18)) | J18: =IF(A18="","",$B$6-1) | K18: =IF(A18="","",C18-1) | L18: =IF(A18="","",IF(OR($B$6<2,$D$6<=Companies!I14),"n.a.",Companies!I14/(($D$6-Companies!I14)/($B$6-1)))) | M18: =IF(A18="","",COUNTIFS(Holdings!$A$6:$A$205,A18,Holdings!$H$6:$H$205,"Passive",Holdings!$K$6:$K$205,1)) | N18: =IF(A18="","",COUNTIFS(Holdings!$A$6:$A$205,A18,Holdings!$H$6:$H$205,"Active",Holdings!$K$6:$K$205,1)) | O18: =IF(A18="","",IF(OR($G$6=0,M18<>$G$6),"n.a.",SUMIFS(Holdings!$D$6:$D$205,Holdings!$A$6:$A$205,A18,Holdings!$H$6:$H$205,"Passive",Holdings!$K$6:$K$205,1)/$I$6)) | P18: =IF(A18="","",IF(OR($H$6=0,N18<>$H$6),"n.a.",SUMIFS(Holdings!$D$6:$D$205,Holdings!$A$6:$A$205,A18,Holdings!$H$6:$H$205,"Active",Holdings!$K$6:$K$205,1)/$J$6)) | Q18: =IF(A18="","",IF(OR($G$6=0,M18<>$G$6),"n.a.",SUMIFS(Holdings!$D$6:$D$205,Holdings!$A$6:$A$205,A18,Holdings!$H$6:$H$205,"Passive",Holdings!$K$6:$K$205,1)/Companies!I14)) | R18: =IF(A18="","",IF(OR($H$6=0,N18<>$H$6),"n.a.",SUMIFS(Holdings!$D$6:$D$205,Holdings!$A$6:$A$205,A18,Holdings!$H$6:$H$205,"Active",Holdings!$K$6:$K$205,1)/Companies!I14)) | S18: =IF(A18="","",IF($G$6+$H$6=0,"No ETF panel",IF(M18+N18=$G$6+$H$6,"Complete selected panel","Missing ETF pairs"))) | T18: {=IF(A18="","",IFNA(INDEX(Network!$L$14:$L$63,MATCH(A18,Network!$A$14:$A$63,0)),"n.a."))} | U18: =IF(A18="","",IF(OR(OR(COUNT(Rules!$B$45:$B$46)<>2,MIN(Rules!$B$45:$B$46)<0,ABS(SUM(Rules!$B$45:$B$46)-1)>0.000001),AND(Rules!$B$45>0,NOT(ISNUMBER(I18))),AND(Rules!$B$46>0,NOT(ISNUMBER(T18)))),"n.a.",IF(Rules!$B$45=0,0,Rules!$B$45*I18)+IF(Rules!$B$46=0,0,Rules!$B$46*T18))) | V18: =IF(A18="","",IF(OR(COUNT(Rules!$B$45:$B$46)<>2,MIN(Rules!$B$45:$B$46)<0,ABS(SUM(Rules!$B$45:$B$46)-1)>0.000001),"Check combined weights",IF(AND(Rules!$B$45>0,NOT(ISNUMBER(I18))),"Scale score unavailable",IF(AND(Rules!$B$46>0,NOT(ISNUMBER(T18))),"Network review/score unavailable","Ready"))))
A19: =IF(Companies!R15=1,Companies!A15,"") | B19: =IF(A19="","",Companies!C15) | C19: =IF(A19="","",1+COUNTIFS(Companies!$R$6:$R$55,1,Companies!$I$6:$I$55,">"&Companies!I15)) | D19: =IF(A19="","",Companies!I15/$D$6) | E19: =IF(A19="","",IF($A$6<>"Ready","n.a.",Companies!K15/$E$6)) | F19: =IF(A19="","",IF(OR($A$6<>"Ready",E19=0),"n.a.",D19/E19)) | G19: =IF(A19="","",IF($B$6<Rules!$B$12,"n.a.",100*(COUNTIFS(Companies!$R$6:$R$55,1,Companies!$I$6:$I$55,"<"&Companies!I15)+0.5*(COUNTIFS(Companies!$R$6:$R$55,1,Companies!$I$6:$I$55,Companies!I15)-1))/($B$6-1))) | H19: =IF(A19="","",IF($A$6<>"Ready","n.a.",100*(COUNTIFS(Companies!$S$6:$S$55,1,Companies!$K$6:$K$55,"<"&Companies!K15)+0.5*(COUNTIFS(Companies!$S$6:$S$55,1,Companies!$K$6:$K$55,Companies!K15)-1))/($C$6-1))) | I19: =IF(A19="","",IF($A$6<>"Ready","n.a.",Rules!$B$13*H19+Rules!$B$14*G19)) | J19: =IF(A19="","",$B$6-1) | K19: =IF(A19="","",C19-1) | L19: =IF(A19="","",IF(OR($B$6<2,$D$6<=Companies!I15),"n.a.",Companies!I15/(($D$6-Companies!I15)/($B$6-1)))) | M19: =IF(A19="","",COUNTIFS(Holdings!$A$6:$A$205,A19,Holdings!$H$6:$H$205,"Passive",Holdings!$K$6:$K$205,1)) | N19: =IF(A19="","",COUNTIFS(Holdings!$A$6:$A$205,A19,Holdings!$H$6:$H$205,"Active",Holdings!$K$6:$K$205,1)) | O19: =IF(A19="","",IF(OR($G$6=0,M19<>$G$6),"n.a.",SUMIFS(Holdings!$D$6:$D$205,Holdings!$A$6:$A$205,A19,Holdings!$H$6:$H$205,"Passive",Holdings!$K$6:$K$205,1)/$I$6)) | P19: =IF(A19="","",IF(OR($H$6=0,N19<>$H$6),"n.a.",SUMIFS(Holdings!$D$6:$D$205,Holdings!$A$6:$A$205,A19,Holdings!$H$6:$H$205,"Active",Holdings!$K$6:$K$205,1)/$J$6)) | Q19: =IF(A19="","",IF(OR($G$6=0,M19<>$G$6),"n.a.",SUMIFS(Holdings!$D$6:$D$205,Holdings!$A$6:$A$205,A19,Holdings!$H$6:$H$205,"Passive",Holdings!$K$6:$K$205,1)/Companies!I15)) | R19: =IF(A19="","",IF(OR($H$6=0,N19<>$H$6),"n.a.",SUMIFS(Holdings!$D$6:$D$205,Holdings!$A$6:$A$205,A19,Holdings!$H$6:$H$205,"Active",Holdings!$K$6:$K$205,1)/Companies!I15)) | S19: =IF(A19="","",IF($G$6+$H$6=0,"No ETF panel",IF(M19+N19=$G$6+$H$6,"Complete selected panel","Missing ETF pairs"))) | T19: {=IF(A19="","",IFNA(INDEX(Network!$L$14:$L$63,MATCH(A19,Network!$A$14:$A$63,0)),"n.a."))} | U19: =IF(A19="","",IF(OR(OR(COUNT(Rules!$B$45:$B$46)<>2,MIN(Rules!$B$45:$B$46)<0,ABS(SUM(Rules!$B$45:$B$46)-1)>0.000001),AND(Rules!$B$45>0,NOT(ISNUMBER(I19))),AND(Rules!$B$46>0,NOT(ISNUMBER(T19)))),"n.a.",IF(Rules!$B$45=0,0,Rules!$B$45*I19)+IF(Rules!$B$46=0,0,Rules!$B$46*T19))) | V19: =IF(A19="","",IF(OR(COUNT(Rules!$B$45:$B$46)<>2,MIN(Rules!$B$45:$B$46)<0,ABS(SUM(Rules!$B$45:$B$46)-1)>0.000001),"Check combined weights",IF(AND(Rules!$B$45>0,NOT(ISNUMBER(I19))),"Scale score unavailable",IF(AND(Rules!$B$46>0,NOT(ISNUMBER(T19))),"Network review/score unavailable","Ready"))))
A20: =IF(Companies!R16=1,Companies!A16,"") | B20: =IF(A20="","",Companies!C16) | C20: =IF(A20="","",1+COUNTIFS(Companies!$R$6:$R$55,1,Companies!$I$6:$I$55,">"&Companies!I16)) | D20: =IF(A20="","",Companies!I16/$D$6) | E20: =IF(A20="","",IF($A$6<>"Ready","n.a.",Companies!K16/$E$6)) | F20: =IF(A20="","",IF(OR($A$6<>"Ready",E20=0),"n.a.",D20/E20)) | G20: =IF(A20="","",IF($B$6<Rules!$B$12,"n.a.",100*(COUNTIFS(Companies!$R$6:$R$55,1,Companies!$I$6:$I$55,"<"&Companies!I16)+0.5*(COUNTIFS(Companies!$R$6:$R$55,1,Companies!$I$6:$I$55,Companies!I16)-1))/($B$6-1))) | H20: =IF(A20="","",IF($A$6<>"Ready","n.a.",100*(COUNTIFS(Companies!$S$6:$S$55,1,Companies!$K$6:$K$55,"<"&Companies!K16)+0.5*(COUNTIFS(Companies!$S$6:$S$55,1,Companies!$K$6:$K$55,Companies!K16)-1))/($C$6-1))) | I20: =IF(A20="","",IF($A$6<>"Ready","n.a.",Rules!$B$13*H20+Rules!$B$14*G20)) | J20: =IF(A20="","",$B$6-1) | K20: =IF(A20="","",C20-1) | L20: =IF(A20="","",IF(OR($B$6<2,$D$6<=Companies!I16),"n.a.",Companies!I16/(($D$6-Companies!I16)/($B$6-1)))) | M20: =IF(A20="","",COUNTIFS(Holdings!$A$6:$A$205,A20,Holdings!$H$6:$H$205,"Passive",Holdings!$K$6:$K$205,1)) | N20: =IF(A20="","",COUNTIFS(Holdings!$A$6:$A$205,A20,Holdings!$H$6:$H$205,"Active",Holdings!$K$6:$K$205,1)) | O20: =IF(A20="","",IF(OR($G$6=0,M20<>$G$6),"n.a.",SUMIFS(Holdings!$D$6:$D$205,Holdings!$A$6:$A$205,A20,Holdings!$H$6:$H$205,"Passive",Holdings!$K$6:$K$205,1)/$I$6)) | P20: =IF(A20="","",IF(OR($H$6=0,N20<>$H$6),"n.a.",SUMIFS(Holdings!$D$6:$D$205,Holdings!$A$6:$A$205,A20,Holdings!$H$6:$H$205,"Active",Holdings!$K$6:$K$205,1)/$J$6)) | Q20: =IF(A20="","",IF(OR($G$6=0,M20<>$G$6),"n.a.",SUMIFS(Holdings!$D$6:$D$205,Holdings!$A$6:$A$205,A20,Holdings!$H$6:$H$205,"Passive",Holdings!$K$6:$K$205,1)/Companies!I16)) | R20: =IF(A20="","",IF(OR($H$6=0,N20<>$H$6),"n.a.",SUMIFS(Holdings!$D$6:$D$205,Holdings!$A$6:$A$205,A20,Holdings!$H$6:$H$205,"Active",Holdings!$K$6:$K$205,1)/Companies!I16)) | S20: =IF(A20="","",IF($G$6+$H$6=0,"No ETF panel",IF(M20+N20=$G$6+$H$6,"Complete selected panel","Missing ETF pairs"))) | T20: {=IF(A20="","",IFNA(INDEX(Network!$L$14:$L$63,MATCH(A20,Network!$A$14:$A$63,0)),"n.a."))} | U20: =IF(A20="","",IF(OR(OR(COUNT(Rules!$B$45:$B$46)<>2,MIN(Rules!$B$45:$B$46)<0,ABS(SUM(Rules!$B$45:$B$46)-1)>0.000001),AND(Rules!$B$45>0,NOT(ISNUMBER(I20))),AND(Rules!$B$46>0,NOT(ISNUMBER(T20)))),"n.a.",IF(Rules!$B$45=0,0,Rules!$B$45*I20)+IF(Rules!$B$46=0,0,Rules!$B$46*T20))) | V20: =IF(A20="","",IF(OR(COUNT(Rules!$B$45:$B$46)<>2,MIN(Rules!$B$45:$B$46)<0,ABS(SUM(Rules!$B$45:$B$46)-1)>0.000001),"Check combined weights",IF(AND(Rules!$B$45>0,NOT(ISNUMBER(I20))),"Scale score unavailable",IF(AND(Rules!$B$46>0,NOT(ISNUMBER(T20))),"Network review/score unavailable","Ready"))))
A21: =IF(Companies!R17=1,Companies!A17,"") | B21: =IF(A21="","",Companies!C17) | C21: =IF(A21="","",1+COUNTIFS(Companies!$R$6:$R$55,1,Companies!$I$6:$I$55,">"&Companies!I17)) | D21: =IF(A21="","",Companies!I17/$D$6) | E21: =IF(A21="","",IF($A$6<>"Ready","n.a.",Companies!K17/$E$6)) | F21: =IF(A21="","",IF(OR($A$6<>"Ready",E21=0),"n.a.",D21/E21)) | G21: =IF(A21="","",IF($B$6<Rules!$B$12,"n.a.",100*(COUNTIFS(Companies!$R$6:$R$55,1,Companies!$I$6:$I$55,"<"&Companies!I17)+0.5*(COUNTIFS(Companies!$R$6:$R$55,1,Companies!$I$6:$I$55,Companies!I17)-1))/($B$6-1))) | H21: =IF(A21="","",IF($A$6<>"Ready","n.a.",100*(COUNTIFS(Companies!$S$6:$S$55,1,Companies!$K$6:$K$55,"<"&Companies!K17)+0.5*(COUNTIFS(Companies!$S$6:$S$55,1,Companies!$K$6:$K$55,Companies!K17)-1))/($C$6-1))) | I21: =IF(A21="","",IF($A$6<>"Ready","n.a.",Rules!$B$13*H21+Rules!$B$14*G21)) | J21: =IF(A21="","",$B$6-1) | K21: =IF(A21="","",C21-1) | L21: =IF(A21="","",IF(OR($B$6<2,$D$6<=Companies!I17),"n.a.",Companies!I17/(($D$6-Companies!I17)/($B$6-1)))) | M21: =IF(A21="","",COUNTIFS(Holdings!$A$6:$A$205,A21,Holdings!$H$6:$H$205,"Passive",Holdings!$K$6:$K$205,1)) | N21: =IF(A21="","",COUNTIFS(Holdings!$A$6:$A$205,A21,Holdings!$H$6:$H$205,"Active",Holdings!$K$6:$K$205,1)) | O21: =IF(A21="","",IF(OR($G$6=0,M21<>$G$6),"n.a.",SUMIFS(Holdings!$D$6:$D$205,Holdings!$A$6:$A$205,A21,Holdings!$H$6:$H$205,"Passive",Holdings!$K$6:$K$205,1)/$I$6)) | P21: =IF(A21="","",IF(OR($H$6=0,N21<>$H$6),"n.a.",SUMIFS(Holdings!$D$6:$D$205,Holdings!$A$6:$A$205,A21,Holdings!$H$6:$H$205,"Active",Holdings!$K$6:$K$205,1)/$J$6)) | Q21: =IF(A21="","",IF(OR($G$6=0,M21<>$G$6),"n.a.",SUMIFS(Holdings!$D$6:$D$205,Holdings!$A$6:$A$205,A21,Holdings!$H$6:$H$205,"Passive",Holdings!$K$6:$K$205,1)/Companies!I17)) | R21: =IF(A21="","",IF(OR($H$6=0,N21<>$H$6),"n.a.",SUMIFS(Holdings!$D$6:$D$205,Holdings!$A$6:$A$205,A21,Holdings!$H$6:$H$205,"Active",Holdings!$K$6:$K$205,1)/Companies!I17)) | S21: =IF(A21="","",IF($G$6+$H$6=0,"No ETF panel",IF(M21+N21=$G$6+$H$6,"Complete selected panel","Missing ETF pairs"))) | T21: {=IF(A21="","",IFNA(INDEX(Network!$L$14:$L$63,MATCH(A21,Network!$A$14:$A$63,0)),"n.a."))} | U21: =IF(A21="","",IF(OR(OR(COUNT(Rules!$B$45:$B$46)<>2,MIN(Rules!$B$45:$B$46)<0,ABS(SUM(Rules!$B$45:$B$46)-1)>0.000001),AND(Rules!$B$45>0,NOT(ISNUMBER(I21))),AND(Rules!$B$46>0,NOT(ISNUMBER(T21)))),"n.a.",IF(Rules!$B$45=0,0,Rules!$B$45*I21)+IF(Rules!$B$46=0,0,Rules!$B$46*T21))) | V21: =IF(A21="","",IF(OR(COUNT(Rules!$B$45:$B$46)<>2,MIN(Rules!$B$45:$B$46)<0,ABS(SUM(Rules!$B$45:$B$46)-1)>0.000001),"Check combined weights",IF(AND(Rules!$B$45>0,NOT(ISNUMBER(I21))),"Scale score unavailable",IF(AND(Rules!$B$46>0,NOT(ISNUMBER(T21))),"Network review/score unavailable","Ready"))))
... A59: =IF(Companies!R55=1,Companies!A55,"") | B59: =IF(A59="","",Companies!C55) | C59: =IF(A59="","",1+COUNTIFS(Companies!$R$6:$R$55,1,Companies!$I$6:$I$55,">"&Companies!I55)) | D59: =IF(A59="","",Companies!I55/$D$6) | E59: =IF(A59="","",IF($A$6<>"Ready","n.a.",Companies!K55/$E$6)) | F59: =IF(A59="","",IF(OR($A$6<>"Ready",E59=0),"n.a.",D59/E59)) | G59: =IF(A59="","",IF($B$6<Rules!$B$12,"n.a.",100*(COUNTIFS(Companies!$R$6:$R$55,1,Companies!$I$6:$I$55,"<"&Companies!I55)+0.5*(COUNTIFS(Companies!$R$6:$R$55,1,Companies!$I$6:$I$55,Companies!I55)-1))/($B$6-1))) | H59: =IF(A59="","",IF($A$6<>"Ready","n.a.",100*(COUNTIFS(Companies!$S$6:$S$55,1,Companies!$K$6:$K$55,"<"&Companies!K55)+0.5*(COUNTIFS(Companies!$S$6:$S$55,1,Companies!$K$6:$K$55,Companies!K55)-1))/($C$6-1))) | I59: =IF(A59="","",IF($A$6<>"Ready","n.a.",Rules!$B$13*H59+Rules!$B$14*G59)) | J59: =IF(A59="","",$B$6-1) | K59: =IF(A59="","",C59-1) | L59: =IF(A59="","",IF(OR($B$6<2,$D$6<=Companies!I55),"n.a.",Companies!I55/(($D$6-Companies!I55)/($B$6-1)))) | M59: =IF(A59="","",COUNTIFS(Holdings!$A$6:$A$205,A59,Holdings!$H$6:$H$205,"Passive",Holdings!$K$6:$K$205,1)) | N59: =IF(A59="","",COUNTIFS(Holdings!$A$6:$A$205,A59,Holdings!$H$6:$H$205,"Active",Holdings!$K$6:$K$205,1)) | O59: =IF(A59="","",IF(OR($G$6=0,M59<>$G$6),"n.a.",SUMIFS(Holdings!$D$6:$D$205,Holdings!$A$6:$A$205,A59,Holdings!$H$6:$H$205,"Passive",Holdings!$K$6:$K$205,1)/$I$6)) | P59: =IF(A59="","",IF(OR($H$6=0,N59<>$H$6),"n.a.",SUMIFS(Holdings!$D$6:$D$205,Holdings!$A$6:$A$205,A59,Holdings!$H$6:$H$205,"Active",Holdings!$K$6:$K$205,1)/$J$6)) | Q59: =IF(A59="","",IF(OR($G$6=0,M59<>$G$6),"n.a.",SUMIFS(Holdings!$D$6:$D$205,Holdings!$A$6:$A$205,A59,Holdings!$H$6:$H$205,"Passive",Holdings!$K$6:$K$205,1)/Companies!I55)) | R59: =IF(A59="","",IF(OR($H$6=0,N59<>$H$6),"n.a.",SUMIFS(Holdings!$D$6:$D$205,Holdings!$A$6:$A$205,A59,Holdings!$H$6:$H$205,"Active",Holdings!$K$6:$K$205,1)/Companies!I55)) | S59: =IF(A59="","",IF($G$6+$H$6=0,"No ETF panel",IF(M59+N59=$G$6+$H$6,"Complete selected panel","Missing ETF pairs"))) | T59: {=IF(A59="","",IFNA(INDEX(Network!$L$14:$L$63,MATCH(A59,Network!$A$14:$A$63,0)),"n.a."))} | U59: =IF(A59="","",IF(OR(OR(COUNT(Rules!$B$45:$B$46)<>2,MIN(Rules!$B$45:$B$46)<0,ABS(SUM(Rules!$B$45:$B$46)-1)>0.000001),AND(Rules!$B$45>0,NOT(ISNUMBER(I59))),AND(Rules!$B$46>0,NOT(ISNUMBER(T59)))),"n.a.",IF(Rules!$B$45=0,0,Rules!$B$45*I59)+IF(Rules!$B$46=0,0,Rules!$B$46*T59))) | V59: =IF(A59="","",IF(OR(COUNT(Rules!$B$45:$B$46)<>2,MIN(Rules!$B$45:$B$46)<0,ABS(SUM(Rules!$B$45:$B$46)-1)>0.000001),"Check combined weights",IF(AND(Rules!$B$45>0,NOT(ISNUMBER(I59))),"Scale score unavailable",IF(AND(Rules!$B$46>0,NOT(ISNUMBER(T59))),"Network review/score unavailable","Ready"))))

Sheet Network
A2: Client and partner network strength
A3: Draft relative network score. Complete the dated review for each issuer; only verified public-company ties >= USD10bn qualify.
A4: Research snapshot | B4: =Rules!B6 -> 46298 | F4: Network component | G4: Weight
A5: Cap-eligible issuers | B5: =COUNTIF(Companies!$R$6:$R$55,1) -> 0 | F5: Breadth | G5: =Rules!B43 -> 0.5
A6: Scorable reviews | B6: =COUNTIF($P$14:$P$63,1) -> 0 | F6: Median cap | G6: =Rules!B44 -> 0.5
A7: Review coverage | B7: =IF(B5=0,"n.a.",B6/B5) -> n.a.
A8: Network status | B8: =IF(Rules!B15<>"Yes","Confirm issuer universe",IF(OR(COUNT(G5:G6)<>2,MIN(G5:G6)<0,ABS(SUM(G5:G6)-1)>0.000001),"Check network weights",IF(B10>0,"Assign relationship issuer IDs",IF(B6<B9,"Too few reviewed companies","Ready")))) -> Confirm issuer universe | F8: Competitive blend | G8: Weight
A9: Minimum comparison count | B9: =Rules!B12 -> 3 | F9: Scale | G9: =Rules!B45 -> 0.5
A10: Orphan included records | B10: =COUNTIFS(Relationships!$L$6:$L$205,"Yes",Relationships!$M$6:$M$205,0,Relationships!$E$6:$E$205,"Active")+COUNTIFS(Relationships!$L$6:$L$205,"Yes",Relationships!$M$6:$M$205,0,Relationships!$E$6:$E$205,"Unclear")+COUNTIFS(Relationships!$L$6:$L$205,"Yes",Relationships!$M$6:$M$205,0,Relationships!$E$6:$E$205,"") -> 0 | F10: Network | G10: =Rules!B46 -> 0.5
F11: Weights are draft assumptions.
F12: Higher scores mean broader/larger disclosed networks.
A13: Issuer ID | B13: Company | C13: Review complete? | D13: Review date | E13: Review source / scope log | F13: Qualifying counterparties | G13: Clients | H13: Partners | I13: Median counterparty cap USD bn | J13: Breadth score /100 | K13: Size score /100 | L13: Network score /100 | M13: Network rank | N13: Unresolved included records | O13: Row status | P13: Scorable | Q13: Subject cap eligible | R13: Issuer ID count | S13: Scorable median cap
B14: {=IF(A14="","",IF(COUNTIF(Companies!$A$6:$A$55,A14)<>1,"n.a.",INDEX(Companies!$C$6:$C$55,MATCH(A14,Companies!$A$6:$A$55,0))))} | F14: =IF(A14="","",COUNTIFS(Relationships!$A$6:$A$205,A14,Relationships!$U$6:$U$205,1)) | G14: =IF(A14="","",COUNTIFS(Relationships!$A$6:$A$205,A14,Relationships!$U$6:$U$205,1,Relationships!$C$6:$C$205,"Client")+COUNTIFS(Relationships!$A$6:$A$205,A14,Relationships!$U$6:$U$205,1,Relationships!$C$6:$C$205,"Client and partner")) | H14: =IF(A14="","",COUNTIFS(Relationships!$A$6:$A$205,A14,Relationships!$U$6:$U$205,1,Relationships!$C$6:$C$205,"Partner")+COUNTIFS(Relationships!$A$6:$A$205,A14,Relationships!$U$6:$U$205,1,Relationships!$C$6:$C$205,"Client and partner")) | I14: =IFERROR(__xludf.DUMMYFUNCTION("IF(A14="""","""",IF(F14=0,""n.a."",MEDIAN(FILTER(Relationships!$Q$6:$Q$205,Relationships!$A$6:$A$205=A14,Relationships!$U$6:$U$205=1))))"),"") | J14: =IF(A14="","",IF(OR(P14<>1,$B$8<>"Ready"),"n.a.",IF(F14=0,0,100*(COUNTIFS($P$14:$P$63,1,$F$14:$F$63,"<"&F14)+0.5*(COUNTIFS($P$14:$P$63,1,$F$14:$F$63,F14)-1))/($B$6-1)))) | K14: =IF(A14="","",IF(OR(P14<>1,$B$8<>"Ready"),"n.a.",IF(F14=0,0,100*(COUNTIFS($P$14:$P$63,1,$S$14:$S$63,"<"&I14)+0.5*(COUNTIFS($P$14:$P$63,1,$S$14:$S$63,I14)-1))/($B$6-1)))) | L14: =IF(A14="","",IF(OR(P14<>1,$B$8<>"Ready"),"n.a.",$G$5*J14+$G$6*K14)) | M14: =IF(A14="","",IF(NOT(ISNUMBER(L14)),"n.a.",1+COUNTIFS($P$14:$P$63,1,$L$14:$L$63,">"&L14))) | N14: =IF(A14="","",COUNTIFS(Relationships!$A$6:$A$205,A14,Relationships!$V$6:$V$205,1)) | O14: =IF(A14="","",IF(Q14<>1,"Outside cap universe",IF(R14<>1,"Duplicate network issuer",IF(C14<>"Yes","Review incomplete",IF(OR(NOT(ISNUMBER(D14)),D14>Rules!$B$6,Rules!$B$6-D14>Rules!$B$42,E14=""),"Check review date/log",IF(N14>0,"Resolve included records",IF($B$8<>"Ready",$B$8,IF(F14=0,"Reviewed: no qualifying ties","Ranked")))))))) | P14: =IF(A14="",0,IF(AND(Q14=1,R14=1,C14="Yes",ISNUMBER(D14),D14<=Rules!$B$6,Rules!$B$6-D14<=Rules!$B$42,E14<>"",N14=0),1,0)) -> 0 | Q14: {=IF(A14="",0,IF(COUNTIF(Companies!$A$6:$A$55,A14)<>1,0,IF(AND(INDEX(Companies!$R$6:$R$55,MATCH(A14,Companies!$A$6:$A$55,0))=1,INDEX(Companies!$I$6:$I$55,MATCH(A14,Companies!$A$6:$A$55,0))>=MAX(10,Rules!$B$22)),1,0)))} -> 0 | R14: =IF(A14="","",COUNTIF($A$14:$A$63,A14)) | S14: =IF(P14<>1,"",IF(F14=0,0,I14))
B15: {=IF(A15="","",IF(COUNTIF(Companies!$A$6:$A$55,A15)<>1,"n.a.",INDEX(Companies!$C$6:$C$55,MATCH(A15,Companies!$A$6:$A$55,0))))} | F15: =IF(A15="","",COUNTIFS(Relationships!$A$6:$A$205,A15,Relationships!$U$6:$U$205,1)) | G15: =IF(A15="","",COUNTIFS(Relationships!$A$6:$A$205,A15,Relationships!$U$6:$U$205,1,Relationships!$C$6:$C$205,"Client")+COUNTIFS(Relationships!$A$6:$A$205,A15,Relationships!$U$6:$U$205,1,Relationships!$C$6:$C$205,"Client and partner")) | H15: =IF(A15="","",COUNTIFS(Relationships!$A$6:$A$205,A15,Relationships!$U$6:$U$205,1,Relationships!$C$6:$C$205,"Partner")+COUNTIFS(Relationships!$A$6:$A$205,A15,Relationships!$U$6:$U$205,1,Relationships!$C$6:$C$205,"Client and partner")) | I15: =IFERROR(__xludf.DUMMYFUNCTION("IF(A15="""","""",IF(F15=0,""n.a."",MEDIAN(FILTER(Relationships!$Q$6:$Q$205,Relationships!$A$6:$A$205=A15,Relationships!$U$6:$U$205=1))))"),"") | J15: =IF(A15="","",IF(OR(P15<>1,$B$8<>"Ready"),"n.a.",IF(F15=0,0,100*(COUNTIFS($P$14:$P$63,1,$F$14:$F$63,"<"&F15)+0.5*(COUNTIFS($P$14:$P$63,1,$F$14:$F$63,F15)-1))/($B$6-1)))) | K15: =IF(A15="","",IF(OR(P15<>1,$B$8<>"Ready"),"n.a.",IF(F15=0,0,100*(COUNTIFS($P$14:$P$63,1,$S$14:$S$63,"<"&I15)+0.5*(COUNTIFS($P$14:$P$63,1,$S$14:$S$63,I15)-1))/($B$6-1)))) | L15: =IF(A15="","",IF(OR(P15<>1,$B$8<>"Ready"),"n.a.",$G$5*J15+$G$6*K15)) | M15: =IF(A15="","",IF(NOT(ISNUMBER(L15)),"n.a.",1+COUNTIFS($P$14:$P$63,1,$L$14:$L$63,">"&L15))) | N15: =IF(A15="","",COUNTIFS(Relationships!$A$6:$A$205,A15,Relationships!$V$6:$V$205,1)) | O15: =IF(A15="","",IF(Q15<>1,"Outside cap universe",IF(R15<>1,"Duplicate network issuer",IF(C15<>"Yes","Review incomplete",IF(OR(NOT(ISNUMBER(D15)),D15>Rules!$B$6,Rules!$B$6-D15>Rules!$B$42,E15=""),"Check review date/log",IF(N15>0,"Resolve included records",IF($B$8<>"Ready",$B$8,IF(F15=0,"Reviewed: no qualifying ties","Ranked")))))))) | P15: =IF(A15="",0,IF(AND(Q15=1,R15=1,C15="Yes",ISNUMBER(D15),D15<=Rules!$B$6,Rules!$B$6-D15<=Rules!$B$42,E15<>"",N15=0),1,0)) -> 0 | Q15: {=IF(A15="",0,IF(COUNTIF(Companies!$A$6:$A$55,A15)<>1,0,IF(AND(INDEX(Companies!$R$6:$R$55,MATCH(A15,Companies!$A$6:$A$55,0))=1,INDEX(Companies!$I$6:$I$55,MATCH(A15,Companies!$A$6:$A$55,0))>=MAX(10,Rules!$B$22)),1,0)))} -> 0 | R15: =IF(A15="","",COUNTIF($A$14:$A$63,A15)) | S15: =IF(P15<>1,"",IF(F15=0,0,I15))
B16: {=IF(A16="","",IF(COUNTIF(Companies!$A$6:$A$55,A16)<>1,"n.a.",INDEX(Companies!$C$6:$C$55,MATCH(A16,Companies!$A$6:$A$55,0))))} | F16: =IF(A16="","",COUNTIFS(Relationships!$A$6:$A$205,A16,Relationships!$U$6:$U$205,1)) | G16: =IF(A16="","",COUNTIFS(Relationships!$A$6:$A$205,A16,Relationships!$U$6:$U$205,1,Relationships!$C$6:$C$205,"Client")+COUNTIFS(Relationships!$A$6:$A$205,A16,Relationships!$U$6:$U$205,1,Relationships!$C$6:$C$205,"Client and partner")) | H16: =IF(A16="","",COUNTIFS(Relationships!$A$6:$A$205,A16,Relationships!$U$6:$U$205,1,Relationships!$C$6:$C$205,"Partner")+COUNTIFS(Relationships!$A$6:$A$205,A16,Relationships!$U$6:$U$205,1,Relationships!$C$6:$C$205,"Client and partner")) | I16: =IFERROR(__xludf.DUMMYFUNCTION("IF(A16="""","""",IF(F16=0,""n.a."",MEDIAN(FILTER(Relationships!$Q$6:$Q$205,Relationships!$A$6:$A$205=A16,Relationships!$U$6:$U$205=1))))"),"") | J16: =IF(A16="","",IF(OR(P16<>1,$B$8<>"Ready"),"n.a.",IF(F16=0,0,100*(COUNTIFS($P$14:$P$63,1,$F$14:$F$63,"<"&F16)+0.5*(COUNTIFS($P$14:$P$63,1,$F$14:$F$63,F16)-1))/($B$6-1)))) | K16: =IF(A16="","",IF(OR(P16<>1,$B$8<>"Ready"),"n.a.",IF(F16=0,0,100*(COUNTIFS($P$14:$P$63,1,$S$14:$S$63,"<"&I16)+0.5*(COUNTIFS($P$14:$P$63,1,$S$14:$S$63,I16)-1))/($B$6-1)))) | L16: =IF(A16="","",IF(OR(P16<>1,$B$8<>"Ready"),"n.a.",$G$5*J16+$G$6*K16)) | M16: =IF(A16="","",IF(NOT(ISNUMBER(L16)),"n.a.",1+COUNTIFS($P$14:$P$63,1,$L$14:$L$63,">"&L16))) | N16: =IF(A16="","",COUNTIFS(Relationships!$A$6:$A$205,A16,Relationships!$V$6:$V$205,1)) | O16: =IF(A16="","",IF(Q16<>1,"Outside cap universe",IF(R16<>1,"Duplicate network issuer",IF(C16<>"Yes","Review incomplete",IF(OR(NOT(ISNUMBER(D16)),D16>Rules!$B$6,Rules!$B$6-D16>Rules!$B$42,E16=""),"Check review date/log",IF(N16>0,"Resolve included records",IF($B$8<>"Ready",$B$8,IF(F16=0,"Reviewed: no qualifying ties","Ranked")))))))) | P16: =IF(A16="",0,IF(AND(Q16=1,R16=1,C16="Yes",ISNUMBER(D16),D16<=Rules!$B$6,Rules!$B$6-D16<=Rules!$B$42,E16<>"",N16=0),1,0)) -> 0 | Q16: {=IF(A16="",0,IF(COUNTIF(Companies!$A$6:$A$55,A16)<>1,0,IF(AND(INDEX(Companies!$R$6:$R$55,MATCH(A16,Companies!$A$6:$A$55,0))=1,INDEX(Companies!$I$6:$I$55,MATCH(A16,Companies!$A$6:$A$55,0))>=MAX(10,Rules!$B$22)),1,0)))} -> 0 | R16: =IF(A16="","",COUNTIF($A$14:$A$63,A16)) | S16: =IF(P16<>1,"",IF(F16=0,0,I16))
B17: {=IF(A17="","",IF(COUNTIF(Companies!$A$6:$A$55,A17)<>1,"n.a.",INDEX(Companies!$C$6:$C$55,MATCH(A17,Companies!$A$6:$A$55,0))))} | F17: =IF(A17="","",COUNTIFS(Relationships!$A$6:$A$205,A17,Relationships!$U$6:$U$205,1)) | G17: =IF(A17="","",COUNTIFS(Relationships!$A$6:$A$205,A17,Relationships!$U$6:$U$205,1,Relationships!$C$6:$C$205,"Client")+COUNTIFS(Relationships!$A$6:$A$205,A17,Relationships!$U$6:$U$205,1,Relationships!$C$6:$C$205,"Client and partner")) | H17: =IF(A17="","",COUNTIFS(Relationships!$A$6:$A$205,A17,Relationships!$U$6:$U$205,1,Relationships!$C$6:$C$205,"Partner")+COUNTIFS(Relationships!$A$6:$A$205,A17,Relationships!$U$6:$U$205,1,Relationships!$C$6:$C$205,"Client and partner")) | I17: =IFERROR(__xludf.DUMMYFUNCTION("IF(A17="""","""",IF(F17=0,""n.a."",MEDIAN(FILTER(Relationships!$Q$6:$Q$205,Relationships!$A$6:$A$205=A17,Relationships!$U$6:$U$205=1))))"),"") | J17: =IF(A17="","",IF(OR(P17<>1,$B$8<>"Ready"),"n.a.",IF(F17=0,0,100*(COUNTIFS($P$14:$P$63,1,$F$14:$F$63,"<"&F17)+0.5*(COUNTIFS($P$14:$P$63,1,$F$14:$F$63,F17)-1))/($B$6-1)))) | K17: =IF(A17="","",IF(OR(P17<>1,$B$8<>"Ready"),"n.a.",IF(F17=0,0,100*(COUNTIFS($P$14:$P$63,1,$S$14:$S$63,"<"&I17)+0.5*(COUNTIFS($P$14:$P$63,1,$S$14:$S$63,I17)-1))/($B$6-1)))) | L17: =IF(A17="","",IF(OR(P17<>1,$B$8<>"Ready"),"n.a.",$G$5*J17+$G$6*K17)) | M17: =IF(A17="","",IF(NOT(ISNUMBER(L17)),"n.a.",1+COUNTIFS($P$14:$P$63,1,$L$14:$L$63,">"&L17))) | N17: =IF(A17="","",COUNTIFS(Relationships!$A$6:$A$205,A17,Relationships!$V$6:$V$205,1)) | O17: =IF(A17="","",IF(Q17<>1,"Outside cap universe",IF(R17<>1,"Duplicate network issuer",IF(C17<>"Yes","Review incomplete",IF(OR(NOT(ISNUMBER(D17)),D17>Rules!$B$6,Rules!$B$6-D17>Rules!$B$42,E17=""),"Check review date/log",IF(N17>0,"Resolve included records",IF($B$8<>"Ready",$B$8,IF(F17=0,"Reviewed: no qualifying ties","Ranked")))))))) | P17: =IF(A17="",0,IF(AND(Q17=1,R17=1,C17="Yes",ISNUMBER(D17),D17<=Rules!$B$6,Rules!$B$6-D17<=Rules!$B$42,E17<>"",N17=0),1,0)) -> 0 | Q17: {=IF(A17="",0,IF(COUNTIF(Companies!$A$6:$A$55,A17)<>1,0,IF(AND(INDEX(Companies!$R$6:$R$55,MATCH(A17,Companies!$A$6:$A$55,0))=1,INDEX(Companies!$I$6:$I$55,MATCH(A17,Companies!$A$6:$A$55,0))>=MAX(10,Rules!$B$22)),1,0)))} -> 0 | R17: =IF(A17="","",COUNTIF($A$14:$A$63,A17)) | S17: =IF(P17<>1,"",IF(F17=0,0,I17))
B18: {=IF(A18="","",IF(COUNTIF(Companies!$A$6:$A$55,A18)<>1,"n.a.",INDEX(Companies!$C$6:$C$55,MATCH(A18,Companies!$A$6:$A$55,0))))} | F18: =IF(A18="","",COUNTIFS(Relationships!$A$6:$A$205,A18,Relationships!$U$6:$U$205,1)) | G18: =IF(A18="","",COUNTIFS(Relationships!$A$6:$A$205,A18,Relationships!$U$6:$U$205,1,Relationships!$C$6:$C$205,"Client")+COUNTIFS(Relationships!$A$6:$A$205,A18,Relationships!$U$6:$U$205,1,Relationships!$C$6:$C$205,"Client and partner")) | H18: =IF(A18="","",COUNTIFS(Relationships!$A$6:$A$205,A18,Relationships!$U$6:$U$205,1,Relationships!$C$6:$C$205,"Partner")+COUNTIFS(Relationships!$A$6:$A$205,A18,Relationships!$U$6:$U$205,1,Relationships!$C$6:$C$205,"Client and partner")) | I18: =IFERROR(__xludf.DUMMYFUNCTION("IF(A18="""","""",IF(F18=0,""n.a."",MEDIAN(FILTER(Relationships!$Q$6:$Q$205,Relationships!$A$6:$A$205=A18,Relationships!$U$6:$U$205=1))))"),"") | J18: =IF(A18="","",IF(OR(P18<>1,$B$8<>"Ready"),"n.a.",IF(F18=0,0,100*(COUNTIFS($P$14:$P$63,1,$F$14:$F$63,"<"&F18)+0.5*(COUNTIFS($P$14:$P$63,1,$F$14:$F$63,F18)-1))/($B$6-1)))) | K18: =IF(A18="","",IF(OR(P18<>1,$B$8<>"Ready"),"n.a.",IF(F18=0,0,100*(COUNTIFS($P$14:$P$63,1,$S$14:$S$63,"<"&I18)+0.5*(COUNTIFS($P$14:$P$63,1,$S$14:$S$63,I18)-1))/($B$6-1)))) | L18: =IF(A18="","",IF(OR(P18<>1,$B$8<>"Ready"),"n.a.",$G$5*J18+$G$6*K18)) | M18: =IF(A18="","",IF(NOT(ISNUMBER(L18)),"n.a.",1+COUNTIFS($P$14:$P$63,1,$L$14:$L$63,">"&L18))) | N18: =IF(A18="","",COUNTIFS(Relationships!$A$6:$A$205,A18,Relationships!$V$6:$V$205,1)) | O18: =IF(A18="","",IF(Q18<>1,"Outside cap universe",IF(R18<>1,"Duplicate network issuer",IF(C18<>"Yes","Review incomplete",IF(OR(NOT(ISNUMBER(D18)),D18>Rules!$B$6,Rules!$B$6-D18>Rules!$B$42,E18=""),"Check review date/log",IF(N18>0,"Resolve included records",IF($B$8<>"Ready",$B$8,IF(F18=0,"Reviewed: no qualifying ties","Ranked")))))))) | P18: =IF(A18="",0,IF(AND(Q18=1,R18=1,C18="Yes",ISNUMBER(D18),D18<=Rules!$B$6,Rules!$B$6-D18<=Rules!$B$42,E18<>"",N18=0),1,0)) -> 0 | Q18: {=IF(A18="",0,IF(COUNTIF(Companies!$A$6:$A$55,A18)<>1,0,IF(AND(INDEX(Companies!$R$6:$R$55,MATCH(A18,Companies!$A$6:$A$55,0))=1,INDEX(Companies!$I$6:$I$55,MATCH(A18,Companies!$A$6:$A$55,0))>=MAX(10,Rules!$B$22)),1,0)))} -> 0 | R18: =IF(A18="","",COUNTIF($A$14:$A$63,A18)) | S18: =IF(P18<>1,"",IF(F18=0,0,I18))
B19: {=IF(A19="","",IF(COUNTIF(Companies!$A$6:$A$55,A19)<>1,"n.a.",INDEX(Companies!$C$6:$C$55,MATCH(A19,Companies!$A$6:$A$55,0))))} | F19: =IF(A19="","",COUNTIFS(Relationships!$A$6:$A$205,A19,Relationships!$U$6:$U$205,1)) | G19: =IF(A19="","",COUNTIFS(Relationships!$A$6:$A$205,A19,Relationships!$U$6:$U$205,1,Relationships!$C$6:$C$205,"Client")+COUNTIFS(Relationships!$A$6:$A$205,A19,Relationships!$U$6:$U$205,1,Relationships!$C$6:$C$205,"Client and partner")) | H19: =IF(A19="","",COUNTIFS(Relationships!$A$6:$A$205,A19,Relationships!$U$6:$U$205,1,Relationships!$C$6:$C$205,"Partner")+COUNTIFS(Relationships!$A$6:$A$205,A19,Relationships!$U$6:$U$205,1,Relationships!$C$6:$C$205,"Client and partner")) | I19: =IFERROR(__xludf.DUMMYFUNCTION("IF(A19="""","""",IF(F19=0,""n.a."",MEDIAN(FILTER(Relationships!$Q$6:$Q$205,Relationships!$A$6:$A$205=A19,Relationships!$U$6:$U$205=1))))"),"") | J19: =IF(A19="","",IF(OR(P19<>1,$B$8<>"Ready"),"n.a.",IF(F19=0,0,100*(COUNTIFS($P$14:$P$63,1,$F$14:$F$63,"<"&F19)+0.5*(COUNTIFS($P$14:$P$63,1,$F$14:$F$63,F19)-1))/($B$6-1)))) | K19: =IF(A19="","",IF(OR(P19<>1,$B$8<>"Ready"),"n.a.",IF(F19=0,0,100*(COUNTIFS($P$14:$P$63,1,$S$14:$S$63,"<"&I19)+0.5*(COUNTIFS($P$14:$P$63,1,$S$14:$S$63,I19)-1))/($B$6-1)))) | L19: =IF(A19="","",IF(OR(P19<>1,$B$8<>"Ready"),"n.a.",$G$5*J19+$G$6*K19)) | M19: =IF(A19="","",IF(NOT(ISNUMBER(L19)),"n.a.",1+COUNTIFS($P$14:$P$63,1,$L$14:$L$63,">"&L19))) | N19: =IF(A19="","",COUNTIFS(Relationships!$A$6:$A$205,A19,Relationships!$V$6:$V$205,1)) | O19: =IF(A19="","",IF(Q19<>1,"Outside cap universe",IF(R19<>1,"Duplicate network issuer",IF(C19<>"Yes","Review incomplete",IF(OR(NOT(ISNUMBER(D19)),D19>Rules!$B$6,Rules!$B$6-D19>Rules!$B$42,E19=""),"Check review date/log",IF(N19>0,"Resolve included records",IF($B$8<>"Ready",$B$8,IF(F19=0,"Reviewed: no qualifying ties","Ranked")))))))) | P19: =IF(A19="",0,IF(AND(Q19=1,R19=1,C19="Yes",ISNUMBER(D19),D19<=Rules!$B$6,Rules!$B$6-D19<=Rules!$B$42,E19<>"",N19=0),1,0)) -> 0 | Q19: {=IF(A19="",0,IF(COUNTIF(Companies!$A$6:$A$55,A19)<>1,0,IF(AND(INDEX(Companies!$R$6:$R$55,MATCH(A19,Companies!$A$6:$A$55,0))=1,INDEX(Companies!$I$6:$I$55,MATCH(A19,Companies!$A$6:$A$55,0))>=MAX(10,Rules!$B$22)),1,0)))} -> 0 | R19: =IF(A19="","",COUNTIF($A$14:$A$63,A19)) | S19: =IF(P19<>1,"",IF(F19=0,0,I19))
B20: {=IF(A20="","",IF(COUNTIF(Companies!$A$6:$A$55,A20)<>1,"n.a.",INDEX(Companies!$C$6:$C$55,MATCH(A20,Companies!$A$6:$A$55,0))))} | F20: =IF(A20="","",COUNTIFS(Relationships!$A$6:$A$205,A20,Relationships!$U$6:$U$205,1)) | G20: =IF(A20="","",COUNTIFS(Relationships!$A$6:$A$205,A20,Relationships!$U$6:$U$205,1,Relationships!$C$6:$C$205,"Client")+COUNTIFS(Relationships!$A$6:$A$205,A20,Relationships!$U$6:$U$205,1,Relationships!$C$6:$C$205,"Client and partner")) | H20: =IF(A20="","",COUNTIFS(Relationships!$A$6:$A$205,A20,Relationships!$U$6:$U$205,1,Relationships!$C$6:$C$205,"Partner")+COUNTIFS(Relationships!$A$6:$A$205,A20,Relationships!$U$6:$U$205,1,Relationships!$C$6:$C$205,"Client and partner")) | I20: =IFERROR(__xludf.DUMMYFUNCTION("IF(A20="""","""",IF(F20=0,""n.a."",MEDIAN(FILTER(Relationships!$Q$6:$Q$205,Relationships!$A$6:$A$205=A20,Relationships!$U$6:$U$205=1))))"),"") | J20: =IF(A20="","",IF(OR(P20<>1,$B$8<>"Ready"),"n.a.",IF(F20=0,0,100*(COUNTIFS($P$14:$P$63,1,$F$14:$F$63,"<"&F20)+0.5*(COUNTIFS($P$14:$P$63,1,$F$14:$F$63,F20)-1))/($B$6-1)))) | K20: =IF(A20="","",IF(OR(P20<>1,$B$8<>"Ready"),"n.a.",IF(F20=0,0,100*(COUNTIFS($P$14:$P$63,1,$S$14:$S$63,"<"&I20)+0.5*(COUNTIFS($P$14:$P$63,1,$S$14:$S$63,I20)-1))/($B$6-1)))) | L20: =IF(A20="","",IF(OR(P20<>1,$B$8<>"Ready"),"n.a.",$G$5*J20+$G$6*K20)) | M20: =IF(A20="","",IF(NOT(ISNUMBER(L20)),"n.a.",1+COUNTIFS($P$14:$P$63,1,$L$14:$L$63,">"&L20))) | N20: =IF(A20="","",COUNTIFS(Relationships!$A$6:$A$205,A20,Relationships!$V$6:$V$205,1)) | O20: =IF(A20="","",IF(Q20<>1,"Outside cap universe",IF(R20<>1,"Duplicate network issuer",IF(C20<>"Yes","Review incomplete",IF(OR(NOT(ISNUMBER(D20)),D20>Rules!$B$6,Rules!$B$6-D20>Rules!$B$42,E20=""),"Check review date/log",IF(N20>0,"Resolve included records",IF($B$8<>"Ready",$B$8,IF(F20=0,"Reviewed: no qualifying ties","Ranked")))))))) | P20: =IF(A20="",0,IF(AND(Q20=1,R20=1,C20="Yes",ISNUMBER(D20),D20<=Rules!$B$6,Rules!$B$6-D20<=Rules!$B$42,E20<>"",N20=0),1,0)) -> 0 | Q20: {=IF(A20="",0,IF(COUNTIF(Companies!$A$6:$A$55,A20)<>1,0,IF(AND(INDEX(Companies!$R$6:$R$55,MATCH(A20,Companies!$A$6:$A$55,0))=1,INDEX(Companies!$I$6:$I$55,MATCH(A20,Companies!$A$6:$A$55,0))>=MAX(10,Rules!$B$22)),1,0)))} -> 0 | R20: =IF(A20="","",COUNTIF($A$14:$A$63,A20)) | S20: =IF(P20<>1,"",IF(F20=0,0,I20))
B21: {=IF(A21="","",IF(COUNTIF(Companies!$A$6:$A$55,A21)<>1,"n.a.",INDEX(Companies!$C$6:$C$55,MATCH(A21,Companies!$A$6:$A$55,0))))} | F21: =IF(A21="","",COUNTIFS(Relationships!$A$6:$A$205,A21,Relationships!$U$6:$U$205,1)) | G21: =IF(A21="","",COUNTIFS(Relationships!$A$6:$A$205,A21,Relationships!$U$6:$U$205,1,Relationships!$C$6:$C$205,"Client")+COUNTIFS(Relationships!$A$6:$A$205,A21,Relationships!$U$6:$U$205,1,Relationships!$C$6:$C$205,"Client and partner")) | H21: =IF(A21="","",COUNTIFS(Relationships!$A$6:$A$205,A21,Relationships!$U$6:$U$205,1,Relationships!$C$6:$C$205,"Partner")+COUNTIFS(Relationships!$A$6:$A$205,A21,Relationships!$U$6:$U$205,1,Relationships!$C$6:$C$205,"Client and partner")) | I21: =IFERROR(__xludf.DUMMYFUNCTION("IF(A21="""","""",IF(F21=0,""n.a."",MEDIAN(FILTER(Relationships!$Q$6:$Q$205,Relationships!$A$6:$A$205=A21,Relationships!$U$6:$U$205=1))))"),"") | J21: =IF(A21="","",IF(OR(P21<>1,$B$8<>"Ready"),"n.a.",IF(F21=0,0,100*(COUNTIFS($P$14:$P$63,1,$F$14:$F$63,"<"&F21)+0.5*(COUNTIFS($P$14:$P$63,1,$F$14:$F$63,F21)-1))/($B$6-1)))) | K21: =IF(A21="","",IF(OR(P21<>1,$B$8<>"Ready"),"n.a.",IF(F21=0,0,100*(COUNTIFS($P$14:$P$63,1,$S$14:$S$63,"<"&I21)+0.5*(COUNTIFS($P$14:$P$63,1,$S$14:$S$63,I21)-1))/($B$6-1)))) | L21: =IF(A21="","",IF(OR(P21<>1,$B$8<>"Ready"),"n.a.",$G$5*J21+$G$6*K21)) | M21: =IF(A21="","",IF(NOT(ISNUMBER(L21)),"n.a.",1+COUNTIFS($P$14:$P$63,1,$L$14:$L$63,">"&L21))) | N21: =IF(A21="","",COUNTIFS(Relationships!$A$6:$A$205,A21,Relationships!$V$6:$V$205,1)) | O21: =IF(A21="","",IF(Q21<>1,"Outside cap universe",IF(R21<>1,"Duplicate network issuer",IF(C21<>"Yes","Review incomplete",IF(OR(NOT(ISNUMBER(D21)),D21>Rules!$B$6,Rules!$B$6-D21>Rules!$B$42,E21=""),"Check review date/log",IF(N21>0,"Resolve included records",IF($B$8<>"Ready",$B$8,IF(F21=0,"Reviewed: no qualifying ties","Ranked")))))))) | P21: =IF(A21="",0,IF(AND(Q21=1,R21=1,C21="Yes",ISNUMBER(D21),D21<=Rules!$B$6,Rules!$B$6-D21<=Rules!$B$42,E21<>"",N21=0),1,0)) -> 0 | Q21: {=IF(A21="",0,IF(COUNTIF(Companies!$A$6:$A$55,A21)<>1,0,IF(AND(INDEX(Companies!$R$6:$R$55,MATCH(A21,Companies!$A$6:$A$55,0))=1,INDEX(Companies!$I$6:$I$55,MATCH(A21,Companies!$A$6:$A$55,0))>=MAX(10,Rules!$B$22)),1,0)))} -> 0 | R21: =IF(A21="","",COUNTIF($A$14:$A$63,A21)) | S21: =IF(P21<>1,"",IF(F21=0,0,I21))
B22: {=IF(A22="","",IF(COUNTIF(Companies!$A$6:$A$55,A22)<>1,"n.a.",INDEX(Companies!$C$6:$C$55,MATCH(A22,Companies!$A$6:$A$55,0))))} | F22: =IF(A22="","",COUNTIFS(Relationships!$A$6:$A$205,A22,Relationships!$U$6:$U$205,1)) | G22: =IF(A22="","",COUNTIFS(Relationships!$A$6:$A$205,A22,Relationships!$U$6:$U$205,1,Relationships!$C$6:$C$205,"Client")+COUNTIFS(Relationships!$A$6:$A$205,A22,Relationships!$U$6:$U$205,1,Relationships!$C$6:$C$205,"Client and partner")) | H22: =IF(A22="","",COUNTIFS(Relationships!$A$6:$A$205,A22,Relationships!$U$6:$U$205,1,Relationships!$C$6:$C$205,"Partner")+COUNTIFS(Relationships!$A$6:$A$205,A22,Relationships!$U$6:$U$205,1,Relationships!$C$6:$C$205,"Client and partner")) | I22: =IFERROR(__xludf.DUMMYFUNCTION("IF(A22="""","""",IF(F22=0,""n.a."",MEDIAN(FILTER(Relationships!$Q$6:$Q$205,Relationships!$A$6:$A$205=A22,Relationships!$U$6:$U$205=1))))"),"") | J22: =IF(A22="","",IF(OR(P22<>1,$B$8<>"Ready"),"n.a.",IF(F22=0,0,100*(COUNTIFS($P$14:$P$63,1,$F$14:$F$63,"<"&F22)+0.5*(COUNTIFS($P$14:$P$63,1,$F$14:$F$63,F22)-1))/($B$6-1)))) | K22: =IF(A22="","",IF(OR(P22<>1,$B$8<>"Ready"),"n.a.",IF(F22=0,0,100*(COUNTIFS($P$14:$P$63,1,$S$14:$S$63,"<"&I22)+0.5*(COUNTIFS($P$14:$P$63,1,$S$14:$S$63,I22)-1))/($B$6-1)))) | L22: =IF(A22="","",IF(OR(P22<>1,$B$8<>"Ready"),"n.a.",$G$5*J22+$G$6*K22)) | M22: =IF(A22="","",IF(NOT(ISNUMBER(L22)),"n.a.",1+COUNTIFS($P$14:$P$63,1,$L$14:$L$63,">"&L22))) | N22: =IF(A22="","",COUNTIFS(Relationships!$A$6:$A$205,A22,Relationships!$V$6:$V$205,1)) | O22: =IF(A22="","",IF(Q22<>1,"Outside cap universe",IF(R22<>1,"Duplicate network issuer",IF(C22<>"Yes","Review incomplete",IF(OR(NOT(ISNUMBER(D22)),D22>Rules!$B$6,Rules!$B$6-D22>Rules!$B$42,E22=""),"Check review date/log",IF(N22>0,"Resolve included records",IF($B$8<>"Ready",$B$8,IF(F22=0,"Reviewed: no qualifying ties","Ranked")))))))) | P22: =IF(A22="",0,IF(AND(Q22=1,R22=1,C22="Yes",ISNUMBER(D22),D22<=Rules!$B$6,Rules!$B$6-D22<=Rules!$B$42,E22<>"",N22=0),1,0)) -> 0 | Q22: {=IF(A22="",0,IF(COUNTIF(Companies!$A$6:$A$55,A22)<>1,0,IF(AND(INDEX(Companies!$R$6:$R$55,MATCH(A22,Companies!$A$6:$A$55,0))=1,INDEX(Companies!$I$6:$I$55,MATCH(A22,Companies!$A$6:$A$55,0))>=MAX(10,Rules!$B$22)),1,0)))} -> 0 | R22: =IF(A22="","",COUNTIF($A$14:$A$63,A22)) | S22: =IF(P22<>1,"",IF(F22=0,0,I22))
B23: {=IF(A23="","",IF(COUNTIF(Companies!$A$6:$A$55,A23)<>1,"n.a.",INDEX(Companies!$C$6:$C$55,MATCH(A23,Companies!$A$6:$A$55,0))))} | F23: =IF(A23="","",COUNTIFS(Relationships!$A$6:$A$205,A23,Relationships!$U$6:$U$205,1)) | G23: =IF(A23="","",COUNTIFS(Relationships!$A$6:$A$205,A23,Relationships!$U$6:$U$205,1,Relationships!$C$6:$C$205,"Client")+COUNTIFS(Relationships!$A$6:$A$205,A23,Relationships!$U$6:$U$205,1,Relationships!$C$6:$C$205,"Client and partner")) | H23: =IF(A23="","",COUNTIFS(Relationships!$A$6:$A$205,A23,Relationships!$U$6:$U$205,1,Relationships!$C$6:$C$205,"Partner")+COUNTIFS(Relationships!$A$6:$A$205,A23,Relationships!$U$6:$U$205,1,Relationships!$C$6:$C$205,"Client and partner")) | I23: =IFERROR(__xludf.DUMMYFUNCTION("IF(A23="""","""",IF(F23=0,""n.a."",MEDIAN(FILTER(Relationships!$Q$6:$Q$205,Relationships!$A$6:$A$205=A23,Relationships!$U$6:$U$205=1))))"),"") | J23: =IF(A23="","",IF(OR(P23<>1,$B$8<>"Ready"),"n.a.",IF(F23=0,0,100*(COUNTIFS($P$14:$P$63,1,$F$14:$F$63,"<"&F23)+0.5*(COUNTIFS($P$14:$P$63,1,$F$14:$F$63,F23)-1))/($B$6-1)))) | K23: =IF(A23="","",IF(OR(P23<>1,$B$8<>"Ready"),"n.a.",IF(F23=0,0,100*(COUNTIFS($P$14:$P$63,1,$S$14:$S$63,"<"&I23)+0.5*(COUNTIFS($P$14:$P$63,1,$S$14:$S$63,I23)-1))/($B$6-1)))) | L23: =IF(A23="","",IF(OR(P23<>1,$B$8<>"Ready"),"n.a.",$G$5*J23+$G$6*K23)) | M23: =IF(A23="","",IF(NOT(ISNUMBER(L23)),"n.a.",1+COUNTIFS($P$14:$P$63,1,$L$14:$L$63,">"&L23))) | N23: =IF(A23="","",COUNTIFS(Relationships!$A$6:$A$205,A23,Relationships!$V$6:$V$205,1)) | O23: =IF(A23="","",IF(Q23<>1,"Outside cap universe",IF(R23<>1,"Duplicate network issuer",IF(C23<>"Yes","Review incomplete",IF(OR(NOT(ISNUMBER(D23)),D23>Rules!$B$6,Rules!$B$6-D23>Rules!$B$42,E23=""),"Check review date/log",IF(N23>0,"Resolve included records",IF($B$8<>"Ready",$B$8,IF(F23=0,"Reviewed: no qualifying ties","Ranked")))))))) | P23: =IF(A23="",0,IF(AND(Q23=1,R23=1,C23="Yes",ISNUMBER(D23),D23<=Rules!$B$6,Rules!$B$6-D23<=Rules!$B$42,E23<>"",N23=0),1,0)) -> 0 | Q23: {=IF(A23="",0,IF(COUNTIF(Companies!$A$6:$A$55,A23)<>1,0,IF(AND(INDEX(Companies!$R$6:$R$55,MATCH(A23,Companies!$A$6:$A$55,0))=1,INDEX(Companies!$I$6:$I$55,MATCH(A23,Companies!$A$6:$A$55,0))>=MAX(10,Rules!$B$22)),1,0)))} -> 0 | R23: =IF(A23="","",COUNTIF($A$14:$A$63,A23)) | S23: =IF(P23<>1,"",IF(F23=0,0,I23))
B24: {=IF(A24="","",IF(COUNTIF(Companies!$A$6:$A$55,A24)<>1,"n.a.",INDEX(Companies!$C$6:$C$55,MATCH(A24,Companies!$A$6:$A$55,0))))} | F24: =IF(A24="","",COUNTIFS(Relationships!$A$6:$A$205,A24,Relationships!$U$6:$U$205,1)) | G24: =IF(A24="","",COUNTIFS(Relationships!$A$6:$A$205,A24,Relationships!$U$6:$U$205,1,Relationships!$C$6:$C$205,"Client")+COUNTIFS(Relationships!$A$6:$A$205,A24,Relationships!$U$6:$U$205,1,Relationships!$C$6:$C$205,"Client and partner")) | H24: =IF(A24="","",COUNTIFS(Relationships!$A$6:$A$205,A24,Relationships!$U$6:$U$205,1,Relationships!$C$6:$C$205,"Partner")+COUNTIFS(Relationships!$A$6:$A$205,A24,Relationships!$U$6:$U$205,1,Relationships!$C$6:$C$205,"Client and partner")) | I24: =IFERROR(__xludf.DUMMYFUNCTION("IF(A24="""","""",IF(F24=0,""n.a."",MEDIAN(FILTER(Relationships!$Q$6:$Q$205,Relationships!$A$6:$A$205=A24,Relationships!$U$6:$U$205=1))))"),"") | J24: =IF(A24="","",IF(OR(P24<>1,$B$8<>"Ready"),"n.a.",IF(F24=0,0,100*(COUNTIFS($P$14:$P$63,1,$F$14:$F$63,"<"&F24)+0.5*(COUNTIFS($P$14:$P$63,1,$F$14:$F$63,F24)-1))/($B$6-1)))) | K24: =IF(A24="","",IF(OR(P24<>1,$B$8<>"Ready"),"n.a.",IF(F24=0,0,100*(COUNTIFS($P$14:$P$63,1,$S$14:$S$63,"<"&I24)+0.5*(COUNTIFS($P$14:$P$63,1,$S$14:$S$63,I24)-1))/($B$6-1)))) | L24: =IF(A24="","",IF(OR(P24<>1,$B$8<>"Ready"),"n.a.",$G$5*J24+$G$6*K24)) | M24: =IF(A24="","",IF(NOT(ISNUMBER(L24)),"n.a.",1+COUNTIFS($P$14:$P$63,1,$L$14:$L$63,">"&L24))) | N24: =IF(A24="","",COUNTIFS(Relationships!$A$6:$A$205,A24,Relationships!$V$6:$V$205,1)) | O24: =IF(A24="","",IF(Q24<>1,"Outside cap universe",IF(R24<>1,"Duplicate network issuer",IF(C24<>"Yes","Review incomplete",IF(OR(NOT(ISNUMBER(D24)),D24>Rules!$B$6,Rules!$B$6-D24>Rules!$B$42,E24=""),"Check review date/log",IF(N24>0,"Resolve included records",IF($B$8<>"Ready",$B$8,IF(F24=0,"Reviewed: no qualifying ties","Ranked")))))))) | P24: =IF(A24="",0,IF(AND(Q24=1,R24=1,C24="Yes",ISNUMBER(D24),D24<=Rules!$B$6,Rules!$B$6-D24<=Rules!$B$42,E24<>"",N24=0),1,0)) -> 0 | Q24: {=IF(A24="",0,IF(COUNTIF(Companies!$A$6:$A$55,A24)<>1,0,IF(AND(INDEX(Companies!$R$6:$R$55,MATCH(A24,Companies!$A$6:$A$55,0))=1,INDEX(Companies!$I$6:$I$55,MATCH(A24,Companies!$A$6:$A$55,0))>=MAX(10,Rules!$B$22)),1,0)))} -> 0 | R24: =IF(A24="","",COUNTIF($A$14:$A$63,A24)) | S24: =IF(P24<>1,"",IF(F24=0,0,I24))
B25: {=IF(A25="","",IF(COUNTIF(Companies!$A$6:$A$55,A25)<>1,"n.a.",INDEX(Companies!$C$6:$C$55,MATCH(A25,Companies!$A$6:$A$55,0))))} | F25: =IF(A25="","",COUNTIFS(Relationships!$A$6:$A$205,A25,Relationships!$U$6:$U$205,1)) | G25: =IF(A25="","",COUNTIFS(Relationships!$A$6:$A$205,A25,Relationships!$U$6:$U$205,1,Relationships!$C$6:$C$205,"Client")+COUNTIFS(Relationships!$A$6:$A$205,A25,Relationships!$U$6:$U$205,1,Relationships!$C$6:$C$205,"Client and partner")) | H25: =IF(A25="","",COUNTIFS(Relationships!$A$6:$A$205,A25,Relationships!$U$6:$U$205,1,Relationships!$C$6:$C$205,"Partner")+COUNTIFS(Relationships!$A$6:$A$205,A25,Relationships!$U$6:$U$205,1,Relationships!$C$6:$C$205,"Client and partner")) | I25: =IFERROR(__xludf.DUMMYFUNCTION("IF(A25="""","""",IF(F25=0,""n.a."",MEDIAN(FILTER(Relationships!$Q$6:$Q$205,Relationships!$A$6:$A$205=A25,Relationships!$U$6:$U$205=1))))"),"") | J25: =IF(A25="","",IF(OR(P25<>1,$B$8<>"Ready"),"n.a.",IF(F25=0,0,100*(COUNTIFS($P$14:$P$63,1,$F$14:$F$63,"<"&F25)+0.5*(COUNTIFS($P$14:$P$63,1,$F$14:$F$63,F25)-1))/($B$6-1)))) | K25: =IF(A25="","",IF(OR(P25<>1,$B$8<>"Ready"),"n.a.",IF(F25=0,0,100*(COUNTIFS($P$14:$P$63,1,$S$14:$S$63,"<"&I25)+0.5*(COUNTIFS($P$14:$P$63,1,$S$14:$S$63,I25)-1))/($B$6-1)))) | L25: =IF(A25="","",IF(OR(P25<>1,$B$8<>"Ready"),"n.a.",$G$5*J25+$G$6*K25)) | M25: =IF(A25="","",IF(NOT(ISNUMBER(L25)),"n.a.",1+COUNTIFS($P$14:$P$63,1,$L$14:$L$63,">"&L25))) | N25: =IF(A25="","",COUNTIFS(Relationships!$A$6:$A$205,A25,Relationships!$V$6:$V$205,1)) | O25: =IF(A25="","",IF(Q25<>1,"Outside cap universe",IF(R25<>1,"Duplicate network issuer",IF(C25<>"Yes","Review incomplete",IF(OR(NOT(ISNUMBER(D25)),D25>Rules!$B$6,Rules!$B$6-D25>Rules!$B$42,E25=""),"Check review date/log",IF(N25>0,"Resolve included records",IF($B$8<>"Ready",$B$8,IF(F25=0,"Reviewed: no qualifying ties","Ranked")))))))) | P25: =IF(A25="",0,IF(AND(Q25=1,R25=1,C25="Yes",ISNUMBER(D25),D25<=Rules!$B$6,Rules!$B$6-D25<=Rules!$B$42,E25<>"",N25=0),1,0)) -> 0 | Q25: {=IF(A25="",0,IF(COUNTIF(Companies!$A$6:$A$55,A25)<>1,0,IF(AND(INDEX(Companies!$R$6:$R$55,MATCH(A25,Companies!$A$6:$A$55,0))=1,INDEX(Companies!$I$6:$I$55,MATCH(A25,Companies!$A$6:$A$55,0))>=MAX(10,Rules!$B$22)),1,0)))} -> 0 | R25: =IF(A25="","",COUNTIF($A$14:$A$63,A25)) | S25: =IF(P25<>1,"",IF(F25=0,0,I25))
B26: {=IF(A26="","",IF(COUNTIF(Companies!$A$6:$A$55,A26)<>1,"n.a.",INDEX(Companies!$C$6:$C$55,MATCH(A26,Companies!$A$6:$A$55,0))))} | F26: =IF(A26="","",COUNTIFS(Relationships!$A$6:$A$205,A26,Relationships!$U$6:$U$205,1)) | G26: =IF(A26="","",COUNTIFS(Relationships!$A$6:$A$205,A26,Relationships!$U$6:$U$205,1,Relationships!$C$6:$C$205,"Client")+COUNTIFS(Relationships!$A$6:$A$205,A26,Relationships!$U$6:$U$205,1,Relationships!$C$6:$C$205,"Client and partner")) | H26: =IF(A26="","",COUNTIFS(Relationships!$A$6:$A$205,A26,Relationships!$U$6:$U$205,1,Relationships!$C$6:$C$205,"Partner")+COUNTIFS(Relationships!$A$6:$A$205,A26,Relationships!$U$6:$U$205,1,Relationships!$C$6:$C$205,"Client and partner")) | I26: =IFERROR(__xludf.DUMMYFUNCTION("IF(A26="""","""",IF(F26=0,""n.a."",MEDIAN(FILTER(Relationships!$Q$6:$Q$205,Relationships!$A$6:$A$205=A26,Relationships!$U$6:$U$205=1))))"),"") | J26: =IF(A26="","",IF(OR(P26<>1,$B$8<>"Ready"),"n.a.",IF(F26=0,0,100*(COUNTIFS($P$14:$P$63,1,$F$14:$F$63,"<"&F26)+0.5*(COUNTIFS($P$14:$P$63,1,$F$14:$F$63,F26)-1))/($B$6-1)))) | K26: =IF(A26="","",IF(OR(P26<>1,$B$8<>"Ready"),"n.a.",IF(F26=0,0,100*(COUNTIFS($P$14:$P$63,1,$S$14:$S$63,"<"&I26)+0.5*(COUNTIFS($P$14:$P$63,1,$S$14:$S$63,I26)-1))/($B$6-1)))) | L26: =IF(A26="","",IF(OR(P26<>1,$B$8<>"Ready"),"n.a.",$G$5*J26+$G$6*K26)) | M26: =IF(A26="","",IF(NOT(ISNUMBER(L26)),"n.a.",1+COUNTIFS($P$14:$P$63,1,$L$14:$L$63,">"&L26))) | N26: =IF(A26="","",COUNTIFS(Relationships!$A$6:$A$205,A26,Relationships!$V$6:$V$205,1)) | O26: =IF(A26="","",IF(Q26<>1,"Outside cap universe",IF(R26<>1,"Duplicate network issuer",IF(C26<>"Yes","Review incomplete",IF(OR(NOT(ISNUMBER(D26)),D26>Rules!$B$6,Rules!$B$6-D26>Rules!$B$42,E26=""),"Check review date/log",IF(N26>0,"Resolve included records",IF($B$8<>"Ready",$B$8,IF(F26=0,"Reviewed: no qualifying ties","Ranked")))))))) | P26: =IF(A26="",0,IF(AND(Q26=1,R26=1,C26="Yes",ISNUMBER(D26),D26<=Rules!$B$6,Rules!$B$6-D26<=Rules!$B$42,E26<>"",N26=0),1,0)) -> 0 | Q26: {=IF(A26="",0,IF(COUNTIF(Companies!$A$6:$A$55,A26)<>1,0,IF(AND(INDEX(Companies!$R$6:$R$55,MATCH(A26,Companies!$A$6:$A$55,0))=1,INDEX(Companies!$I$6:$I$55,MATCH(A26,Companies!$A$6:$A$55,0))>=MAX(10,Rules!$B$22)),1,0)))} -> 0 | R26: =IF(A26="","",COUNTIF($A$14:$A$63,A26)) | S26: =IF(P26<>1,"",IF(F26=0,0,I26))
B27: {=IF(A27="","",IF(COUNTIF(Companies!$A$6:$A$55,A27)<>1,"n.a.",INDEX(Companies!$C$6:$C$55,MATCH(A27,Companies!$A$6:$A$55,0))))} | F27: =IF(A27="","",COUNTIFS(Relationships!$A$6:$A$205,A27,Relationships!$U$6:$U$205,1)) | G27: =IF(A27="","",COUNTIFS(Relationships!$A$6:$A$205,A27,Relationships!$U$6:$U$205,1,Relationships!$C$6:$C$205,"Client")+COUNTIFS(Relationships!$A$6:$A$205,A27,Relationships!$U$6:$U$205,1,Relationships!$C$6:$C$205,"Client and partner")) | H27: =IF(A27="","",COUNTIFS(Relationships!$A$6:$A$205,A27,Relationships!$U$6:$U$205,1,Relationships!$C$6:$C$205,"Partner")+COUNTIFS(Relationships!$A$6:$A$205,A27,Relationships!$U$6:$U$205,1,Relationships!$C$6:$C$205,"Client and partner")) | I27: =IFERROR(__xludf.DUMMYFUNCTION("IF(A27="""","""",IF(F27=0,""n.a."",MEDIAN(FILTER(Relationships!$Q$6:$Q$205,Relationships!$A$6:$A$205=A27,Relationships!$U$6:$U$205=1))))"),"") | J27: =IF(A27="","",IF(OR(P27<>1,$B$8<>"Ready"),"n.a.",IF(F27=0,0,100*(COUNTIFS($P$14:$P$63,1,$F$14:$F$63,"<"&F27)+0.5*(COUNTIFS($P$14:$P$63,1,$F$14:$F$63,F27)-1))/($B$6-1)))) | K27: =IF(A27="","",IF(OR(P27<>1,$B$8<>"Ready"),"n.a.",IF(F27=0,0,100*(COUNTIFS($P$14:$P$63,1,$S$14:$S$63,"<"&I27)+0.5*(COUNTIFS($P$14:$P$63,1,$S$14:$S$63,I27)-1))/($B$6-1)))) | L27: =IF(A27="","",IF(OR(P27<>1,$B$8<>"Ready"),"n.a.",$G$5*J27+$G$6*K27)) | M27: =IF(A27="","",IF(NOT(ISNUMBER(L27)),"n.a.",1+COUNTIFS($P$14:$P$63,1,$L$14:$L$63,">"&L27))) | N27: =IF(A27="","",COUNTIFS(Relationships!$A$6:$A$205,A27,Relationships!$V$6:$V$205,1)) | O27: =IF(A27="","",IF(Q27<>1,"Outside cap universe",IF(R27<>1,"Duplicate network issuer",IF(C27<>"Yes","Review incomplete",IF(OR(NOT(ISNUMBER(D27)),D27>Rules!$B$6,Rules!$B$6-D27>Rules!$B$42,E27=""),"Check review date/log",IF(N27>0,"Resolve included records",IF($B$8<>"Ready",$B$8,IF(F27=0,"Reviewed: no qualifying ties","Ranked")))))))) | P27: =IF(A27="",0,IF(AND(Q27=1,R27=1,C27="Yes",ISNUMBER(D27),D27<=Rules!$B$6,Rules!$B$6-D27<=Rules!$B$42,E27<>"",N27=0),1,0)) -> 0 | Q27: {=IF(A27="",0,IF(COUNTIF(Companies!$A$6:$A$55,A27)<>1,0,IF(AND(INDEX(Companies!$R$6:$R$55,MATCH(A27,Companies!$A$6:$A$55,0))=1,INDEX(Companies!$I$6:$I$55,MATCH(A27,Companies!$A$6:$A$55,0))>=MAX(10,Rules!$B$22)),1,0)))} -> 0 | R27: =IF(A27="","",COUNTIF($A$14:$A$63,A27)) | S27: =IF(P27<>1,"",IF(F27=0,0,I27))
B28: {=IF(A28="","",IF(COUNTIF(Companies!$A$6:$A$55,A28)<>1,"n.a.",INDEX(Companies!$C$6:$C$55,MATCH(A28,Companies!$A$6:$A$55,0))))} | F28: =IF(A28="","",COUNTIFS(Relationships!$A$6:$A$205,A28,Relationships!$U$6:$U$205,1)) | G28: =IF(A28="","",COUNTIFS(Relationships!$A$6:$A$205,A28,Relationships!$U$6:$U$205,1,Relationships!$C$6:$C$205,"Client")+COUNTIFS(Relationships!$A$6:$A$205,A28,Relationships!$U$6:$U$205,1,Relationships!$C$6:$C$205,"Client and partner")) | H28: =IF(A28="","",COUNTIFS(Relationships!$A$6:$A$205,A28,Relationships!$U$6:$U$205,1,Relationships!$C$6:$C$205,"Partner")+COUNTIFS(Relationships!$A$6:$A$205,A28,Relationships!$U$6:$U$205,1,Relationships!$C$6:$C$205,"Client and partner")) | I28: =IFERROR(__xludf.DUMMYFUNCTION("IF(A28="""","""",IF(F28=0,""n.a."",MEDIAN(FILTER(Relationships!$Q$6:$Q$205,Relationships!$A$6:$A$205=A28,Relationships!$U$6:$U$205=1))))"),"") | J28: =IF(A28="","",IF(OR(P28<>1,$B$8<>"Ready"),"n.a.",IF(F28=0,0,100*(COUNTIFS($P$14:$P$63,1,$F$14:$F$63,"<"&F28)+0.5*(COUNTIFS($P$14:$P$63,1,$F$14:$F$63,F28)-1))/($B$6-1)))) | K28: =IF(A28="","",IF(OR(P28<>1,$B$8<>"Ready"),"n.a.",IF(F28=0,0,100*(COUNTIFS($P$14:$P$63,1,$S$14:$S$63,"<"&I28)+0.5*(COUNTIFS($P$14:$P$63,1,$S$14:$S$63,I28)-1))/($B$6-1)))) | L28: =IF(A28="","",IF(OR(P28<>1,$B$8<>"Ready"),"n.a.",$G$5*J28+$G$6*K28)) | M28: =IF(A28="","",IF(NOT(ISNUMBER(L28)),"n.a.",1+COUNTIFS($P$14:$P$63,1,$L$14:$L$63,">"&L28))) | N28: =IF(A28="","",COUNTIFS(Relationships!$A$6:$A$205,A28,Relationships!$V$6:$V$205,1)) | O28: =IF(A28="","",IF(Q28<>1,"Outside cap universe",IF(R28<>1,"Duplicate network issuer",IF(C28<>"Yes","Review incomplete",IF(OR(NOT(ISNUMBER(D28)),D28>Rules!$B$6,Rules!$B$6-D28>Rules!$B$42,E28=""),"Check review date/log",IF(N28>0,"Resolve included records",IF($B$8<>"Ready",$B$8,IF(F28=0,"Reviewed: no qualifying ties","Ranked")))))))) | P28: =IF(A28="",0,IF(AND(Q28=1,R28=1,C28="Yes",ISNUMBER(D28),D28<=Rules!$B$6,Rules!$B$6-D28<=Rules!$B$42,E28<>"",N28=0),1,0)) -> 0 | Q28: {=IF(A28="",0,IF(COUNTIF(Companies!$A$6:$A$55,A28)<>1,0,IF(AND(INDEX(Companies!$R$6:$R$55,MATCH(A28,Companies!$A$6:$A$55,0))=1,INDEX(Companies!$I$6:$I$55,MATCH(A28,Companies!$A$6:$A$55,0))>=MAX(10,Rules!$B$22)),1,0)))} -> 0 | R28: =IF(A28="","",COUNTIF($A$14:$A$63,A28)) | S28: =IF(P28<>1,"",IF(F28=0,0,I28))
B29: {=IF(A29="","",IF(COUNTIF(Companies!$A$6:$A$55,A29)<>1,"n.a.",INDEX(Companies!$C$6:$C$55,MATCH(A29,Companies!$A$6:$A$55,0))))} | F29: =IF(A29="","",COUNTIFS(Relationships!$A$6:$A$205,A29,Relationships!$U$6:$U$205,1)) | G29: =IF(A29="","",COUNTIFS(Relationships!$A$6:$A$205,A29,Relationships!$U$6:$U$205,1,Relationships!$C$6:$C$205,"Client")+COUNTIFS(Relationships!$A$6:$A$205,A29,Relationships!$U$6:$U$205,1,Relationships!$C$6:$C$205,"Client and partner")) | H29: =IF(A29="","",COUNTIFS(Relationships!$A$6:$A$205,A29,Relationships!$U$6:$U$205,1,Relationships!$C$6:$C$205,"Partner")+COUNTIFS(Relationships!$A$6:$A$205,A29,Relationships!$U$6:$U$205,1,Relationships!$C$6:$C$205,"Client and partner")) | I29: =IFERROR(__xludf.DUMMYFUNCTION("IF(A29="""","""",IF(F29=0,""n.a."",MEDIAN(FILTER(Relationships!$Q$6:$Q$205,Relationships!$A$6:$A$205=A29,Relationships!$U$6:$U$205=1))))"),"") | J29: =IF(A29="","",IF(OR(P29<>1,$B$8<>"Ready"),"n.a.",IF(F29=0,0,100*(COUNTIFS($P$14:$P$63,1,$F$14:$F$63,"<"&F29)+0.5*(COUNTIFS($P$14:$P$63,1,$F$14:$F$63,F29)-1))/($B$6-1)))) | K29: =IF(A29="","",IF(OR(P29<>1,$B$8<>"Ready"),"n.a.",IF(F29=0,0,100*(COUNTIFS($P$14:$P$63,1,$S$14:$S$63,"<"&I29)+0.5*(COUNTIFS($P$14:$P$63,1,$S$14:$S$63,I29)-1))/($B$6-1)))) | L29: =IF(A29="","",IF(OR(P29<>1,$B$8<>"Ready"),"n.a.",$G$5*J29+$G$6*K29)) | M29: =IF(A29="","",IF(NOT(ISNUMBER(L29)),"n.a.",1+COUNTIFS($P$14:$P$63,1,$L$14:$L$63,">"&L29))) | N29: =IF(A29="","",COUNTIFS(Relationships!$A$6:$A$205,A29,Relationships!$V$6:$V$205,1)) | O29: =IF(A29="","",IF(Q29<>1,"Outside cap universe",IF(R29<>1,"Duplicate network issuer",IF(C29<>"Yes","Review incomplete",IF(OR(NOT(ISNUMBER(D29)),D29>Rules!$B$6,Rules!$B$6-D29>Rules!$B$42,E29=""),"Check review date/log",IF(N29>0,"Resolve included records",IF($B$8<>"Ready",$B$8,IF(F29=0,"Reviewed: no qualifying ties","Ranked")))))))) | P29: =IF(A29="",0,IF(AND(Q29=1,R29=1,C29="Yes",ISNUMBER(D29),D29<=Rules!$B$6,Rules!$B$6-D29<=Rules!$B$42,E29<>"",N29=0),1,0)) -> 0 | Q29: {=IF(A29="",0,IF(COUNTIF(Companies!$A$6:$A$55,A29)<>1,0,IF(AND(INDEX(Companies!$R$6:$R$55,MATCH(A29,Companies!$A$6:$A$55,0))=1,INDEX(Companies!$I$6:$I$55,MATCH(A29,Companies!$A$6:$A$55,0))>=MAX(10,Rules!$B$22)),1,0)))} -> 0 | R29: =IF(A29="","",COUNTIF($A$14:$A$63,A29)) | S29: =IF(P29<>1,"",IF(F29=0,0,I29))
B30: {=IF(A30="","",IF(COUNTIF(Companies!$A$6:$A$55,A30)<>1,"n.a.",INDEX(Companies!$C$6:$C$55,MATCH(A30,Companies!$A$6:$A$55,0))))} | F30: =IF(A30="","",COUNTIFS(Relationships!$A$6:$A$205,A30,Relationships!$U$6:$U$205,1)) | G30: =IF(A30="","",COUNTIFS(Relationships!$A$6:$A$205,A30,Relationships!$U$6:$U$205,1,Relationships!$C$6:$C$205,"Client")+COUNTIFS(Relationships!$A$6:$A$205,A30,Relationships!$U$6:$U$205,1,Relationships!$C$6:$C$205,"Client and partner")) | H30: =IF(A30="","",COUNTIFS(Relationships!$A$6:$A$205,A30,Relationships!$U$6:$U$205,1,Relationships!$C$6:$C$205,"Partner")+COUNTIFS(Relationships!$A$6:$A$205,A30,Relationships!$U$6:$U$205,1,Relationships!$C$6:$C$205,"Client and partner")) | I30: =IFERROR(__xludf.DUMMYFUNCTION("IF(A30="""","""",IF(F30=0,""n.a."",MEDIAN(FILTER(Relationships!$Q$6:$Q$205,Relationships!$A$6:$A$205=A30,Relationships!$U$6:$U$205=1))))"),"") | J30: =IF(A30="","",IF(OR(P30<>1,$B$8<>"Ready"),"n.a.",IF(F30=0,0,100*(COUNTIFS($P$14:$P$63,1,$F$14:$F$63,"<"&F30)+0.5*(COUNTIFS($P$14:$P$63,1,$F$14:$F$63,F30)-1))/($B$6-1)))) | K30: =IF(A30="","",IF(OR(P30<>1,$B$8<>"Ready"),"n.a.",IF(F30=0,0,100*(COUNTIFS($P$14:$P$63,1,$S$14:$S$63,"<"&I30)+0.5*(COUNTIFS($P$14:$P$63,1,$S$14:$S$63,I30)-1))/($B$6-1)))) | L30: =IF(A30="","",IF(OR(P30<>1,$B$8<>"Ready"),"n.a.",$G$5*J30+$G$6*K30)) | M30: =IF(A30="","",IF(NOT(ISNUMBER(L30)),"n.a.",1+COUNTIFS($P$14:$P$63,1,$L$14:$L$63,">"&L30))) | N30: =IF(A30="","",COUNTIFS(Relationships!$A$6:$A$205,A30,Relationships!$V$6:$V$205,1)) | O30: =IF(A30="","",IF(Q30<>1,"Outside cap universe",IF(R30<>1,"Duplicate network issuer",IF(C30<>"Yes","Review incomplete",IF(OR(NOT(ISNUMBER(D30)),D30>Rules!$B$6,Rules!$B$6-D30>Rules!$B$42,E30=""),"Check review date/log",IF(N30>0,"Resolve included records",IF($B$8<>"Ready",$B$8,IF(F30=0,"Reviewed: no qualifying ties","Ranked")))))))) | P30: =IF(A30="",0,IF(AND(Q30=1,R30=1,C30="Yes",ISNUMBER(D30),D30<=Rules!$B$6,Rules!$B$6-D30<=Rules!$B$42,E30<>"",N30=0),1,0)) -> 0 | Q30: {=IF(A30="",0,IF(COUNTIF(Companies!$A$6:$A$55,A30)<>1,0,IF(AND(INDEX(Companies!$R$6:$R$55,MATCH(A30,Companies!$A$6:$A$55,0))=1,INDEX(Companies!$I$6:$I$55,MATCH(A30,Companies!$A$6:$A$55,0))>=MAX(10,Rules!$B$22)),1,0)))} -> 0 | R30: =IF(A30="","",COUNTIF($A$14:$A$63,A30)) | S30: =IF(P30<>1,"",IF(F30=0,0,I30))
B31: {=IF(A31="","",IF(COUNTIF(Companies!$A$6:$A$55,A31)<>1,"n.a.",INDEX(Companies!$C$6:$C$55,MATCH(A31,Companies!$A$6:$A$55,0))))} | F31: =IF(A31="","",COUNTIFS(Relationships!$A$6:$A$205,A31,Relationships!$U$6:$U$205,1)) | G31: =IF(A31="","",COUNTIFS(Relationships!$A$6:$A$205,A31,Relationships!$U$6:$U$205,1,Relationships!$C$6:$C$205,"Client")+COUNTIFS(Relationships!$A$6:$A$205,A31,Relationships!$U$6:$U$205,1,Relationships!$C$6:$C$205,"Client and partner")) | H31: =IF(A31="","",COUNTIFS(Relationships!$A$6:$A$205,A31,Relationships!$U$6:$U$205,1,Relationships!$C$6:$C$205,"Partner")+COUNTIFS(Relationships!$A$6:$A$205,A31,Relationships!$U$6:$U$205,1,Relationships!$C$6:$C$205,"Client and partner")) | I31: =IFERROR(__xludf.DUMMYFUNCTION("IF(A31="""","""",IF(F31=0,""n.a."",MEDIAN(FILTER(Relationships!$Q$6:$Q$205,Relationships!$A$6:$A$205=A31,Relationships!$U$6:$U$205=1))))"),"") | J31: =IF(A31="","",IF(OR(P31<>1,$B$8<>"Ready"),"n.a.",IF(F31=0,0,100*(COUNTIFS($P$14:$P$63,1,$F$14:$F$63,"<"&F31)+0.5*(COUNTIFS($P$14:$P$63,1,$F$14:$F$63,F31)-1))/($B$6-1)))) | K31: =IF(A31="","",IF(OR(P31<>1,$B$8<>"Ready"),"n.a.",IF(F31=0,0,100*(COUNTIFS($P$14:$P$63,1,$S$14:$S$63,"<"&I31)+0.5*(COUNTIFS($P$14:$P$63,1,$S$14:$S$63,I31)-1))/($B$6-1)))) | L31: =IF(A31="","",IF(OR(P31<>1,$B$8<>"Ready"),"n.a.",$G$5*J31+$G$6*K31)) | M31: =IF(A31="","",IF(NOT(ISNUMBER(L31)),"n.a.",1+COUNTIFS($P$14:$P$63,1,$L$14:$L$63,">"&L31))) | N31: =IF(A31="","",COUNTIFS(Relationships!$A$6:$A$205,A31,Relationships!$V$6:$V$205,1)) | O31: =IF(A31="","",IF(Q31<>1,"Outside cap universe",IF(R31<>1,"Duplicate network issuer",IF(C31<>"Yes","Review incomplete",IF(OR(NOT(ISNUMBER(D31)),D31>Rules!$B$6,Rules!$B$6-D31>Rules!$B$42,E31=""),"Check review date/log",IF(N31>0,"Resolve included records",IF($B$8<>"Ready",$B$8,IF(F31=0,"Reviewed: no qualifying ties","Ranked")))))))) | P31: =IF(A31="",0,IF(AND(Q31=1,R31=1,C31="Yes",ISNUMBER(D31),D31<=Rules!$B$6,Rules!$B$6-D31<=Rules!$B$42,E31<>"",N31=0),1,0)) -> 0 | Q31: {=IF(A31="",0,IF(COUNTIF(Companies!$A$6:$A$55,A31)<>1,0,IF(AND(INDEX(Companies!$R$6:$R$55,MATCH(A31,Companies!$A$6:$A$55,0))=1,INDEX(Companies!$I$6:$I$55,MATCH(A31,Companies!$A$6:$A$55,0))>=MAX(10,Rules!$B$22)),1,0)))} -> 0 | R31: =IF(A31="","",COUNTIF($A$14:$A$63,A31)) | S31: =IF(P31<>1,"",IF(F31=0,0,I31))
B32: {=IF(A32="","",IF(COUNTIF(Companies!$A$6:$A$55,A32)<>1,"n.a.",INDEX(Companies!$C$6:$C$55,MATCH(A32,Companies!$A$6:$A$55,0))))} | F32: =IF(A32="","",COUNTIFS(Relationships!$A$6:$A$205,A32,Relationships!$U$6:$U$205,1)) | G32: =IF(A32="","",COUNTIFS(Relationships!$A$6:$A$205,A32,Relationships!$U$6:$U$205,1,Relationships!$C$6:$C$205,"Client")+COUNTIFS(Relationships!$A$6:$A$205,A32,Relationships!$U$6:$U$205,1,Relationships!$C$6:$C$205,"Client and partner")) | H32: =IF(A32="","",COUNTIFS(Relationships!$A$6:$A$205,A32,Relationships!$U$6:$U$205,1,Relationships!$C$6:$C$205,"Partner")+COUNTIFS(Relationships!$A$6:$A$205,A32,Relationships!$U$6:$U$205,1,Relationships!$C$6:$C$205,"Client and partner")) | I32: =IFERROR(__xludf.DUMMYFUNCTION("IF(A32="""","""",IF(F32=0,""n.a."",MEDIAN(FILTER(Relationships!$Q$6:$Q$205,Relationships!$A$6:$A$205=A32,Relationships!$U$6:$U$205=1))))"),"") | J32: =IF(A32="","",IF(OR(P32<>1,$B$8<>"Ready"),"n.a.",IF(F32=0,0,100*(COUNTIFS($P$14:$P$63,1,$F$14:$F$63,"<"&F32)+0.5*(COUNTIFS($P$14:$P$63,1,$F$14:$F$63,F32)-1))/($B$6-1)))) | K32: =IF(A32="","",IF(OR(P32<>1,$B$8<>"Ready"),"n.a.",IF(F32=0,0,100*(COUNTIFS($P$14:$P$63,1,$S$14:$S$63,"<"&I32)+0.5*(COUNTIFS($P$14:$P$63,1,$S$14:$S$63,I32)-1))/($B$6-1)))) | L32: =IF(A32="","",IF(OR(P32<>1,$B$8<>"Ready"),"n.a.",$G$5*J32+$G$6*K32)) | M32: =IF(A32="","",IF(NOT(ISNUMBER(L32)),"n.a.",1+COUNTIFS($P$14:$P$63,1,$L$14:$L$63,">"&L32))) | N32: =IF(A32="","",COUNTIFS(Relationships!$A$6:$A$205,A32,Relationships!$V$6:$V$205,1)) | O32: =IF(A32="","",IF(Q32<>1,"Outside cap universe",IF(R32<>1,"Duplicate network issuer",IF(C32<>"Yes","Review incomplete",IF(OR(NOT(ISNUMBER(D32)),D32>Rules!$B$6,Rules!$B$6-D32>Rules!$B$42,E32=""),"Check review date/log",IF(N32>0,"Resolve included records",IF($B$8<>"Ready",$B$8,IF(F32=0,"Reviewed: no qualifying ties","Ranked")))))))) | P32: =IF(A32="",0,IF(AND(Q32=1,R32=1,C32="Yes",ISNUMBER(D32),D32<=Rules!$B$6,Rules!$B$6-D32<=Rules!$B$42,E32<>"",N32=0),1,0)) -> 0 | Q32: {=IF(A32="",0,IF(COUNTIF(Companies!$A$6:$A$55,A32)<>1,0,IF(AND(INDEX(Companies!$R$6:$R$55,MATCH(A32,Companies!$A$6:$A$55,0))=1,INDEX(Companies!$I$6:$I$55,MATCH(A32,Companies!$A$6:$A$55,0))>=MAX(10,Rules!$B$22)),1,0)))} -> 0 | R32: =IF(A32="","",COUNTIF($A$14:$A$63,A32)) | S32: =IF(P32<>1,"",IF(F32=0,0,I32))
B33: {=IF(A33="","",IF(COUNTIF(Companies!$A$6:$A$55,A33)<>1,"n.a.",INDEX(Companies!$C$6:$C$55,MATCH(A33,Companies!$A$6:$A$55,0))))} | F33: =IF(A33="","",COUNTIFS(Relationships!$A$6:$A$205,A33,Relationships!$U$6:$U$205,1)) | G33: =IF(A33="","",COUNTIFS(Relationships!$A$6:$A$205,A33,Relationships!$U$6:$U$205,1,Relationships!$C$6:$C$205,"Client")+COUNTIFS(Relationships!$A$6:$A$205,A33,Relationships!$U$6:$U$205,1,Relationships!$C$6:$C$205,"Client and partner")) | H33: =IF(A33="","",COUNTIFS(Relationships!$A$6:$A$205,A33,Relationships!$U$6:$U$205,1,Relationships!$C$6:$C$205,"Partner")+COUNTIFS(Relationships!$A$6:$A$205,A33,Relationships!$U$6:$U$205,1,Relationships!$C$6:$C$205,"Client and partner")) | I33: =IFERROR(__xludf.DUMMYFUNCTION("IF(A33="""","""",IF(F33=0,""n.a."",MEDIAN(FILTER(Relationships!$Q$6:$Q$205,Relationships!$A$6:$A$205=A33,Relationships!$U$6:$U$205=1))))"),"") | J33: =IF(A33="","",IF(OR(P33<>1,$B$8<>"Ready"),"n.a.",IF(F33=0,0,100*(COUNTIFS($P$14:$P$63,1,$F$14:$F$63,"<"&F33)+0.5*(COUNTIFS($P$14:$P$63,1,$F$14:$F$63,F33)-1))/($B$6-1)))) | K33: =IF(A33="","",IF(OR(P33<>1,$B$8<>"Ready"),"n.a.",IF(F33=0,0,100*(COUNTIFS($P$14:$P$63,1,$S$14:$S$63,"<"&I33)+0.5*(COUNTIFS($P$14:$P$63,1,$S$14:$S$63,I33)-1))/($B$6-1)))) | L33: =IF(A33="","",IF(OR(P33<>1,$B$8<>"Ready"),"n.a.",$G$5*J33+$G$6*K33)) | M33: =IF(A33="","",IF(NOT(ISNUMBER(L33)),"n.a.",1+COUNTIFS($P$14:$P$63,1,$L$14:$L$63,">"&L33))) | N33: =IF(A33="","",COUNTIFS(Relationships!$A$6:$A$205,A33,Relationships!$V$6:$V$205,1)) | O33: =IF(A33="","",IF(Q33<>1,"Outside cap universe",IF(R33<>1,"Duplicate network issuer",IF(C33<>"Yes","Review incomplete",IF(OR(NOT(ISNUMBER(D33)),D33>Rules!$B$6,Rules!$B$6-D33>Rules!$B$42,E33=""),"Check review date/log",IF(N33>0,"Resolve included records",IF($B$8<>"Ready",$B$8,IF(F33=0,"Reviewed: no qualifying ties","Ranked")))))))) | P33: =IF(A33="",0,IF(AND(Q33=1,R33=1,C33="Yes",ISNUMBER(D33),D33<=Rules!$B$6,Rules!$B$6-D33<=Rules!$B$42,E33<>"",N33=0),1,0)) -> 0 | Q33: {=IF(A33="",0,IF(COUNTIF(Companies!$A$6:$A$55,A33)<>1,0,IF(AND(INDEX(Companies!$R$6:$R$55,MATCH(A33,Companies!$A$6:$A$55,0))=1,INDEX(Companies!$I$6:$I$55,MATCH(A33,Companies!$A$6:$A$55,0))>=MAX(10,Rules!$B$22)),1,0)))} -> 0 | R33: =IF(A33="","",COUNTIF($A$14:$A$63,A33)) | S33: =IF(P33<>1,"",IF(F33=0,0,I33))
B34: {=IF(A34="","",IF(COUNTIF(Companies!$A$6:$A$55,A34)<>1,"n.a.",INDEX(Companies!$C$6:$C$55,MATCH(A34,Companies!$A$6:$A$55,0))))} | F34: =IF(A34="","",COUNTIFS(Relationships!$A$6:$A$205,A34,Relationships!$U$6:$U$205,1)) | G34: =IF(A34="","",COUNTIFS(Relationships!$A$6:$A$205,A34,Relationships!$U$6:$U$205,1,Relationships!$C$6:$C$205,"Client")+COUNTIFS(Relationships!$A$6:$A$205,A34,Relationships!$U$6:$U$205,1,Relationships!$C$6:$C$205,"Client and partner")) | H34: =IF(A34="","",COUNTIFS(Relationships!$A$6:$A$205,A34,Relationships!$U$6:$U$205,1,Relationships!$C$6:$C$205,"Partner")+COUNTIFS(Relationships!$A$6:$A$205,A34,Relationships!$U$6:$U$205,1,Relationships!$C$6:$C$205,"Client and partner")) | I34: =IFERROR(__xludf.DUMMYFUNCTION("IF(A34="""","""",IF(F34=0,""n.a."",MEDIAN(FILTER(Relationships!$Q$6:$Q$205,Relationships!$A$6:$A$205=A34,Relationships!$U$6:$U$205=1))))"),"") | J34: =IF(A34="","",IF(OR(P34<>1,$B$8<>"Ready"),"n.a.",IF(F34=0,0,100*(COUNTIFS($P$14:$P$63,1,$F$14:$F$63,"<"&F34)+0.5*(COUNTIFS($P$14:$P$63,1,$F$14:$F$63,F34)-1))/($B$6-1)))) | K34: =IF(A34="","",IF(OR(P34<>1,$B$8<>"Ready"),"n.a.",IF(F34=0,0,100*(COUNTIFS($P$14:$P$63,1,$S$14:$S$63,"<"&I34)+0.5*(COUNTIFS($P$14:$P$63,1,$S$14:$S$63,I34)-1))/($B$6-1)))) | L34: =IF(A34="","",IF(OR(P34<>1,$B$8<>"Ready"),"n.a.",$G$5*J34+$G$6*K34)) | M34: =IF(A34="","",IF(NOT(ISNUMBER(L34)),"n.a.",1+COUNTIFS($P$14:$P$63,1,$L$14:$L$63,">"&L34))) | N34: =IF(A34="","",COUNTIFS(Relationships!$A$6:$A$205,A34,Relationships!$V$6:$V$205,1)) | O34: =IF(A34="","",IF(Q34<>1,"Outside cap universe",IF(R34<>1,"Duplicate network issuer",IF(C34<>"Yes","Review incomplete",IF(OR(NOT(ISNUMBER(D34)),D34>Rules!$B$6,Rules!$B$6-D34>Rules!$B$42,E34=""),"Check review date/log",IF(N34>0,"Resolve included records",IF($B$8<>"Ready",$B$8,IF(F34=0,"Reviewed: no qualifying ties","Ranked")))))))) | P34: =IF(A34="",0,IF(AND(Q34=1,R34=1,C34="Yes",ISNUMBER(D34),D34<=Rules!$B$6,Rules!$B$6-D34<=Rules!$B$42,E34<>"",N34=0),1,0)) -> 0 | Q34: {=IF(A34="",0,IF(COUNTIF(Companies!$A$6:$A$55,A34)<>1,0,IF(AND(INDEX(Companies!$R$6:$R$55,MATCH(A34,Companies!$A$6:$A$55,0))=1,INDEX(Companies!$I$6:$I$55,MATCH(A34,Companies!$A$6:$A$55,0))>=MAX(10,Rules!$B$22)),1,0)))} -> 0 | R34: =IF(A34="","",COUNTIF($A$14:$A$63,A34)) | S34: =IF(P34<>1,"",IF(F34=0,0,I34))
B35: {=IF(A35="","",IF(COUNTIF(Companies!$A$6:$A$55,A35)<>1,"n.a.",INDEX(Companies!$C$6:$C$55,MATCH(A35,Companies!$A$6:$A$55,0))))} | F35: =IF(A35="","",COUNTIFS(Relationships!$A$6:$A$205,A35,Relationships!$U$6:$U$205,1)) | G35: =IF(A35="","",COUNTIFS(Relationships!$A$6:$A$205,A35,Relationships!$U$6:$U$205,1,Relationships!$C$6:$C$205,"Client")+COUNTIFS(Relationships!$A$6:$A$205,A35,Relationships!$U$6:$U$205,1,Relationships!$C$6:$C$205,"Client and partner")) | H35: =IF(A35="","",COUNTIFS(Relationships!$A$6:$A$205,A35,Relationships!$U$6:$U$205,1,Relationships!$C$6:$C$205,"Partner")+COUNTIFS(Relationships!$A$6:$A$205,A35,Relationships!$U$6:$U$205,1,Relationships!$C$6:$C$205,"Client and partner")) | I35: =IFERROR(__xludf.DUMMYFUNCTION("IF(A35="""","""",IF(F35=0,""n.a."",MEDIAN(FILTER(Relationships!$Q$6:$Q$205,Relationships!$A$6:$A$205=A35,Relationships!$U$6:$U$205=1))))"),"") | J35: =IF(A35="","",IF(OR(P35<>1,$B$8<>"Ready"),"n.a.",IF(F35=0,0,100*(COUNTIFS($P$14:$P$63,1,$F$14:$F$63,"<"&F35)+0.5*(COUNTIFS($P$14:$P$63,1,$F$14:$F$63,F35)-1))/($B$6-1)))) | K35: =IF(A35="","",IF(OR(P35<>1,$B$8<>"Ready"),"n.a.",IF(F35=0,0,100*(COUNTIFS($P$14:$P$63,1,$S$14:$S$63,"<"&I35)+0.5*(COUNTIFS($P$14:$P$63,1,$S$14:$S$63,I35)-1))/($B$6-1)))) | L35: =IF(A35="","",IF(OR(P35<>1,$B$8<>"Ready"),"n.a.",$G$5*J35+$G$6*K35)) | M35: =IF(A35="","",IF(NOT(ISNUMBER(L35)),"n.a.",1+COUNTIFS($P$14:$P$63,1,$L$14:$L$63,">"&L35))) | N35: =IF(A35="","",COUNTIFS(Relationships!$A$6:$A$205,A35,Relationships!$V$6:$V$205,1)) | O35: =IF(A35="","",IF(Q35<>1,"Outside cap universe",IF(R35<>1,"Duplicate network issuer",IF(C35<>"Yes","Review incomplete",IF(OR(NOT(ISNUMBER(D35)),D35>Rules!$B$6,Rules!$B$6-D35>Rules!$B$42,E35=""),"Check review date/log",IF(N35>0,"Resolve included records",IF($B$8<>"Ready",$B$8,IF(F35=0,"Reviewed: no qualifying ties","Ranked")))))))) | P35: =IF(A35="",0,IF(AND(Q35=1,R35=1,C35="Yes",ISNUMBER(D35),D35<=Rules!$B$6,Rules!$B$6-D35<=Rules!$B$42,E35<>"",N35=0),1,0)) -> 0 | Q35: {=IF(A35="",0,IF(COUNTIF(Companies!$A$6:$A$55,A35)<>1,0,IF(AND(INDEX(Companies!$R$6:$R$55,MATCH(A35,Companies!$A$6:$A$55,0))=1,INDEX(Companies!$I$6:$I$55,MATCH(A35,Companies!$A$6:$A$55,0))>=MAX(10,Rules!$B$22)),1,0)))} -> 0 | R35: =IF(A35="","",COUNTIF($A$14:$A$63,A35)) | S35: =IF(P35<>1,"",IF(F35=0,0,I35))
B36: {=IF(A36="","",IF(COUNTIF(Companies!$A$6:$A$55,A36)<>1,"n.a.",INDEX(Companies!$C$6:$C$55,MATCH(A36,Companies!$A$6:$A$55,0))))} | F36: =IF(A36="","",COUNTIFS(Relationships!$A$6:$A$205,A36,Relationships!$U$6:$U$205,1)) | G36: =IF(A36="","",COUNTIFS(Relationships!$A$6:$A$205,A36,Relationships!$U$6:$U$205,1,Relationships!$C$6:$C$205,"Client")+COUNTIFS(Relationships!$A$6:$A$205,A36,Relationships!$U$6:$U$205,1,Relationships!$C$6:$C$205,"Client and partner")) | H36: =IF(A36="","",COUNTIFS(Relationships!$A$6:$A$205,A36,Relationships!$U$6:$U$205,1,Relationships!$C$6:$C$205,"Partner")+COUNTIFS(Relationships!$A$6:$A$205,A36,Relationships!$U$6:$U$205,1,Relationships!$C$6:$C$205,"Client and partner")) | I36: =IFERROR(__xludf.DUMMYFUNCTION("IF(A36="""","""",IF(F36=0,""n.a."",MEDIAN(FILTER(Relationships!$Q$6:$Q$205,Relationships!$A$6:$A$205=A36,Relationships!$U$6:$U$205=1))))"),"") | J36: =IF(A36="","",IF(OR(P36<>1,$B$8<>"Ready"),"n.a.",IF(F36=0,0,100*(COUNTIFS($P$14:$P$63,1,$F$14:$F$63,"<"&F36)+0.5*(COUNTIFS($P$14:$P$63,1,$F$14:$F$63,F36)-1))/($B$6-1)))) | K36: =IF(A36="","",IF(OR(P36<>1,$B$8<>"Ready"),"n.a.",IF(F36=0,0,100*(COUNTIFS($P$14:$P$63,1,$S$14:$S$63,"<"&I36)+0.5*(COUNTIFS($P$14:$P$63,1,$S$14:$S$63,I36)-1))/($B$6-1)))) | L36: =IF(A36="","",IF(OR(P36<>1,$B$8<>"Ready"),"n.a.",$G$5*J36+$G$6*K36)) | M36: =IF(A36="","",IF(NOT(ISNUMBER(L36)),"n.a.",1+COUNTIFS($P$14:$P$63,1,$L$14:$L$63,">"&L36))) | N36: =IF(A36="","",COUNTIFS(Relationships!$A$6:$A$205,A36,Relationships!$V$6:$V$205,1)) | O36: =IF(A36="","",IF(Q36<>1,"Outside cap universe",IF(R36<>1,"Duplicate network issuer",IF(C36<>"Yes","Review incomplete",IF(OR(NOT(ISNUMBER(D36)),D36>Rules!$B$6,Rules!$B$6-D36>Rules!$B$42,E36=""),"Check review date/log",IF(N36>0,"Resolve included records",IF($B$8<>"Ready",$B$8,IF(F36=0,"Reviewed: no qualifying ties","Ranked")))))))) | P36: =IF(A36="",0,IF(AND(Q36=1,R36=1,C36="Yes",ISNUMBER(D36),D36<=Rules!$B$6,Rules!$B$6-D36<=Rules!$B$42,E36<>"",N36=0),1,0)) -> 0 | Q36: {=IF(A36="",0,IF(COUNTIF(Companies!$A$6:$A$55,A36)<>1,0,IF(AND(INDEX(Companies!$R$6:$R$55,MATCH(A36,Companies!$A$6:$A$55,0))=1,INDEX(Companies!$I$6:$I$55,MATCH(A36,Companies!$A$6:$A$55,0))>=MAX(10,Rules!$B$22)),1,0)))} -> 0 | R36: =IF(A36="","",COUNTIF($A$14:$A$63,A36)) | S36: =IF(P36<>1,"",IF(F36=0,0,I36))
B37: {=IF(A37="","",IF(COUNTIF(Companies!$A$6:$A$55,A37)<>1,"n.a.",INDEX(Companies!$C$6:$C$55,MATCH(A37,Companies!$A$6:$A$55,0))))} | F37: =IF(A37="","",COUNTIFS(Relationships!$A$6:$A$205,A37,Relationships!$U$6:$U$205,1)) | G37: =IF(A37="","",COUNTIFS(Relationships!$A$6:$A$205,A37,Relationships!$U$6:$U$205,1,Relationships!$C$6:$C$205,"Client")+COUNTIFS(Relationships!$A$6:$A$205,A37,Relationships!$U$6:$U$205,1,Relationships!$C$6:$C$205,"Client and partner")) | H37: =IF(A37="","",COUNTIFS(Relationships!$A$6:$A$205,A37,Relationships!$U$6:$U$205,1,Relationships!$C$6:$C$205,"Partner")+COUNTIFS(Relationships!$A$6:$A$205,A37,Relationships!$U$6:$U$205,1,Relationships!$C$6:$C$205,"Client and partner")) | I37: =IFERROR(__xludf.DUMMYFUNCTION("IF(A37="""","""",IF(F37=0,""n.a."",MEDIAN(FILTER(Relationships!$Q$6:$Q$205,Relationships!$A$6:$A$205=A37,Relationships!$U$6:$U$205=1))))"),"") | J37: =IF(A37="","",IF(OR(P37<>1,$B$8<>"Ready"),"n.a.",IF(F37=0,0,100*(COUNTIFS($P$14:$P$63,1,$F$14:$F$63,"<"&F37)+0.5*(COUNTIFS($P$14:$P$63,1,$F$14:$F$63,F37)-1))/($B$6-1)))) | K37: =IF(A37="","",IF(OR(P37<>1,$B$8<>"Ready"),"n.a.",IF(F37=0,0,100*(COUNTIFS($P$14:$P$63,1,$S$14:$S$63,"<"&I37)+0.5*(COUNTIFS($P$14:$P$63,1,$S$14:$S$63,I37)-1))/($B$6-1)))) | L37: =IF(A37="","",IF(OR(P37<>1,$B$8<>"Ready"),"n.a.",$G$5*J37+$G$6*K37)) | M37: =IF(A37="","",IF(NOT(ISNUMBER(L37)),"n.a.",1+COUNTIFS($P$14:$P$63,1,$L$14:$L$63,">"&L37))) | N37: =IF(A37="","",COUNTIFS(Relationships!$A$6:$A$205,A37,Relationships!$V$6:$V$205,1)) | O37: =IF(A37="","",IF(Q37<>1,"Outside cap universe",IF(R37<>1,"Duplicate network issuer",IF(C37<>"Yes","Review incomplete",IF(OR(NOT(ISNUMBER(D37)),D37>Rules!$B$6,Rules!$B$6-D37>Rules!$B$42,E37=""),"Check review date/log",IF(N37>0,"Resolve included records",IF($B$8<>"Ready",$B$8,IF(F37=0,"Reviewed: no qualifying ties","Ranked")))))))) | P37: =IF(A37="",0,IF(AND(Q37=1,R37=1,C37="Yes",ISNUMBER(D37),D37<=Rules!$B$6,Rules!$B$6-D37<=Rules!$B$42,E37<>"",N37=0),1,0)) -> 0 | Q37: {=IF(A37="",0,IF(COUNTIF(Companies!$A$6:$A$55,A37)<>1,0,IF(AND(INDEX(Companies!$R$6:$R$55,MATCH(A37,Companies!$A$6:$A$55,0))=1,INDEX(Companies!$I$6:$I$55,MATCH(A37,Companies!$A$6:$A$55,0))>=MAX(10,Rules!$B$22)),1,0)))} -> 0 | R37: =IF(A37="","",COUNTIF($A$14:$A$63,A37)) | S37: =IF(P37<>1,"",IF(F37=0,0,I37))
B38: {=IF(A38="","",IF(COUNTIF(Companies!$A$6:$A$55,A38)<>1,"n.a.",INDEX(Companies!$C$6:$C$55,MATCH(A38,Companies!$A$6:$A$55,0))))} | F38: =IF(A38="","",COUNTIFS(Relationships!$A$6:$A$205,A38,Relationships!$U$6:$U$205,1)) | G38: =IF(A38="","",COUNTIFS(Relationships!$A$6:$A$205,A38,Relationships!$U$6:$U$205,1,Relationships!$C$6:$C$205,"Client")+COUNTIFS(Relationships!$A$6:$A$205,A38,Relationships!$U$6:$U$205,1,Relationships!$C$6:$C$205,"Client and partner")) | H38: =IF(A38="","",COUNTIFS(Relationships!$A$6:$A$205,A38,Relationships!$U$6:$U$205,1,Relationships!$C$6:$C$205,"Partner")+COUNTIFS(Relationships!$A$6:$A$205,A38,Relationships!$U$6:$U$205,1,Relationships!$C$6:$C$205,"Client and partner")) | I38: =IFERROR(__xludf.DUMMYFUNCTION("IF(A38="""","""",IF(F38=0,""n.a."",MEDIAN(FILTER(Relationships!$Q$6:$Q$205,Relationships!$A$6:$A$205=A38,Relationships!$U$6:$U$205=1))))"),"") | J38: =IF(A38="","",IF(OR(P38<>1,$B$8<>"Ready"),"n.a.",IF(F38=0,0,100*(COUNTIFS($P$14:$P$63,1,$F$14:$F$63,"<"&F38)+0.5*(COUNTIFS($P$14:$P$63,1,$F$14:$F$63,F38)-1))/($B$6-1)))) | K38: =IF(A38="","",IF(OR(P38<>1,$B$8<>"Ready"),"n.a.",IF(F38=0,0,100*(COUNTIFS($P$14:$P$63,1,$S$14:$S$63,"<"&I38)+0.5*(COUNTIFS($P$14:$P$63,1,$S$14:$S$63,I38)-1))/($B$6-1)))) | L38: =IF(A38="","",IF(OR(P38<>1,$B$8<>"Ready"),"n.a.",$G$5*J38+$G$6*K38)) | M38: =IF(A38="","",IF(NOT(ISNUMBER(L38)),"n.a.",1+COUNTIFS($P$14:$P$63,1,$L$14:$L$63,">"&L38))) | N38: =IF(A38="","",COUNTIFS(Relationships!$A$6:$A$205,A38,Relationships!$V$6:$V$205,1)) | O38: =IF(A38="","",IF(Q38<>1,"Outside cap universe",IF(R38<>1,"Duplicate network issuer",IF(C38<>"Yes","Review incomplete",IF(OR(NOT(ISNUMBER(D38)),D38>Rules!$B$6,Rules!$B$6-D38>Rules!$B$42,E38=""),"Check review date/log",IF(N38>0,"Resolve included records",IF($B$8<>"Ready",$B$8,IF(F38=0,"Reviewed: no qualifying ties","Ranked")))))))) | P38: =IF(A38="",0,IF(AND(Q38=1,R38=1,C38="Yes",ISNUMBER(D38),D38<=Rules!$B$6,Rules!$B$6-D38<=Rules!$B$42,E38<>"",N38=0),1,0)) -> 0 | Q38: {=IF(A38="",0,IF(COUNTIF(Companies!$A$6:$A$55,A38)<>1,0,IF(AND(INDEX(Companies!$R$6:$R$55,MATCH(A38,Companies!$A$6:$A$55,0))=1,INDEX(Companies!$I$6:$I$55,MATCH(A38,Companies!$A$6:$A$55,0))>=MAX(10,Rules!$B$22)),1,0)))} -> 0 | R38: =IF(A38="","",COUNTIF($A$14:$A$63,A38)) | S38: =IF(P38<>1,"",IF(F38=0,0,I38))
B39: {=IF(A39="","",IF(COUNTIF(Companies!$A$6:$A$55,A39)<>1,"n.a.",INDEX(Companies!$C$6:$C$55,MATCH(A39,Companies!$A$6:$A$55,0))))} | F39: =IF(A39="","",COUNTIFS(Relationships!$A$6:$A$205,A39,Relationships!$U$6:$U$205,1)) | G39: =IF(A39="","",COUNTIFS(Relationships!$A$6:$A$205,A39,Relationships!$U$6:$U$205,1,Relationships!$C$6:$C$205,"Client")+COUNTIFS(Relationships!$A$6:$A$205,A39,Relationships!$U$6:$U$205,1,Relationships!$C$6:$C$205,"Client and partner")) | H39: =IF(A39="","",COUNTIFS(Relationships!$A$6:$A$205,A39,Relationships!$U$6:$U$205,1,Relationships!$C$6:$C$205,"Partner")+COUNTIFS(Relationships!$A$6:$A$205,A39,Relationships!$U$6:$U$205,1,Relationships!$C$6:$C$205,"Client and partner")) | I39: =IFERROR(__xludf.DUMMYFUNCTION("IF(A39="""","""",IF(F39=0,""n.a."",MEDIAN(FILTER(Relationships!$Q$6:$Q$205,Relationships!$A$6:$A$205=A39,Relationships!$U$6:$U$205=1))))"),"") | J39: =IF(A39="","",IF(OR(P39<>1,$B$8<>"Ready"),"n.a.",IF(F39=0,0,100*(COUNTIFS($P$14:$P$63,1,$F$14:$F$63,"<"&F39)+0.5*(COUNTIFS($P$14:$P$63,1,$F$14:$F$63,F39)-1))/($B$6-1)))) | K39: =IF(A39="","",IF(OR(P39<>1,$B$8<>"Ready"),"n.a.",IF(F39=0,0,100*(COUNTIFS($P$14:$P$63,1,$S$14:$S$63,"<"&I39)+0.5*(COUNTIFS($P$14:$P$63,1,$S$14:$S$63,I39)-1))/($B$6-1)))) | L39: =IF(A39="","",IF(OR(P39<>1,$B$8<>"Ready"),"n.a.",$G$5*J39+$G$6*K39)) | M39: =IF(A39="","",IF(NOT(ISNUMBER(L39)),"n.a.",1+COUNTIFS($P$14:$P$63,1,$L$14:$L$63,">"&L39))) | N39: =IF(A39="","",COUNTIFS(Relationships!$A$6:$A$205,A39,Relationships!$V$6:$V$205,1)) | O39: =IF(A39="","",IF(Q39<>1,"Outside cap universe",IF(R39<>1,"Duplicate network issuer",IF(C39<>"Yes","Review incomplete",IF(OR(NOT(ISNUMBER(D39)),D39>Rules!$B$6,Rules!$B$6-D39>Rules!$B$42,E39=""),"Check review date/log",IF(N39>0,"Resolve included records",IF($B$8<>"Ready",$B$8,IF(F39=0,"Reviewed: no qualifying ties","Ranked")))))))) | P39: =IF(A39="",0,IF(AND(Q39=1,R39=1,C39="Yes",ISNUMBER(D39),D39<=Rules!$B$6,Rules!$B$6-D39<=Rules!$B$42,E39<>"",N39=0),1,0)) -> 0 | Q39: {=IF(A39="",0,IF(COUNTIF(Companies!$A$6:$A$55,A39)<>1,0,IF(AND(INDEX(Companies!$R$6:$R$55,MATCH(A39,Companies!$A$6:$A$55,0))=1,INDEX(Companies!$I$6:$I$55,MATCH(A39,Companies!$A$6:$A$55,0))>=MAX(10,Rules!$B$22)),1,0)))} -> 0 | R39: =IF(A39="","",COUNTIF($A$14:$A$63,A39)) | S39: =IF(P39<>1,"",IF(F39=0,0,I39))
B40: {=IF(A40="","",IF(COUNTIF(Companies!$A$6:$A$55,A40)<>1,"n.a.",INDEX(Companies!$C$6:$C$55,MATCH(A40,Companies!$A$6:$A$55,0))))} | F40: =IF(A40="","",COUNTIFS(Relationships!$A$6:$A$205,A40,Relationships!$U$6:$U$205,1)) | G40: =IF(A40="","",COUNTIFS(Relationships!$A$6:$A$205,A40,Relationships!$U$6:$U$205,1,Relationships!$C$6:$C$205,"Client")+COUNTIFS(Relationships!$A$6:$A$205,A40,Relationships!$U$6:$U$205,1,Relationships!$C$6:$C$205,"Client and partner")) | H40: =IF(A40="","",COUNTIFS(Relationships!$A$6:$A$205,A40,Relationships!$U$6:$U$205,1,Relationships!$C$6:$C$205,"Partner")+COUNTIFS(Relationships!$A$6:$A$205,A40,Relationships!$U$6:$U$205,1,Relationships!$C$6:$C$205,"Client and partner")) | I40: =IFERROR(__xludf.DUMMYFUNCTION("IF(A40="""","""",IF(F40=0,""n.a."",MEDIAN(FILTER(Relationships!$Q$6:$Q$205,Relationships!$A$6:$A$205=A40,Relationships!$U$6:$U$205=1))))"),"") | J40: =IF(A40="","",IF(OR(P40<>1,$B$8<>"Ready"),"n.a.",IF(F40=0,0,100*(COUNTIFS($P$14:$P$63,1,$F$14:$F$63,"<"&F40)+0.5*(COUNTIFS($P$14:$P$63,1,$F$14:$F$63,F40)-1))/($B$6-1)))) | K40: =IF(A40="","",IF(OR(P40<>1,$B$8<>"Ready"),"n.a.",IF(F40=0,0,100*(COUNTIFS($P$14:$P$63,1,$S$14:$S$63,"<"&I40)+0.5*(COUNTIFS($P$14:$P$63,1,$S$14:$S$63,I40)-1))/($B$6-1)))) | L40: =IF(A40="","",IF(OR(P40<>1,$B$8<>"Ready"),"n.a.",$G$5*J40+$G$6*K40)) | M40: =IF(A40="","",IF(NOT(ISNUMBER(L40)),"n.a.",1+COUNTIFS($P$14:$P$63,1,$L$14:$L$63,">"&L40))) | N40: =IF(A40="","",COUNTIFS(Relationships!$A$6:$A$205,A40,Relationships!$V$6:$V$205,1)) | O40: =IF(A40="","",IF(Q40<>1,"Outside cap universe",IF(R40<>1,"Duplicate network issuer",IF(C40<>"Yes","Review incomplete",IF(OR(NOT(ISNUMBER(D40)),D40>Rules!$B$6,Rules!$B$6-D40>Rules!$B$42,E40=""),"Check review date/log",IF(N40>0,"Resolve included records",IF($B$8<>"Ready",$B$8,IF(F40=0,"Reviewed: no qualifying ties","Ranked")))))))) | P40: =IF(A40="",0,IF(AND(Q40=1,R40=1,C40="Yes",ISNUMBER(D40),D40<=Rules!$B$6,Rules!$B$6-D40<=Rules!$B$42,E40<>"",N40=0),1,0)) -> 0 | Q40: {=IF(A40="",0,IF(COUNTIF(Companies!$A$6:$A$55,A40)<>1,0,IF(AND(INDEX(Companies!$R$6:$R$55,MATCH(A40,Companies!$A$6:$A$55,0))=1,INDEX(Companies!$I$6:$I$55,MATCH(A40,Companies!$A$6:$A$55,0))>=MAX(10,Rules!$B$22)),1,0)))} -> 0 | R40: =IF(A40="","",COUNTIF($A$14:$A$63,A40)) | S40: =IF(P40<>1,"",IF(F40=0,0,I40))
B41: {=IF(A41="","",IF(COUNTIF(Companies!$A$6:$A$55,A41)<>1,"n.a.",INDEX(Companies!$C$6:$C$55,MATCH(A41,Companies!$A$6:$A$55,0))))} | F41: =IF(A41="","",COUNTIFS(Relationships!$A$6:$A$205,A41,Relationships!$U$6:$U$205,1)) | G41: =IF(A41="","",COUNTIFS(Relationships!$A$6:$A$205,A41,Relationships!$U$6:$U$205,1,Relationships!$C$6:$C$205,"Client")+COUNTIFS(Relationships!$A$6:$A$205,A41,Relationships!$U$6:$U$205,1,Relationships!$C$6:$C$205,"Client and partner")) | H41: =IF(A41="","",COUNTIFS(Relationships!$A$6:$A$205,A41,Relationships!$U$6:$U$205,1,Relationships!$C$6:$C$205,"Partner")+COUNTIFS(Relationships!$A$6:$A$205,A41,Relationships!$U$6:$U$205,1,Relationships!$C$6:$C$205,"Client and partner")) | I41: =IFERROR(__xludf.DUMMYFUNCTION("IF(A41="""","""",IF(F41=0,""n.a."",MEDIAN(FILTER(Relationships!$Q$6:$Q$205,Relationships!$A$6:$A$205=A41,Relationships!$U$6:$U$205=1))))"),"") | J41: =IF(A41="","",IF(OR(P41<>1,$B$8<>"Ready"),"n.a.",IF(F41=0,0,100*(COUNTIFS($P$14:$P$63,1,$F$14:$F$63,"<"&F41)+0.5*(COUNTIFS($P$14:$P$63,1,$F$14:$F$63,F41)-1))/($B$6-1)))) | K41: =IF(A41="","",IF(OR(P41<>1,$B$8<>"Ready"),"n.a.",IF(F41=0,0,100*(COUNTIFS($P$14:$P$63,1,$S$14:$S$63,"<"&I41)+0.5*(COUNTIFS($P$14:$P$63,1,$S$14:$S$63,I41)-1))/($B$6-1)))) | L41: =IF(A41="","",IF(OR(P41<>1,$B$8<>"Ready"),"n.a.",$G$5*J41+$G$6*K41)) | M41: =IF(A41="","",IF(NOT(ISNUMBER(L41)),"n.a.",1+COUNTIFS($P$14:$P$63,1,$L$14:$L$63,">"&L41))) | N41: =IF(A41="","",COUNTIFS(Relationships!$A$6:$A$205,A41,Relationships!$V$6:$V$205,1)) | O41: =IF(A41="","",IF(Q41<>1,"Outside cap universe",IF(R41<>1,"Duplicate network issuer",IF(C41<>"Yes","Review incomplete",IF(OR(NOT(ISNUMBER(D41)),D41>Rules!$B$6,Rules!$B$6-D41>Rules!$B$42,E41=""),"Check review date/log",IF(N41>0,"Resolve included records",IF($B$8<>"Ready",$B$8,IF(F41=0,"Reviewed: no qualifying ties","Ranked")))))))) | P41: =IF(A41="",0,IF(AND(Q41=1,R41=1,C41="Yes",ISNUMBER(D41),D41<=Rules!$B$6,Rules!$B$6-D41<=Rules!$B$42,E41<>"",N41=0),1,0)) -> 0 | Q41: {=IF(A41="",0,IF(COUNTIF(Companies!$A$6:$A$55,A41)<>1,0,IF(AND(INDEX(Companies!$R$6:$R$55,MATCH(A41,Companies!$A$6:$A$55,0))=1,INDEX(Companies!$I$6:$I$55,MATCH(A41,Companies!$A$6:$A$55,0))>=MAX(10,Rules!$B$22)),1,0)))} -> 0 | R41: =IF(A41="","",COUNTIF($A$14:$A$63,A41)) | S41: =IF(P41<>1,"",IF(F41=0,0,I41))
B42: {=IF(A42="","",IF(COUNTIF(Companies!$A$6:$A$55,A42)<>1,"n.a.",INDEX(Companies!$C$6:$C$55,MATCH(A42,Companies!$A$6:$A$55,0))))} | F42: =IF(A42="","",COUNTIFS(Relationships!$A$6:$A$205,A42,Relationships!$U$6:$U$205,1)) | G42: =IF(A42="","",COUNTIFS(Relationships!$A$6:$A$205,A42,Relationships!$U$6:$U$205,1,Relationships!$C$6:$C$205,"Client")+COUNTIFS(Relationships!$A$6:$A$205,A42,Relationships!$U$6:$U$205,1,Relationships!$C$6:$C$205,"Client and partner")) | H42: =IF(A42="","",COUNTIFS(Relationships!$A$6:$A$205,A42,Relationships!$U$6:$U$205,1,Relationships!$C$6:$C$205,"Partner")+COUNTIFS(Relationships!$A$6:$A$205,A42,Relationships!$U$6:$U$205,1,Relationships!$C$6:$C$205,"Client and partner")) | I42: =IFERROR(__xludf.DUMMYFUNCTION("IF(A42="""","""",IF(F42=0,""n.a."",MEDIAN(FILTER(Relationships!$Q$6:$Q$205,Relationships!$A$6:$A$205=A42,Relationships!$U$6:$U$205=1))))"),"") | J42: =IF(A42="","",IF(OR(P42<>1,$B$8<>"Ready"),"n.a.",IF(F42=0,0,100*(COUNTIFS($P$14:$P$63,1,$F$14:$F$63,"<"&F42)+0.5*(COUNTIFS($P$14:$P$63,1,$F$14:$F$63,F42)-1))/($B$6-1)))) | K42: =IF(A42="","",IF(OR(P42<>1,$B$8<>"Ready"),"n.a.",IF(F42=0,0,100*(COUNTIFS($P$14:$P$63,1,$S$14:$S$63,"<"&I42)+0.5*(COUNTIFS($P$14:$P$63,1,$S$14:$S$63,I42)-1))/($B$6-1)))) | L42: =IF(A42="","",IF(OR(P42<>1,$B$8<>"Ready"),"n.a.",$G$5*J42+$G$6*K42)) | M42: =IF(A42="","",IF(NOT(ISNUMBER(L42)),"n.a.",1+COUNTIFS($P$14:$P$63,1,$L$14:$L$63,">"&L42))) | N42: =IF(A42="","",COUNTIFS(Relationships!$A$6:$A$205,A42,Relationships!$V$6:$V$205,1)) | O42: =IF(A42="","",IF(Q42<>1,"Outside cap universe",IF(R42<>1,"Duplicate network issuer",IF(C42<>"Yes","Review incomplete",IF(OR(NOT(ISNUMBER(D42)),D42>Rules!$B$6,Rules!$B$6-D42>Rules!$B$42,E42=""),"Check review date/log",IF(N42>0,"Resolve included records",IF($B$8<>"Ready",$B$8,IF(F42=0,"Reviewed: no qualifying ties","Ranked")))))))) | P42: =IF(A42="",0,IF(AND(Q42=1,R42=1,C42="Yes",ISNUMBER(D42),D42<=Rules!$B$6,Rules!$B$6-D42<=Rules!$B$42,E42<>"",N42=0),1,0)) -> 0 | Q42: {=IF(A42="",0,IF(COUNTIF(Companies!$A$6:$A$55,A42)<>1,0,IF(AND(INDEX(Companies!$R$6:$R$55,MATCH(A42,Companies!$A$6:$A$55,0))=1,INDEX(Companies!$I$6:$I$55,MATCH(A42,Companies!$A$6:$A$55,0))>=MAX(10,Rules!$B$22)),1,0)))} -> 0 | R42: =IF(A42="","",COUNTIF($A$14:$A$63,A42)) | S42: =IF(P42<>1,"",IF(F42=0,0,I42))
B43: {=IF(A43="","",IF(COUNTIF(Companies!$A$6:$A$55,A43)<>1,"n.a.",INDEX(Companies!$C$6:$C$55,MATCH(A43,Companies!$A$6:$A$55,0))))} | F43: =IF(A43="","",COUNTIFS(Relationships!$A$6:$A$205,A43,Relationships!$U$6:$U$205,1)) | G43: =IF(A43="","",COUNTIFS(Relationships!$A$6:$A$205,A43,Relationships!$U$6:$U$205,1,Relationships!$C$6:$C$205,"Client")+COUNTIFS(Relationships!$A$6:$A$205,A43,Relationships!$U$6:$U$205,1,Relationships!$C$6:$C$205,"Client and partner")) | H43: =IF(A43="","",COUNTIFS(Relationships!$A$6:$A$205,A43,Relationships!$U$6:$U$205,1,Relationships!$C$6:$C$205,"Partner")+COUNTIFS(Relationships!$A$6:$A$205,A43,Relationships!$U$6:$U$205,1,Relationships!$C$6:$C$205,"Client and partner")) | I43: =IFERROR(__xludf.DUMMYFUNCTION("IF(A43="""","""",IF(F43=0,""n.a."",MEDIAN(FILTER(Relationships!$Q$6:$Q$205,Relationships!$A$6:$A$205=A43,Relationships!$U$6:$U$205=1))))"),"") | J43: =IF(A43="","",IF(OR(P43<>1,$B$8<>"Ready"),"n.a.",IF(F43=0,0,100*(COUNTIFS($P$14:$P$63,1,$F$14:$F$63,"<"&F43)+0.5*(COUNTIFS($P$14:$P$63,1,$F$14:$F$63,F43)-1))/($B$6-1)))) | K43: =IF(A43="","",IF(OR(P43<>1,$B$8<>"Ready"),"n.a.",IF(F43=0,0,100*(COUNTIFS($P$14:$P$63,1,$S$14:$S$63,"<"&I43)+0.5*(COUNTIFS($P$14:$P$63,1,$S$14:$S$63,I43)-1))/($B$6-1)))) | L43: =IF(A43="","",IF(OR(P43<>1,$B$8<>"Ready"),"n.a.",$G$5*J43+$G$6*K43)) | M43: =IF(A43="","",IF(NOT(ISNUMBER(L43)),"n.a.",1+COUNTIFS($P$14:$P$63,1,$L$14:$L$63,">"&L43))) | N43: =IF(A43="","",COUNTIFS(Relationships!$A$6:$A$205,A43,Relationships!$V$6:$V$205,1)) | O43: =IF(A43="","",IF(Q43<>1,"Outside cap universe",IF(R43<>1,"Duplicate network issuer",IF(C43<>"Yes","Review incomplete",IF(OR(NOT(ISNUMBER(D43)),D43>Rules!$B$6,Rules!$B$6-D43>Rules!$B$42,E43=""),"Check review date/log",IF(N43>0,"Resolve included records",IF($B$8<>"Ready",$B$8,IF(F43=0,"Reviewed: no qualifying ties","Ranked")))))))) | P43: =IF(A43="",0,IF(AND(Q43=1,R43=1,C43="Yes",ISNUMBER(D43),D43<=Rules!$B$6,Rules!$B$6-D43<=Rules!$B$42,E43<>"",N43=0),1,0)) -> 0 | Q43: {=IF(A43="",0,IF(COUNTIF(Companies!$A$6:$A$55,A43)<>1,0,IF(AND(INDEX(Companies!$R$6:$R$55,MATCH(A43,Companies!$A$6:$A$55,0))=1,INDEX(Companies!$I$6:$I$55,MATCH(A43,Companies!$A$6:$A$55,0))>=MAX(10,Rules!$B$22)),1,0)))} -> 0 | R43: =IF(A43="","",COUNTIF($A$14:$A$63,A43)) | S43: =IF(P43<>1,"",IF(F43=0,0,I43))
B44: {=IF(A44="","",IF(COUNTIF(Companies!$A$6:$A$55,A44)<>1,"n.a.",INDEX(Companies!$C$6:$C$55,MATCH(A44,Companies!$A$6:$A$55,0))))} | F44: =IF(A44="","",COUNTIFS(Relationships!$A$6:$A$205,A44,Relationships!$U$6:$U$205,1)) | G44: =IF(A44="","",COUNTIFS(Relationships!$A$6:$A$205,A44,Relationships!$U$6:$U$205,1,Relationships!$C$6:$C$205,"Client")+COUNTIFS(Relationships!$A$6:$A$205,A44,Relationships!$U$6:$U$205,1,Relationships!$C$6:$C$205,"Client and partner")) | H44: =IF(A44="","",COUNTIFS(Relationships!$A$6:$A$205,A44,Relationships!$U$6:$U$205,1,Relationships!$C$6:$C$205,"Partner")+COUNTIFS(Relationships!$A$6:$A$205,A44,Relationships!$U$6:$U$205,1,Relationships!$C$6:$C$205,"Client and partner")) | I44: =IFERROR(__xludf.DUMMYFUNCTION("IF(A44="""","""",IF(F44=0,""n.a."",MEDIAN(FILTER(Relationships!$Q$6:$Q$205,Relationships!$A$6:$A$205=A44,Relationships!$U$6:$U$205=1))))"),"") | J44: =IF(A44="","",IF(OR(P44<>1,$B$8<>"Ready"),"n.a.",IF(F44=0,0,100*(COUNTIFS($P$14:$P$63,1,$F$14:$F$63,"<"&F44)+0.5*(COUNTIFS($P$14:$P$63,1,$F$14:$F$63,F44)-1))/($B$6-1)))) | K44: =IF(A44="","",IF(OR(P44<>1,$B$8<>"Ready"),"n.a.",IF(F44=0,0,100*(COUNTIFS($P$14:$P$63,1,$S$14:$S$63,"<"&I44)+0.5*(COUNTIFS($P$14:$P$63,1,$S$14:$S$63,I44)-1))/($B$6-1)))) | L44: =IF(A44="","",IF(OR(P44<>1,$B$8<>"Ready"),"n.a.",$G$5*J44+$G$6*K44)) | M44: =IF(A44="","",IF(NOT(ISNUMBER(L44)),"n.a.",1+COUNTIFS($P$14:$P$63,1,$L$14:$L$63,">"&L44))) | N44: =IF(A44="","",COUNTIFS(Relationships!$A$6:$A$205,A44,Relationships!$V$6:$V$205,1)) | O44: =IF(A44="","",IF(Q44<>1,"Outside cap universe",IF(R44<>1,"Duplicate network issuer",IF(C44<>"Yes","Review incomplete",IF(OR(NOT(ISNUMBER(D44)),D44>Rules!$B$6,Rules!$B$6-D44>Rules!$B$42,E44=""),"Check review date/log",IF(N44>0,"Resolve included records",IF($B$8<>"Ready",$B$8,IF(F44=0,"Reviewed: no qualifying ties","Ranked")))))))) | P44: =IF(A44="",0,IF(AND(Q44=1,R44=1,C44="Yes",ISNUMBER(D44),D44<=Rules!$B$6,Rules!$B$6-D44<=Rules!$B$42,E44<>"",N44=0),1,0)) -> 0 | Q44: {=IF(A44="",0,IF(COUNTIF(Companies!$A$6:$A$55,A44)<>1,0,IF(AND(INDEX(Companies!$R$6:$R$55,MATCH(A44,Companies!$A$6:$A$55,0))=1,INDEX(Companies!$I$6:$I$55,MATCH(A44,Companies!$A$6:$A$55,0))>=MAX(10,Rules!$B$22)),1,0)))} -> 0 | R44: =IF(A44="","",COUNTIF($A$14:$A$63,A44)) | S44: =IF(P44<>1,"",IF(F44=0,0,I44))
B45: {=IF(A45="","",IF(COUNTIF(Companies!$A$6:$A$55,A45)<>1,"n.a.",INDEX(Companies!$C$6:$C$55,MATCH(A45,Companies!$A$6:$A$55,0))))} | F45: =IF(A45="","",COUNTIFS(Relationships!$A$6:$A$205,A45,Relationships!$U$6:$U$205,1)) | G45: =IF(A45="","",COUNTIFS(Relationships!$A$6:$A$205,A45,Relationships!$U$6:$U$205,1,Relationships!$C$6:$C$205,"Client")+COUNTIFS(Relationships!$A$6:$A$205,A45,Relationships!$U$6:$U$205,1,Relationships!$C$6:$C$205,"Client and partner")) | H45: =IF(A45="","",COUNTIFS(Relationships!$A$6:$A$205,A45,Relationships!$U$6:$U$205,1,Relationships!$C$6:$C$205,"Partner")+COUNTIFS(Relationships!$A$6:$A$205,A45,Relationships!$U$6:$U$205,1,Relationships!$C$6:$C$205,"Client and partner")) | I45: =IFERROR(__xludf.DUMMYFUNCTION("IF(A45="""","""",IF(F45=0,""n.a."",MEDIAN(FILTER(Relationships!$Q$6:$Q$205,Relationships!$A$6:$A$205=A45,Relationships!$U$6:$U$205=1))))"),"") | J45: =IF(A45="","",IF(OR(P45<>1,$B$8<>"Ready"),"n.a.",IF(F45=0,0,100*(COUNTIFS($P$14:$P$63,1,$F$14:$F$63,"<"&F45)+0.5*(COUNTIFS($P$14:$P$63,1,$F$14:$F$63,F45)-1))/($B$6-1)))) | K45: =IF(A45="","",IF(OR(P45<>1,$B$8<>"Ready"),"n.a.",IF(F45=0,0,100*(COUNTIFS($P$14:$P$63,1,$S$14:$S$63,"<"&I45)+0.5*(COUNTIFS($P$14:$P$63,1,$S$14:$S$63,I45)-1))/($B$6-1)))) | L45: =IF(A45="","",IF(OR(P45<>1,$B$8<>"Ready"),"n.a.",$G$5*J45+$G$6*K45)) | M45: =IF(A45="","",IF(NOT(ISNUMBER(L45)),"n.a.",1+COUNTIFS($P$14:$P$63,1,$L$14:$L$63,">"&L45))) | N45: =IF(A45="","",COUNTIFS(Relationships!$A$6:$A$205,A45,Relationships!$V$6:$V$205,1)) | O45: =IF(A45="","",IF(Q45<>1,"Outside cap universe",IF(R45<>1,"Duplicate network issuer",IF(C45<>"Yes","Review incomplete",IF(OR(NOT(ISNUMBER(D45)),D45>Rules!$B$6,Rules!$B$6-D45>Rules!$B$42,E45=""),"Check review date/log",IF(N45>0,"Resolve included records",IF($B$8<>"Ready",$B$8,IF(F45=0,"Reviewed: no qualifying ties","Ranked")))))))) | P45: =IF(A45="",0,IF(AND(Q45=1,R45=1,C45="Yes",ISNUMBER(D45),D45<=Rules!$B$6,Rules!$B$6-D45<=Rules!$B$42,E45<>"",N45=0),1,0)) -> 0 | Q45: {=IF(A45="",0,IF(COUNTIF(Companies!$A$6:$A$55,A45)<>1,0,IF(AND(INDEX(Companies!$R$6:$R$55,MATCH(A45,Companies!$A$6:$A$55,0))=1,INDEX(Companies!$I$6:$I$55,MATCH(A45,Companies!$A$6:$A$55,0))>=MAX(10,Rules!$B$22)),1,0)))} -> 0 | R45: =IF(A45="","",COUNTIF($A$14:$A$63,A45)) | S45: =IF(P45<>1,"",IF(F45=0,0,I45))
B46: {=IF(A46="","",IF(COUNTIF(Companies!$A$6:$A$55,A46)<>1,"n.a.",INDEX(Companies!$C$6:$C$55,MATCH(A46,Companies!$A$6:$A$55,0))))} | F46: =IF(A46="","",COUNTIFS(Relationships!$A$6:$A$205,A46,Relationships!$U$6:$U$205,1)) | G46: =IF(A46="","",COUNTIFS(Relationships!$A$6:$A$205,A46,Relationships!$U$6:$U$205,1,Relationships!$C$6:$C$205,"Client")+COUNTIFS(Relationships!$A$6:$A$205,A46,Relationships!$U$6:$U$205,1,Relationships!$C$6:$C$205,"Client and partner")) | H46: =IF(A46="","",COUNTIFS(Relationships!$A$6:$A$205,A46,Relationships!$U$6:$U$205,1,Relationships!$C$6:$C$205,"Partner")+COUNTIFS(Relationships!$A$6:$A$205,A46,Relationships!$U$6:$U$205,1,Relationships!$C$6:$C$205,"Client and partner")) | I46: =IFERROR(__xludf.DUMMYFUNCTION("IF(A46="""","""",IF(F46=0,""n.a."",MEDIAN(FILTER(Relationships!$Q$6:$Q$205,Relationships!$A$6:$A$205=A46,Relationships!$U$6:$U$205=1))))"),"") | J46: =IF(A46="","",IF(OR(P46<>1,$B$8<>"Ready"),"n.a.",IF(F46=0,0,100*(COUNTIFS($P$14:$P$63,1,$F$14:$F$63,"<"&F46)+0.5*(COUNTIFS($P$14:$P$63,1,$F$14:$F$63,F46)-1))/($B$6-1)))) | K46: =IF(A46="","",IF(OR(P46<>1,$B$8<>"Ready"),"n.a.",IF(F46=0,0,100*(COUNTIFS($P$14:$P$63,1,$S$14:$S$63,"<"&I46)+0.5*(COUNTIFS($P$14:$P$63,1,$S$14:$S$63,I46)-1))/($B$6-1)))) | L46: =IF(A46="","",IF(OR(P46<>1,$B$8<>"Ready"),"n.a.",$G$5*J46+$G$6*K46)) | M46: =IF(A46="","",IF(NOT(ISNUMBER(L46)),"n.a.",1+COUNTIFS($P$14:$P$63,1,$L$14:$L$63,">"&L46))) | N46: =IF(A46="","",COUNTIFS(Relationships!$A$6:$A$205,A46,Relationships!$V$6:$V$205,1)) | O46: =IF(A46="","",IF(Q46<>1,"Outside cap universe",IF(R46<>1,"Duplicate network issuer",IF(C46<>"Yes","Review incomplete",IF(OR(NOT(ISNUMBER(D46)),D46>Rules!$B$6,Rules!$B$6-D46>Rules!$B$42,E46=""),"Check review date/log",IF(N46>0,"Resolve included records",IF($B$8<>"Ready",$B$8,IF(F46=0,"Reviewed: no qualifying ties","Ranked")))))))) | P46: =IF(A46="",0,IF(AND(Q46=1,R46=1,C46="Yes",ISNUMBER(D46),D46<=Rules!$B$6,Rules!$B$6-D46<=Rules!$B$42,E46<>"",N46=0),1,0)) -> 0 | Q46: {=IF(A46="",0,IF(COUNTIF(Companies!$A$6:$A$55,A46)<>1,0,IF(AND(INDEX(Companies!$R$6:$R$55,MATCH(A46,Companies!$A$6:$A$55,0))=1,INDEX(Companies!$I$6:$I$55,MATCH(A46,Companies!$A$6:$A$55,0))>=MAX(10,Rules!$B$22)),1,0)))} -> 0 | R46: =IF(A46="","",COUNTIF($A$14:$A$63,A46)) | S46: =IF(P46<>1,"",IF(F46=0,0,I46))
B47: {=IF(A47="","",IF(COUNTIF(Companies!$A$6:$A$55,A47)<>1,"n.a.",INDEX(Companies!$C$6:$C$55,MATCH(A47,Companies!$A$6:$A$55,0))))} | F47: =IF(A47="","",COUNTIFS(Relationships!$A$6:$A$205,A47,Relationships!$U$6:$U$205,1)) | G47: =IF(A47="","",COUNTIFS(Relationships!$A$6:$A$205,A47,Relationships!$U$6:$U$205,1,Relationships!$C$6:$C$205,"Client")+COUNTIFS(Relationships!$A$6:$A$205,A47,Relationships!$U$6:$U$205,1,Relationships!$C$6:$C$205,"Client and partner")) | H47: =IF(A47="","",COUNTIFS(Relationships!$A$6:$A$205,A47,Relationships!$U$6:$U$205,1,Relationships!$C$6:$C$205,"Partner")+COUNTIFS(Relationships!$A$6:$A$205,A47,Relationships!$U$6:$U$205,1,Relationships!$C$6:$C$205,"Client and partner")) | I47: =IFERROR(__xludf.DUMMYFUNCTION("IF(A47="""","""",IF(F47=0,""n.a."",MEDIAN(FILTER(Relationships!$Q$6:$Q$205,Relationships!$A$6:$A$205=A47,Relationships!$U$6:$U$205=1))))"),"") | J47: =IF(A47="","",IF(OR(P47<>1,$B$8<>"Ready"),"n.a.",IF(F47=0,0,100*(COUNTIFS($P$14:$P$63,1,$F$14:$F$63,"<"&F47)+0.5*(COUNTIFS($P$14:$P$63,1,$F$14:$F$63,F47)-1))/($B$6-1)))) | K47: =IF(A47="","",IF(OR(P47<>1,$B$8<>"Ready"),"n.a.",IF(F47=0,0,100*(COUNTIFS($P$14:$P$63,1,$S$14:$S$63,"<"&I47)+0.5*(COUNTIFS($P$14:$P$63,1,$S$14:$S$63,I47)-1))/($B$6-1)))) | L47: =IF(A47="","",IF(OR(P47<>1,$B$8<>"Ready"),"n.a.",$G$5*J47+$G$6*K47)) | M47: =IF(A47="","",IF(NOT(ISNUMBER(L47)),"n.a.",1+COUNTIFS($P$14:$P$63,1,$L$14:$L$63,">"&L47))) | N47: =IF(A47="","",COUNTIFS(Relationships!$A$6:$A$205,A47,Relationships!$V$6:$V$205,1)) | O47: =IF(A47="","",IF(Q47<>1,"Outside cap universe",IF(R47<>1,"Duplicate network issuer",IF(C47<>"Yes","Review incomplete",IF(OR(NOT(ISNUMBER(D47)),D47>Rules!$B$6,Rules!$B$6-D47>Rules!$B$42,E47=""),"Check review date/log",IF(N47>0,"Resolve included records",IF($B$8<>"Ready",$B$8,IF(F47=0,"Reviewed: no qualifying ties","Ranked")))))))) | P47: =IF(A47="",0,IF(AND(Q47=1,R47=1,C47="Yes",ISNUMBER(D47),D47<=Rules!$B$6,Rules!$B$6-D47<=Rules!$B$42,E47<>"",N47=0),1,0)) -> 0 | Q47: {=IF(A47="",0,IF(COUNTIF(Companies!$A$6:$A$55,A47)<>1,0,IF(AND(INDEX(Companies!$R$6:$R$55,MATCH(A47,Companies!$A$6:$A$55,0))=1,INDEX(Companies!$I$6:$I$55,MATCH(A47,Companies!$A$6:$A$55,0))>=MAX(10,Rules!$B$22)),1,0)))} -> 0 | R47: =IF(A47="","",COUNTIF($A$14:$A$63,A47)) | S47: =IF(P47<>1,"",IF(F47=0,0,I47))
B48: {=IF(A48="","",IF(COUNTIF(Companies!$A$6:$A$55,A48)<>1,"n.a.",INDEX(Companies!$C$6:$C$55,MATCH(A48,Companies!$A$6:$A$55,0))))} | F48: =IF(A48="","",COUNTIFS(Relationships!$A$6:$A$205,A48,Relationships!$U$6:$U$205,1)) | G48: =IF(A48="","",COUNTIFS(Relationships!$A$6:$A$205,A48,Relationships!$U$6:$U$205,1,Relationships!$C$6:$C$205,"Client")+COUNTIFS(Relationships!$A$6:$A$205,A48,Relationships!$U$6:$U$205,1,Relationships!$C$6:$C$205,"Client and partner")) | H48: =IF(A48="","",COUNTIFS(Relationships!$A$6:$A$205,A48,Relationships!$U$6:$U$205,1,Relationships!$C$6:$C$205,"Partner")+COUNTIFS(Relationships!$A$6:$A$205,A48,Relationships!$U$6:$U$205,1,Relationships!$C$6:$C$205,"Client and partner")) | I48: =IFERROR(__xludf.DUMMYFUNCTION("IF(A48="""","""",IF(F48=0,""n.a."",MEDIAN(FILTER(Relationships!$Q$6:$Q$205,Relationships!$A$6:$A$205=A48,Relationships!$U$6:$U$205=1))))"),"") | J48: =IF(A48="","",IF(OR(P48<>1,$B$8<>"Ready"),"n.a.",IF(F48=0,0,100*(COUNTIFS($P$14:$P$63,1,$F$14:$F$63,"<"&F48)+0.5*(COUNTIFS($P$14:$P$63,1,$F$14:$F$63,F48)-1))/($B$6-1)))) | K48: =IF(A48="","",IF(OR(P48<>1,$B$8<>"Ready"),"n.a.",IF(F48=0,0,100*(COUNTIFS($P$14:$P$63,1,$S$14:$S$63,"<"&I48)+0.5*(COUNTIFS($P$14:$P$63,1,$S$14:$S$63,I48)-1))/($B$6-1)))) | L48: =IF(A48="","",IF(OR(P48<>1,$B$8<>"Ready"),"n.a.",$G$5*J48+$G$6*K48)) | M48: =IF(A48="","",IF(NOT(ISNUMBER(L48)),"n.a.",1+COUNTIFS($P$14:$P$63,1,$L$14:$L$63,">"&L48))) | N48: =IF(A48="","",COUNTIFS(Relationships!$A$6:$A$205,A48,Relationships!$V$6:$V$205,1)) | O48: =IF(A48="","",IF(Q48<>1,"Outside cap universe",IF(R48<>1,"Duplicate network issuer",IF(C48<>"Yes","Review incomplete",IF(OR(NOT(ISNUMBER(D48)),D48>Rules!$B$6,Rules!$B$6-D48>Rules!$B$42,E48=""),"Check review date/log",IF(N48>0,"Resolve included records",IF($B$8<>"Ready",$B$8,IF(F48=0,"Reviewed: no qualifying ties","Ranked")))))))) | P48: =IF(A48="",0,IF(AND(Q48=1,R48=1,C48="Yes",ISNUMBER(D48),D48<=Rules!$B$6,Rules!$B$6-D48<=Rules!$B$42,E48<>"",N48=0),1,0)) -> 0 | Q48: {=IF(A48="",0,IF(COUNTIF(Companies!$A$6:$A$55,A48)<>1,0,IF(AND(INDEX(Companies!$R$6:$R$55,MATCH(A48,Companies!$A$6:$A$55,0))=1,INDEX(Companies!$I$6:$I$55,MATCH(A48,Companies!$A$6:$A$55,0))>=MAX(10,Rules!$B$22)),1,0)))} -> 0 | R48: =IF(A48="","",COUNTIF($A$14:$A$63,A48)) | S48: =IF(P48<>1,"",IF(F48=0,0,I48))
B49: {=IF(A49="","",IF(COUNTIF(Companies!$A$6:$A$55,A49)<>1,"n.a.",INDEX(Companies!$C$6:$C$55,MATCH(A49,Companies!$A$6:$A$55,0))))} | F49: =IF(A49="","",COUNTIFS(Relationships!$A$6:$A$205,A49,Relationships!$U$6:$U$205,1)) | G49: =IF(A49="","",COUNTIFS(Relationships!$A$6:$A$205,A49,Relationships!$U$6:$U$205,1,Relationships!$C$6:$C$205,"Client")+COUNTIFS(Relationships!$A$6:$A$205,A49,Relationships!$U$6:$U$205,1,Relationships!$C$6:$C$205,"Client and partner")) | H49: =IF(A49="","",COUNTIFS(Relationships!$A$6:$A$205,A49,Relationships!$U$6:$U$205,1,Relationships!$C$6:$C$205,"Partner")+COUNTIFS(Relationships!$A$6:$A$205,A49,Relationships!$U$6:$U$205,1,Relationships!$C$6:$C$205,"Client and partner")) | I49: =IFERROR(__xludf.DUMMYFUNCTION("IF(A49="""","""",IF(F49=0,""n.a."",MEDIAN(FILTER(Relationships!$Q$6:$Q$205,Relationships!$A$6:$A$205=A49,Relationships!$U$6:$U$205=1))))"),"") | J49: =IF(A49="","",IF(OR(P49<>1,$B$8<>"Ready"),"n.a.",IF(F49=0,0,100*(COUNTIFS($P$14:$P$63,1,$F$14:$F$63,"<"&F49)+0.5*(COUNTIFS($P$14:$P$63,1,$F$14:$F$63,F49)-1))/($B$6-1)))) | K49: =IF(A49="","",IF(OR(P49<>1,$B$8<>"Ready"),"n.a.",IF(F49=0,0,100*(COUNTIFS($P$14:$P$63,1,$S$14:$S$63,"<"&I49)+0.5*(COUNTIFS($P$14:$P$63,1,$S$14:$S$63,I49)-1))/($B$6-1)))) | L49: =IF(A49="","",IF(OR(P49<>1,$B$8<>"Ready"),"n.a.",$G$5*J49+$G$6*K49)) | M49: =IF(A49="","",IF(NOT(ISNUMBER(L49)),"n.a.",1+COUNTIFS($P$14:$P$63,1,$L$14:$L$63,">"&L49))) | N49: =IF(A49="","",COUNTIFS(Relationships!$A$6:$A$205,A49,Relationships!$V$6:$V$205,1)) | O49: =IF(A49="","",IF(Q49<>1,"Outside cap universe",IF(R49<>1,"Duplicate network issuer",IF(C49<>"Yes","Review incomplete",IF(OR(NOT(ISNUMBER(D49)),D49>Rules!$B$6,Rules!$B$6-D49>Rules!$B$42,E49=""),"Check review date/log",IF(N49>0,"Resolve included records",IF($B$8<>"Ready",$B$8,IF(F49=0,"Reviewed: no qualifying ties","Ranked")))))))) | P49: =IF(A49="",0,IF(AND(Q49=1,R49=1,C49="Yes",ISNUMBER(D49),D49<=Rules!$B$6,Rules!$B$6-D49<=Rules!$B$42,E49<>"",N49=0),1,0)) -> 0 | Q49: {=IF(A49="",0,IF(COUNTIF(Companies!$A$6:$A$55,A49)<>1,0,IF(AND(INDEX(Companies!$R$6:$R$55,MATCH(A49,Companies!$A$6:$A$55,0))=1,INDEX(Companies!$I$6:$I$55,MATCH(A49,Companies!$A$6:$A$55,0))>=MAX(10,Rules!$B$22)),1,0)))} -> 0 | R49: =IF(A49="","",COUNTIF($A$14:$A$63,A49)) | S49: =IF(P49<>1,"",IF(F49=0,0,I49))
B50: {=IF(A50="","",IF(COUNTIF(Companies!$A$6:$A$55,A50)<>1,"n.a.",INDEX(Companies!$C$6:$C$55,MATCH(A50,Companies!$A$6:$A$55,0))))} | F50: =IF(A50="","",COUNTIFS(Relationships!$A$6:$A$205,A50,Relationships!$U$6:$U$205,1)) | G50: =IF(A50="","",COUNTIFS(Relationships!$A$6:$A$205,A50,Relationships!$U$6:$U$205,1,Relationships!$C$6:$C$205,"Client")+COUNTIFS(Relationships!$A$6:$A$205,A50,Relationships!$U$6:$U$205,1,Relationships!$C$6:$C$205,"Client and partner")) | H50: =IF(A50="","",COUNTIFS(Relationships!$A$6:$A$205,A50,Relationships!$U$6:$U$205,1,Relationships!$C$6:$C$205,"Partner")+COUNTIFS(Relationships!$A$6:$A$205,A50,Relationships!$U$6:$U$205,1,Relationships!$C$6:$C$205,"Client and partner")) | I50: =IFERROR(__xludf.DUMMYFUNCTION("IF(A50="""","""",IF(F50=0,""n.a."",MEDIAN(FILTER(Relationships!$Q$6:$Q$205,Relationships!$A$6:$A$205=A50,Relationships!$U$6:$U$205=1))))"),"") | J50: =IF(A50="","",IF(OR(P50<>1,$B$8<>"Ready"),"n.a.",IF(F50=0,0,100*(COUNTIFS($P$14:$P$63,1,$F$14:$F$63,"<"&F50)+0.5*(COUNTIFS($P$14:$P$63,1,$F$14:$F$63,F50)-1))/($B$6-1)))) | K50: =IF(A50="","",IF(OR(P50<>1,$B$8<>"Ready"),"n.a.",IF(F50=0,0,100*(COUNTIFS($P$14:$P$63,1,$S$14:$S$63,"<"&I50)+0.5*(COUNTIFS($P$14:$P$63,1,$S$14:$S$63,I50)-1))/($B$6-1)))) | L50: =IF(A50="","",IF(OR(P50<>1,$B$8<>"Ready"),"n.a.",$G$5*J50+$G$6*K50)) | M50: =IF(A50="","",IF(NOT(ISNUMBER(L50)),"n.a.",1+COUNTIFS($P$14:$P$63,1,$L$14:$L$63,">"&L50))) | N50: =IF(A50="","",COUNTIFS(Relationships!$A$6:$A$205,A50,Relationships!$V$6:$V$205,1)) | O50: =IF(A50="","",IF(Q50<>1,"Outside cap universe",IF(R50<>1,"Duplicate network issuer",IF(C50<>"Yes","Review incomplete",IF(OR(NOT(ISNUMBER(D50)),D50>Rules!$B$6,Rules!$B$6-D50>Rules!$B$42,E50=""),"Check review date/log",IF(N50>0,"Resolve included records",IF($B$8<>"Ready",$B$8,IF(F50=0,"Reviewed: no qualifying ties","Ranked")))))))) | P50: =IF(A50="",0,IF(AND(Q50=1,R50=1,C50="Yes",ISNUMBER(D50),D50<=Rules!$B$6,Rules!$B$6-D50<=Rules!$B$42,E50<>"",N50=0),1,0)) -> 0 | Q50: {=IF(A50="",0,IF(COUNTIF(Companies!$A$6:$A$55,A50)<>1,0,IF(AND(INDEX(Companies!$R$6:$R$55,MATCH(A50,Companies!$A$6:$A$55,0))=1,INDEX(Companies!$I$6:$I$55,MATCH(A50,Companies!$A$6:$A$55,0))>=MAX(10,Rules!$B$22)),1,0)))} -> 0 | R50: =IF(A50="","",COUNTIF($A$14:$A$63,A50)) | S50: =IF(P50<>1,"",IF(F50=0,0,I50))
B51: {=IF(A51="","",IF(COUNTIF(Companies!$A$6:$A$55,A51)<>1,"n.a.",INDEX(Companies!$C$6:$C$55,MATCH(A51,Companies!$A$6:$A$55,0))))} | F51: =IF(A51="","",COUNTIFS(Relationships!$A$6:$A$205,A51,Relationships!$U$6:$U$205,1)) | G51: =IF(A51="","",COUNTIFS(Relationships!$A$6:$A$205,A51,Relationships!$U$6:$U$205,1,Relationships!$C$6:$C$205,"Client")+COUNTIFS(Relationships!$A$6:$A$205,A51,Relationships!$U$6:$U$205,1,Relationships!$C$6:$C$205,"Client and partner")) | H51: =IF(A51="","",COUNTIFS(Relationships!$A$6:$A$205,A51,Relationships!$U$6:$U$205,1,Relationships!$C$6:$C$205,"Partner")+COUNTIFS(Relationships!$A$6:$A$205,A51,Relationships!$U$6:$U$205,1,Relationships!$C$6:$C$205,"Client and partner")) | I51: =IFERROR(__xludf.DUMMYFUNCTION("IF(A51="""","""",IF(F51=0,""n.a."",MEDIAN(FILTER(Relationships!$Q$6:$Q$205,Relationships!$A$6:$A$205=A51,Relationships!$U$6:$U$205=1))))"),"") | J51: =IF(A51="","",IF(OR(P51<>1,$B$8<>"Ready"),"n.a.",IF(F51=0,0,100*(COUNTIFS($P$14:$P$63,1,$F$14:$F$63,"<"&F51)+0.5*(COUNTIFS($P$14:$P$63,1,$F$14:$F$63,F51)-1))/($B$6-1)))) | K51: =IF(A51="","",IF(OR(P51<>1,$B$8<>"Ready"),"n.a.",IF(F51=0,0,100*(COUNTIFS($P$14:$P$63,1,$S$14:$S$63,"<"&I51)+0.5*(COUNTIFS($P$14:$P$63,1,$S$14:$S$63,I51)-1))/($B$6-1)))) | L51: =IF(A51="","",IF(OR(P51<>1,$B$8<>"Ready"),"n.a.",$G$5*J51+$G$6*K51)) | M51: =IF(A51="","",IF(NOT(ISNUMBER(L51)),"n.a.",1+COUNTIFS($P$14:$P$63,1,$L$14:$L$63,">"&L51))) | N51: =IF(A51="","",COUNTIFS(Relationships!$A$6:$A$205,A51,Relationships!$V$6:$V$205,1)) | O51: =IF(A51="","",IF(Q51<>1,"Outside cap universe",IF(R51<>1,"Duplicate network issuer",IF(C51<>"Yes","Review incomplete",IF(OR(NOT(ISNUMBER(D51)),D51>Rules!$B$6,Rules!$B$6-D51>Rules!$B$42,E51=""),"Check review date/log",IF(N51>0,"Resolve included records",IF($B$8<>"Ready",$B$8,IF(F51=0,"Reviewed: no qualifying ties","Ranked")))))))) | P51: =IF(A51="",0,IF(AND(Q51=1,R51=1,C51="Yes",ISNUMBER(D51),D51<=Rules!$B$6,Rules!$B$6-D51<=Rules!$B$42,E51<>"",N51=0),1,0)) -> 0 | Q51: {=IF(A51="",0,IF(COUNTIF(Companies!$A$6:$A$55,A51)<>1,0,IF(AND(INDEX(Companies!$R$6:$R$55,MATCH(A51,Companies!$A$6:$A$55,0))=1,INDEX(Companies!$I$6:$I$55,MATCH(A51,Companies!$A$6:$A$55,0))>=MAX(10,Rules!$B$22)),1,0)))} -> 0 | R51: =IF(A51="","",COUNTIF($A$14:$A$63,A51)) | S51: =IF(P51<>1,"",IF(F51=0,0,I51))
B52: {=IF(A52="","",IF(COUNTIF(Companies!$A$6:$A$55,A52)<>1,"n.a.",INDEX(Companies!$C$6:$C$55,MATCH(A52,Companies!$A$6:$A$55,0))))} | F52: =IF(A52="","",COUNTIFS(Relationships!$A$6:$A$205,A52,Relationships!$U$6:$U$205,1)) | G52: =IF(A52="","",COUNTIFS(Relationships!$A$6:$A$205,A52,Relationships!$U$6:$U$205,1,Relationships!$C$6:$C$205,"Client")+COUNTIFS(Relationships!$A$6:$A$205,A52,Relationships!$U$6:$U$205,1,Relationships!$C$6:$C$205,"Client and partner")) | H52: =IF(A52="","",COUNTIFS(Relationships!$A$6:$A$205,A52,Relationships!$U$6:$U$205,1,Relationships!$C$6:$C$205,"Partner")+COUNTIFS(Relationships!$A$6:$A$205,A52,Relationships!$U$6:$U$205,1,Relationships!$C$6:$C$205,"Client and partner")) | I52: =IFERROR(__xludf.DUMMYFUNCTION("IF(A52="""","""",IF(F52=0,""n.a."",MEDIAN(FILTER(Relationships!$Q$6:$Q$205,Relationships!$A$6:$A$205=A52,Relationships!$U$6:$U$205=1))))"),"") | J52: =IF(A52="","",IF(OR(P52<>1,$B$8<>"Ready"),"n.a.",IF(F52=0,0,100*(COUNTIFS($P$14:$P$63,1,$F$14:$F$63,"<"&F52)+0.5*(COUNTIFS($P$14:$P$63,1,$F$14:$F$63,F52)-1))/($B$6-1)))) | K52: =IF(A52="","",IF(OR(P52<>1,$B$8<>"Ready"),"n.a.",IF(F52=0,0,100*(COUNTIFS($P$14:$P$63,1,$S$14:$S$63,"<"&I52)+0.5*(COUNTIFS($P$14:$P$63,1,$S$14:$S$63,I52)-1))/($B$6-1)))) | L52: =IF(A52="","",IF(OR(P52<>1,$B$8<>"Ready"),"n.a.",$G$5*J52+$G$6*K52)) | M52: =IF(A52="","",IF(NOT(ISNUMBER(L52)),"n.a.",1+COUNTIFS($P$14:$P$63,1,$L$14:$L$63,">"&L52))) | N52: =IF(A52="","",COUNTIFS(Relationships!$A$6:$A$205,A52,Relationships!$V$6:$V$205,1)) | O52: =IF(A52="","",IF(Q52<>1,"Outside cap universe",IF(R52<>1,"Duplicate network issuer",IF(C52<>"Yes","Review incomplete",IF(OR(NOT(ISNUMBER(D52)),D52>Rules!$B$6,Rules!$B$6-D52>Rules!$B$42,E52=""),"Check review date/log",IF(N52>0,"Resolve included records",IF($B$8<>"Ready",$B$8,IF(F52=0,"Reviewed: no qualifying ties","Ranked")))))))) | P52: =IF(A52="",0,IF(AND(Q52=1,R52=1,C52="Yes",ISNUMBER(D52),D52<=Rules!$B$6,Rules!$B$6-D52<=Rules!$B$42,E52<>"",N52=0),1,0)) -> 0 | Q52: {=IF(A52="",0,IF(COUNTIF(Companies!$A$6:$A$55,A52)<>1,0,IF(AND(INDEX(Companies!$R$6:$R$55,MATCH(A52,Companies!$A$6:$A$55,0))=1,INDEX(Companies!$I$6:$I$55,MATCH(A52,Companies!$A$6:$A$55,0))>=MAX(10,Rules!$B$22)),1,0)))} -> 0 | R52: =IF(A52="","",COUNTIF($A$14:$A$63,A52)) | S52: =IF(P52<>1,"",IF(F52=0,0,I52))
B53: {=IF(A53="","",IF(COUNTIF(Companies!$A$6:$A$55,A53)<>1,"n.a.",INDEX(Companies!$C$6:$C$55,MATCH(A53,Companies!$A$6:$A$55,0))))} | F53: =IF(A53="","",COUNTIFS(Relationships!$A$6:$A$205,A53,Relationships!$U$6:$U$205,1)) | G53: =IF(A53="","",COUNTIFS(Relationships!$A$6:$A$205,A53,Relationships!$U$6:$U$205,1,Relationships!$C$6:$C$205,"Client")+COUNTIFS(Relationships!$A$6:$A$205,A53,Relationships!$U$6:$U$205,1,Relationships!$C$6:$C$205,"Client and partner")) | H53: =IF(A53="","",COUNTIFS(Relationships!$A$6:$A$205,A53,Relationships!$U$6:$U$205,1,Relationships!$C$6:$C$205,"Partner")+COUNTIFS(Relationships!$A$6:$A$205,A53,Relationships!$U$6:$U$205,1,Relationships!$C$6:$C$205,"Client and partner")) | I53: =IFERROR(__xludf.DUMMYFUNCTION("IF(A53="""","""",IF(F53=0,""n.a."",MEDIAN(FILTER(Relationships!$Q$6:$Q$205,Relationships!$A$6:$A$205=A53,Relationships!$U$6:$U$205=1))))"),"") | J53: =IF(A53="","",IF(OR(P53<>1,$B$8<>"Ready"),"n.a.",IF(F53=0,0,100*(COUNTIFS($P$14:$P$63,1,$F$14:$F$63,"<"&F53)+0.5*(COUNTIFS($P$14:$P$63,1,$F$14:$F$63,F53)-1))/($B$6-1)))) | K53: =IF(A53="","",IF(OR(P53<>1,$B$8<>"Ready"),"n.a.",IF(F53=0,0,100*(COUNTIFS($P$14:$P$63,1,$S$14:$S$63,"<"&I53)+0.5*(COUNTIFS($P$14:$P$63,1,$S$14:$S$63,I53)-1))/($B$6-1)))) | L53: =IF(A53="","",IF(OR(P53<>1,$B$8<>"Ready"),"n.a.",$G$5*J53+$G$6*K53)) | M53: =IF(A53="","",IF(NOT(ISNUMBER(L53)),"n.a.",1+COUNTIFS($P$14:$P$63,1,$L$14:$L$63,">"&L53))) | N53: =IF(A53="","",COUNTIFS(Relationships!$A$6:$A$205,A53,Relationships!$V$6:$V$205,1)) | O53: =IF(A53="","",IF(Q53<>1,"Outside cap universe",IF(R53<>1,"Duplicate network issuer",IF(C53<>"Yes","Review incomplete",IF(OR(NOT(ISNUMBER(D53)),D53>Rules!$B$6,Rules!$B$6-D53>Rules!$B$42,E53=""),"Check review date/log",IF(N53>0,"Resolve included records",IF($B$8<>"Ready",$B$8,IF(F53=0,"Reviewed: no qualifying ties","Ranked")))))))) | P53: =IF(A53="",0,IF(AND(Q53=1,R53=1,C53="Yes",ISNUMBER(D53),D53<=Rules!$B$6,Rules!$B$6-D53<=Rules!$B$42,E53<>"",N53=0),1,0)) -> 0 | Q53: {=IF(A53="",0,IF(COUNTIF(Companies!$A$6:$A$55,A53)<>1,0,IF(AND(INDEX(Companies!$R$6:$R$55,MATCH(A53,Companies!$A$6:$A$55,0))=1,INDEX(Companies!$I$6:$I$55,MATCH(A53,Companies!$A$6:$A$55,0))>=MAX(10,Rules!$B$22)),1,0)))} -> 0 | R53: =IF(A53="","",COUNTIF($A$14:$A$63,A53)) | S53: =IF(P53<>1,"",IF(F53=0,0,I53))
B54: {=IF(A54="","",IF(COUNTIF(Companies!$A$6:$A$55,A54)<>1,"n.a.",INDEX(Companies!$C$6:$C$55,MATCH(A54,Companies!$A$6:$A$55,0))))} | F54: =IF(A54="","",COUNTIFS(Relationships!$A$6:$A$205,A54,Relationships!$U$6:$U$205,1)) | G54: =IF(A54="","",COUNTIFS(Relationships!$A$6:$A$205,A54,Relationships!$U$6:$U$205,1,Relationships!$C$6:$C$205,"Client")+COUNTIFS(Relationships!$A$6:$A$205,A54,Relationships!$U$6:$U$205,1,Relationships!$C$6:$C$205,"Client and partner")) | H54: =IF(A54="","",COUNTIFS(Relationships!$A$6:$A$205,A54,Relationships!$U$6:$U$205,1,Relationships!$C$6:$C$205,"Partner")+COUNTIFS(Relationships!$A$6:$A$205,A54,Relationships!$U$6:$U$205,1,Relationships!$C$6:$C$205,"Client and partner")) | I54: =IFERROR(__xludf.DUMMYFUNCTION("IF(A54="""","""",IF(F54=0,""n.a."",MEDIAN(FILTER(Relationships!$Q$6:$Q$205,Relationships!$A$6:$A$205=A54,Relationships!$U$6:$U$205=1))))"),"") | J54: =IF(A54="","",IF(OR(P54<>1,$B$8<>"Ready"),"n.a.",IF(F54=0,0,100*(COUNTIFS($P$14:$P$63,1,$F$14:$F$63,"<"&F54)+0.5*(COUNTIFS($P$14:$P$63,1,$F$14:$F$63,F54)-1))/($B$6-1)))) | K54: =IF(A54="","",IF(OR(P54<>1,$B$8<>"Ready"),"n.a.",IF(F54=0,0,100*(COUNTIFS($P$14:$P$63,1,$S$14:$S$63,"<"&I54)+0.5*(COUNTIFS($P$14:$P$63,1,$S$14:$S$63,I54)-1))/($B$6-1)))) | L54: =IF(A54="","",IF(OR(P54<>1,$B$8<>"Ready"),"n.a.",$G$5*J54+$G$6*K54)) | M54: =IF(A54="","",IF(NOT(ISNUMBER(L54)),"n.a.",1+COUNTIFS($P$14:$P$63,1,$L$14:$L$63,">"&L54))) | N54: =IF(A54="","",COUNTIFS(Relationships!$A$6:$A$205,A54,Relationships!$V$6:$V$205,1)) | O54: =IF(A54="","",IF(Q54<>1,"Outside cap universe",IF(R54<>1,"Duplicate network issuer",IF(C54<>"Yes","Review incomplete",IF(OR(NOT(ISNUMBER(D54)),D54>Rules!$B$6,Rules!$B$6-D54>Rules!$B$42,E54=""),"Check review date/log",IF(N54>0,"Resolve included records",IF($B$8<>"Ready",$B$8,IF(F54=0,"Reviewed: no qualifying ties","Ranked")))))))) | P54: =IF(A54="",0,IF(AND(Q54=1,R54=1,C54="Yes",ISNUMBER(D54),D54<=Rules!$B$6,Rules!$B$6-D54<=Rules!$B$42,E54<>"",N54=0),1,0)) -> 0 | Q54: {=IF(A54="",0,IF(COUNTIF(Companies!$A$6:$A$55,A54)<>1,0,IF(AND(INDEX(Companies!$R$6:$R$55,MATCH(A54,Companies!$A$6:$A$55,0))=1,INDEX(Companies!$I$6:$I$55,MATCH(A54,Companies!$A$6:$A$55,0))>=MAX(10,Rules!$B$22)),1,0)))} -> 0 | R54: =IF(A54="","",COUNTIF($A$14:$A$63,A54)) | S54: =IF(P54<>1,"",IF(F54=0,0,I54))
B55: {=IF(A55="","",IF(COUNTIF(Companies!$A$6:$A$55,A55)<>1,"n.a.",INDEX(Companies!$C$6:$C$55,MATCH(A55,Companies!$A$6:$A$55,0))))} | F55: =IF(A55="","",COUNTIFS(Relationships!$A$6:$A$205,A55,Relationships!$U$6:$U$205,1)) | G55: =IF(A55="","",COUNTIFS(Relationships!$A$6:$A$205,A55,Relationships!$U$6:$U$205,1,Relationships!$C$6:$C$205,"Client")+COUNTIFS(Relationships!$A$6:$A$205,A55,Relationships!$U$6:$U$205,1,Relationships!$C$6:$C$205,"Client and partner")) | H55: =IF(A55="","",COUNTIFS(Relationships!$A$6:$A$205,A55,Relationships!$U$6:$U$205,1,Relationships!$C$6:$C$205,"Partner")+COUNTIFS(Relationships!$A$6:$A$205,A55,Relationships!$U$6:$U$205,1,Relationships!$C$6:$C$205,"Client and partner")) | I55: =IFERROR(__xludf.DUMMYFUNCTION("IF(A55="""","""",IF(F55=0,""n.a."",MEDIAN(FILTER(Relationships!$Q$6:$Q$205,Relationships!$A$6:$A$205=A55,Relationships!$U$6:$U$205=1))))"),"") | J55: =IF(A55="","",IF(OR(P55<>1,$B$8<>"Ready"),"n.a.",IF(F55=0,0,100*(COUNTIFS($P$14:$P$63,1,$F$14:$F$63,"<"&F55)+0.5*(COUNTIFS($P$14:$P$63,1,$F$14:$F$63,F55)-1))/($B$6-1)))) | K55: =IF(A55="","",IF(OR(P55<>1,$B$8<>"Ready"),"n.a.",IF(F55=0,0,100*(COUNTIFS($P$14:$P$63,1,$S$14:$S$63,"<"&I55)+0.5*(COUNTIFS($P$14:$P$63,1,$S$14:$S$63,I55)-1))/($B$6-1)))) | L55: =IF(A55="","",IF(OR(P55<>1,$B$8<>"Ready"),"n.a.",$G$5*J55+$G$6*K55)) | M55: =IF(A55="","",IF(NOT(ISNUMBER(L55)),"n.a.",1+COUNTIFS($P$14:$P$63,1,$L$14:$L$63,">"&L55))) | N55: =IF(A55="","",COUNTIFS(Relationships!$A$6:$A$205,A55,Relationships!$V$6:$V$205,1)) | O55: =IF(A55="","",IF(Q55<>1,"Outside cap universe",IF(R55<>1,"Duplicate network issuer",IF(C55<>"Yes","Review incomplete",IF(OR(NOT(ISNUMBER(D55)),D55>Rules!$B$6,Rules!$B$6-D55>Rules!$B$42,E55=""),"Check review date/log",IF(N55>0,"Resolve included records",IF($B$8<>"Ready",$B$8,IF(F55=0,"Reviewed: no qualifying ties","Ranked")))))))) | P55: =IF(A55="",0,IF(AND(Q55=1,R55=1,C55="Yes",ISNUMBER(D55),D55<=Rules!$B$6,Rules!$B$6-D55<=Rules!$B$42,E55<>"",N55=0),1,0)) -> 0 | Q55: {=IF(A55="",0,IF(COUNTIF(Companies!$A$6:$A$55,A55)<>1,0,IF(AND(INDEX(Companies!$R$6:$R$55,MATCH(A55,Companies!$A$6:$A$55,0))=1,INDEX(Companies!$I$6:$I$55,MATCH(A55,Companies!$A$6:$A$55,0))>=MAX(10,Rules!$B$22)),1,0)))} -> 0 | R55: =IF(A55="","",COUNTIF($A$14:$A$63,A55)) | S55: =IF(P55<>1,"",IF(F55=0,0,I55))
B56: {=IF(A56="","",IF(COUNTIF(Companies!$A$6:$A$55,A56)<>1,"n.a.",INDEX(Companies!$C$6:$C$55,MATCH(A56,Companies!$A$6:$A$55,0))))} | F56: =IF(A56="","",COUNTIFS(Relationships!$A$6:$A$205,A56,Relationships!$U$6:$U$205,1)) | G56: =IF(A56="","",COUNTIFS(Relationships!$A$6:$A$205,A56,Relationships!$U$6:$U$205,1,Relationships!$C$6:$C$205,"Client")+COUNTIFS(Relationships!$A$6:$A$205,A56,Relationships!$U$6:$U$205,1,Relationships!$C$6:$C$205,"Client and partner")) | H56: =IF(A56="","",COUNTIFS(Relationships!$A$6:$A$205,A56,Relationships!$U$6:$U$205,1,Relationships!$C$6:$C$205,"Partner")+COUNTIFS(Relationships!$A$6:$A$205,A56,Relationships!$U$6:$U$205,1,Relationships!$C$6:$C$205,"Client and partner")) | I56: =IFERROR(__xludf.DUMMYFUNCTION("IF(A56="""","""",IF(F56=0,""n.a."",MEDIAN(FILTER(Relationships!$Q$6:$Q$205,Relationships!$A$6:$A$205=A56,Relationships!$U$6:$U$205=1))))"),"") | J56: =IF(A56="","",IF(OR(P56<>1,$B$8<>"Ready"),"n.a.",IF(F56=0,0,100*(COUNTIFS($P$14:$P$63,1,$F$14:$F$63,"<"&F56)+0.5*(COUNTIFS($P$14:$P$63,1,$F$14:$F$63,F56)-1))/($B$6-1)))) | K56: =IF(A56="","",IF(OR(P56<>1,$B$8<>"Ready"),"n.a.",IF(F56=0,0,100*(COUNTIFS($P$14:$P$63,1,$S$14:$S$63,"<"&I56)+0.5*(COUNTIFS($P$14:$P$63,1,$S$14:$S$63,I56)-1))/($B$6-1)))) | L56: =IF(A56="","",IF(OR(P56<>1,$B$8<>"Ready"),"n.a.",$G$5*J56+$G$6*K56)) | M56: =IF(A56="","",IF(NOT(ISNUMBER(L56)),"n.a.",1+COUNTIFS($P$14:$P$63,1,$L$14:$L$63,">"&L56))) | N56: =IF(A56="","",COUNTIFS(Relationships!$A$6:$A$205,A56,Relationships!$V$6:$V$205,1)) | O56: =IF(A56="","",IF(Q56<>1,"Outside cap universe",IF(R56<>1,"Duplicate network issuer",IF(C56<>"Yes","Review incomplete",IF(OR(NOT(ISNUMBER(D56)),D56>Rules!$B$6,Rules!$B$6-D56>Rules!$B$42,E56=""),"Check review date/log",IF(N56>0,"Resolve included records",IF($B$8<>"Ready",$B$8,IF(F56=0,"Reviewed: no qualifying ties","Ranked")))))))) | P56: =IF(A56="",0,IF(AND(Q56=1,R56=1,C56="Yes",ISNUMBER(D56),D56<=Rules!$B$6,Rules!$B$6-D56<=Rules!$B$42,E56<>"",N56=0),1,0)) -> 0 | Q56: {=IF(A56="",0,IF(COUNTIF(Companies!$A$6:$A$55,A56)<>1,0,IF(AND(INDEX(Companies!$R$6:$R$55,MATCH(A56,Companies!$A$6:$A$55,0))=1,INDEX(Companies!$I$6:$I$55,MATCH(A56,Companies!$A$6:$A$55,0))>=MAX(10,Rules!$B$22)),1,0)))} -> 0 | R56: =IF(A56="","",COUNTIF($A$14:$A$63,A56)) | S56: =IF(P56<>1,"",IF(F56=0,0,I56))
B57: {=IF(A57="","",IF(COUNTIF(Companies!$A$6:$A$55,A57)<>1,"n.a.",INDEX(Companies!$C$6:$C$55,MATCH(A57,Companies!$A$6:$A$55,0))))} | F57: =IF(A57="","",COUNTIFS(Relationships!$A$6:$A$205,A57,Relationships!$U$6:$U$205,1)) | G57: =IF(A57="","",COUNTIFS(Relationships!$A$6:$A$205,A57,Relationships!$U$6:$U$205,1,Relationships!$C$6:$C$205,"Client")+COUNTIFS(Relationships!$A$6:$A$205,A57,Relationships!$U$6:$U$205,1,Relationships!$C$6:$C$205,"Client and partner")) | H57: =IF(A57="","",COUNTIFS(Relationships!$A$6:$A$205,A57,Relationships!$U$6:$U$205,1,Relationships!$C$6:$C$205,"Partner")+COUNTIFS(Relationships!$A$6:$A$205,A57,Relationships!$U$6:$U$205,1,Relationships!$C$6:$C$205,"Client and partner")) | I57: =IFERROR(__xludf.DUMMYFUNCTION("IF(A57="""","""",IF(F57=0,""n.a."",MEDIAN(FILTER(Relationships!$Q$6:$Q$205,Relationships!$A$6:$A$205=A57,Relationships!$U$6:$U$205=1))))"),"") | J57: =IF(A57="","",IF(OR(P57<>1,$B$8<>"Ready"),"n.a.",IF(F57=0,0,100*(COUNTIFS($P$14:$P$63,1,$F$14:$F$63,"<"&F57)+0.5*(COUNTIFS($P$14:$P$63,1,$F$14:$F$63,F57)-1))/($B$6-1)))) | K57: =IF(A57="","",IF(OR(P57<>1,$B$8<>"Ready"),"n.a.",IF(F57=0,0,100*(COUNTIFS($P$14:$P$63,1,$S$14:$S$63,"<"&I57)+0.5*(COUNTIFS($P$14:$P$63,1,$S$14:$S$63,I57)-1))/($B$6-1)))) | L57: =IF(A57="","",IF(OR(P57<>1,$B$8<>"Ready"),"n.a.",$G$5*J57+$G$6*K57)) | M57: =IF(A57="","",IF(NOT(ISNUMBER(L57)),"n.a.",1+COUNTIFS($P$14:$P$63,1,$L$14:$L$63,">"&L57))) | N57: =IF(A57="","",COUNTIFS(Relationships!$A$6:$A$205,A57,Relationships!$V$6:$V$205,1)) | O57: =IF(A57="","",IF(Q57<>1,"Outside cap universe",IF(R57<>1,"Duplicate network issuer",IF(C57<>"Yes","Review incomplete",IF(OR(NOT(ISNUMBER(D57)),D57>Rules!$B$6,Rules!$B$6-D57>Rules!$B$42,E57=""),"Check review date/log",IF(N57>0,"Resolve included records",IF($B$8<>"Ready",$B$8,IF(F57=0,"Reviewed: no qualifying ties","Ranked")))))))) | P57: =IF(A57="",0,IF(AND(Q57=1,R57=1,C57="Yes",ISNUMBER(D57),D57<=Rules!$B$6,Rules!$B$6-D57<=Rules!$B$42,E57<>"",N57=0),1,0)) -> 0 | Q57: {=IF(A57="",0,IF(COUNTIF(Companies!$A$6:$A$55,A57)<>1,0,IF(AND(INDEX(Companies!$R$6:$R$55,MATCH(A57,Companies!$A$6:$A$55,0))=1,INDEX(Companies!$I$6:$I$55,MATCH(A57,Companies!$A$6:$A$55,0))>=MAX(10,Rules!$B$22)),1,0)))} -> 0 | R57: =IF(A57="","",COUNTIF($A$14:$A$63,A57)) | S57: =IF(P57<>1,"",IF(F57=0,0,I57))
B58: {=IF(A58="","",IF(COUNTIF(Companies!$A$6:$A$55,A58)<>1,"n.a.",INDEX(Companies!$C$6:$C$55,MATCH(A58,Companies!$A$6:$A$55,0))))} | F58: =IF(A58="","",COUNTIFS(Relationships!$A$6:$A$205,A58,Relationships!$U$6:$U$205,1)) | G58: =IF(A58="","",COUNTIFS(Relationships!$A$6:$A$205,A58,Relationships!$U$6:$U$205,1,Relationships!$C$6:$C$205,"Client")+COUNTIFS(Relationships!$A$6:$A$205,A58,Relationships!$U$6:$U$205,1,Relationships!$C$6:$C$205,"Client and partner")) | H58: =IF(A58="","",COUNTIFS(Relationships!$A$6:$A$205,A58,Relationships!$U$6:$U$205,1,Relationships!$C$6:$C$205,"Partner")+COUNTIFS(Relationships!$A$6:$A$205,A58,Relationships!$U$6:$U$205,1,Relationships!$C$6:$C$205,"Client and partner")) | I58: =IFERROR(__xludf.DUMMYFUNCTION("IF(A58="""","""",IF(F58=0,""n.a."",MEDIAN(FILTER(Relationships!$Q$6:$Q$205,Relationships!$A$6:$A$205=A58,Relationships!$U$6:$U$205=1))))"),"") | J58: =IF(A58="","",IF(OR(P58<>1,$B$8<>"Ready"),"n.a.",IF(F58=0,0,100*(COUNTIFS($P$14:$P$63,1,$F$14:$F$63,"<"&F58)+0.5*(COUNTIFS($P$14:$P$63,1,$F$14:$F$63,F58)-1))/($B$6-1)))) | K58: =IF(A58="","",IF(OR(P58<>1,$B$8<>"Ready"),"n.a.",IF(F58=0,0,100*(COUNTIFS($P$14:$P$63,1,$S$14:$S$63,"<"&I58)+0.5*(COUNTIFS($P$14:$P$63,1,$S$14:$S$63,I58)-1))/($B$6-1)))) | L58: =IF(A58="","",IF(OR(P58<>1,$B$8<>"Ready"),"n.a.",$G$5*J58+$G$6*K58)) | M58: =IF(A58="","",IF(NOT(ISNUMBER(L58)),"n.a.",1+COUNTIFS($P$14:$P$63,1,$L$14:$L$63,">"&L58))) | N58: =IF(A58="","",COUNTIFS(Relationships!$A$6:$A$205,A58,Relationships!$V$6:$V$205,1)) | O58: =IF(A58="","",IF(Q58<>1,"Outside cap universe",IF(R58<>1,"Duplicate network issuer",IF(C58<>"Yes","Review incomplete",IF(OR(NOT(ISNUMBER(D58)),D58>Rules!$B$6,Rules!$B$6-D58>Rules!$B$42,E58=""),"Check review date/log",IF(N58>0,"Resolve included records",IF($B$8<>"Ready",$B$8,IF(F58=0,"Reviewed: no qualifying ties","Ranked")))))))) | P58: =IF(A58="",0,IF(AND(Q58=1,R58=1,C58="Yes",ISNUMBER(D58),D58<=Rules!$B$6,Rules!$B$6-D58<=Rules!$B$42,E58<>"",N58=0),1,0)) -> 0 | Q58: {=IF(A58="",0,IF(COUNTIF(Companies!$A$6:$A$55,A58)<>1,0,IF(AND(INDEX(Companies!$R$6:$R$55,MATCH(A58,Companies!$A$6:$A$55,0))=1,INDEX(Companies!$I$6:$I$55,MATCH(A58,Companies!$A$6:$A$55,0))>=MAX(10,Rules!$B$22)),1,0)))} -> 0 | R58: =IF(A58="","",COUNTIF($A$14:$A$63,A58)) | S58: =IF(P58<>1,"",IF(F58=0,0,I58))
B59: {=IF(A59="","",IF(COUNTIF(Companies!$A$6:$A$55,A59)<>1,"n.a.",INDEX(Companies!$C$6:$C$55,MATCH(A59,Companies!$A$6:$A$55,0))))} | F59: =IF(A59="","",COUNTIFS(Relationships!$A$6:$A$205,A59,Relationships!$U$6:$U$205,1)) | G59: =IF(A59="","",COUNTIFS(Relationships!$A$6:$A$205,A59,Relationships!$U$6:$U$205,1,Relationships!$C$6:$C$205,"Client")+COUNTIFS(Relationships!$A$6:$A$205,A59,Relationships!$U$6:$U$205,1,Relationships!$C$6:$C$205,"Client and partner")) | H59: =IF(A59="","",COUNTIFS(Relationships!$A$6:$A$205,A59,Relationships!$U$6:$U$205,1,Relationships!$C$6:$C$205,"Partner")+COUNTIFS(Relationships!$A$6:$A$205,A59,Relationships!$U$6:$U$205,1,Relationships!$C$6:$C$205,"Client and partner")) | I59: =IFERROR(__xludf.DUMMYFUNCTION("IF(A59="""","""",IF(F59=0,""n.a."",MEDIAN(FILTER(Relationships!$Q$6:$Q$205,Relationships!$A$6:$A$205=A59,Relationships!$U$6:$U$205=1))))"),"") | J59: =IF(A59="","",IF(OR(P59<>1,$B$8<>"Ready"),"n.a.",IF(F59=0,0,100*(COUNTIFS($P$14:$P$63,1,$F$14:$F$63,"<"&F59)+0.5*(COUNTIFS($P$14:$P$63,1,$F$14:$F$63,F59)-1))/($B$6-1)))) | K59: =IF(A59="","",IF(OR(P59<>1,$B$8<>"Ready"),"n.a.",IF(F59=0,0,100*(COUNTIFS($P$14:$P$63,1,$S$14:$S$63,"<"&I59)+0.5*(COUNTIFS($P$14:$P$63,1,$S$14:$S$63,I59)-1))/($B$6-1)))) | L59: =IF(A59="","",IF(OR(P59<>1,$B$8<>"Ready"),"n.a.",$G$5*J59+$G$6*K59)) | M59: =IF(A59="","",IF(NOT(ISNUMBER(L59)),"n.a.",1+COUNTIFS($P$14:$P$63,1,$L$14:$L$63,">"&L59))) | N59: =IF(A59="","",COUNTIFS(Relationships!$A$6:$A$205,A59,Relationships!$V$6:$V$205,1)) | O59: =IF(A59="","",IF(Q59<>1,"Outside cap universe",IF(R59<>1,"Duplicate network issuer",IF(C59<>"Yes","Review incomplete",IF(OR(NOT(ISNUMBER(D59)),D59>Rules!$B$6,Rules!$B$6-D59>Rules!$B$42,E59=""),"Check review date/log",IF(N59>0,"Resolve included records",IF($B$8<>"Ready",$B$8,IF(F59=0,"Reviewed: no qualifying ties","Ranked")))))))) | P59: =IF(A59="",0,IF(AND(Q59=1,R59=1,C59="Yes",ISNUMBER(D59),D59<=Rules!$B$6,Rules!$B$6-D59<=Rules!$B$42,E59<>"",N59=0),1,0)) -> 0 | Q59: {=IF(A59="",0,IF(COUNTIF(Companies!$A$6:$A$55,A59)<>1,0,IF(AND(INDEX(Companies!$R$6:$R$55,MATCH(A59,Companies!$A$6:$A$55,0))=1,INDEX(Companies!$I$6:$I$55,MATCH(A59,Companies!$A$6:$A$55,0))>=MAX(10,Rules!$B$22)),1,0)))} -> 0 | R59: =IF(A59="","",COUNTIF($A$14:$A$63,A59)) | S59: =IF(P59<>1,"",IF(F59=0,0,I59))
B60: {=IF(A60="","",IF(COUNTIF(Companies!$A$6:$A$55,A60)<>1,"n.a.",INDEX(Companies!$C$6:$C$55,MATCH(A60,Companies!$A$6:$A$55,0))))} | F60: =IF(A60="","",COUNTIFS(Relationships!$A$6:$A$205,A60,Relationships!$U$6:$U$205,1)) | G60: =IF(A60="","",COUNTIFS(Relationships!$A$6:$A$205,A60,Relationships!$U$6:$U$205,1,Relationships!$C$6:$C$205,"Client")+COUNTIFS(Relationships!$A$6:$A$205,A60,Relationships!$U$6:$U$205,1,Relationships!$C$6:$C$205,"Client and partner")) | H60: =IF(A60="","",COUNTIFS(Relationships!$A$6:$A$205,A60,Relationships!$U$6:$U$205,1,Relationships!$C$6:$C$205,"Partner")+COUNTIFS(Relationships!$A$6:$A$205,A60,Relationships!$U$6:$U$205,1,Relationships!$C$6:$C$205,"Client and partner")) | I60: =IFERROR(__xludf.DUMMYFUNCTION("IF(A60="""","""",IF(F60=0,""n.a."",MEDIAN(FILTER(Relationships!$Q$6:$Q$205,Relationships!$A$6:$A$205=A60,Relationships!$U$6:$U$205=1))))"),"") | J60: =IF(A60="","",IF(OR(P60<>1,$B$8<>"Ready"),"n.a.",IF(F60=0,0,100*(COUNTIFS($P$14:$P$63,1,$F$14:$F$63,"<"&F60)+0.5*(COUNTIFS($P$14:$P$63,1,$F$14:$F$63,F60)-1))/($B$6-1)))) | K60: =IF(A60="","",IF(OR(P60<>1,$B$8<>"Ready"),"n.a.",IF(F60=0,0,100*(COUNTIFS($P$14:$P$63,1,$S$14:$S$63,"<"&I60)+0.5*(COUNTIFS($P$14:$P$63,1,$S$14:$S$63,I60)-1))/($B$6-1)))) | L60: =IF(A60="","",IF(OR(P60<>1,$B$8<>"Ready"),"n.a.",$G$5*J60+$G$6*K60)) | M60: =IF(A60="","",IF(NOT(ISNUMBER(L60)),"n.a.",1+COUNTIFS($P$14:$P$63,1,$L$14:$L$63,">"&L60))) | N60: =IF(A60="","",COUNTIFS(Relationships!$A$6:$A$205,A60,Relationships!$V$6:$V$205,1)) | O60: =IF(A60="","",IF(Q60<>1,"Outside cap universe",IF(R60<>1,"Duplicate network issuer",IF(C60<>"Yes","Review incomplete",IF(OR(NOT(ISNUMBER(D60)),D60>Rules!$B$6,Rules!$B$6-D60>Rules!$B$42,E60=""),"Check review date/log",IF(N60>0,"Resolve included records",IF($B$8<>"Ready",$B$8,IF(F60=0,"Reviewed: no qualifying ties","Ranked")))))))) | P60: =IF(A60="",0,IF(AND(Q60=1,R60=1,C60="Yes",ISNUMBER(D60),D60<=Rules!$B$6,Rules!$B$6-D60<=Rules!$B$42,E60<>"",N60=0),1,0)) -> 0 | Q60: {=IF(A60="",0,IF(COUNTIF(Companies!$A$6:$A$55,A60)<>1,0,IF(AND(INDEX(Companies!$R$6:$R$55,MATCH(A60,Companies!$A$6:$A$55,0))=1,INDEX(Companies!$I$6:$I$55,MATCH(A60,Companies!$A$6:$A$55,0))>=MAX(10,Rules!$B$22)),1,0)))} -> 0 | R60: =IF(A60="","",COUNTIF($A$14:$A$63,A60)) | S60: =IF(P60<>1,"",IF(F60=0,0,I60))
B61: {=IF(A61="","",IF(COUNTIF(Companies!$A$6:$A$55,A61)<>1,"n.a.",INDEX(Companies!$C$6:$C$55,MATCH(A61,Companies!$A$6:$A$55,0))))} | F61: =IF(A61="","",COUNTIFS(Relationships!$A$6:$A$205,A61,Relationships!$U$6:$U$205,1)) | G61: =IF(A61="","",COUNTIFS(Relationships!$A$6:$A$205,A61,Relationships!$U$6:$U$205,1,Relationships!$C$6:$C$205,"Client")+COUNTIFS(Relationships!$A$6:$A$205,A61,Relationships!$U$6:$U$205,1,Relationships!$C$6:$C$205,"Client and partner")) | H61: =IF(A61="","",COUNTIFS(Relationships!$A$6:$A$205,A61,Relationships!$U$6:$U$205,1,Relationships!$C$6:$C$205,"Partner")+COUNTIFS(Relationships!$A$6:$A$205,A61,Relationships!$U$6:$U$205,1,Relationships!$C$6:$C$205,"Client and partner")) | I61: =IFERROR(__xludf.DUMMYFUNCTION("IF(A61="""","""",IF(F61=0,""n.a."",MEDIAN(FILTER(Relationships!$Q$6:$Q$205,Relationships!$A$6:$A$205=A61,Relationships!$U$6:$U$205=1))))"),"") | J61: =IF(A61="","",IF(OR(P61<>1,$B$8<>"Ready"),"n.a.",IF(F61=0,0,100*(COUNTIFS($P$14:$P$63,1,$F$14:$F$63,"<"&F61)+0.5*(COUNTIFS($P$14:$P$63,1,$F$14:$F$63,F61)-1))/($B$6-1)))) | K61: =IF(A61="","",IF(OR(P61<>1,$B$8<>"Ready"),"n.a.",IF(F61=0,0,100*(COUNTIFS($P$14:$P$63,1,$S$14:$S$63,"<"&I61)+0.5*(COUNTIFS($P$14:$P$63,1,$S$14:$S$63,I61)-1))/($B$6-1)))) | L61: =IF(A61="","",IF(OR(P61<>1,$B$8<>"Ready"),"n.a.",$G$5*J61+$G$6*K61)) | M61: =IF(A61="","",IF(NOT(ISNUMBER(L61)),"n.a.",1+COUNTIFS($P$14:$P$63,1,$L$14:$L$63,">"&L61))) | N61: =IF(A61="","",COUNTIFS(Relationships!$A$6:$A$205,A61,Relationships!$V$6:$V$205,1)) | O61: =IF(A61="","",IF(Q61<>1,"Outside cap universe",IF(R61<>1,"Duplicate network issuer",IF(C61<>"Yes","Review incomplete",IF(OR(NOT(ISNUMBER(D61)),D61>Rules!$B$6,Rules!$B$6-D61>Rules!$B$42,E61=""),"Check review date/log",IF(N61>0,"Resolve included records",IF($B$8<>"Ready",$B$8,IF(F61=0,"Reviewed: no qualifying ties","Ranked")))))))) | P61: =IF(A61="",0,IF(AND(Q61=1,R61=1,C61="Yes",ISNUMBER(D61),D61<=Rules!$B$6,Rules!$B$6-D61<=Rules!$B$42,E61<>"",N61=0),1,0)) -> 0 | Q61: {=IF(A61="",0,IF(COUNTIF(Companies!$A$6:$A$55,A61)<>1,0,IF(AND(INDEX(Companies!$R$6:$R$55,MATCH(A61,Companies!$A$6:$A$55,0))=1,INDEX(Companies!$I$6:$I$55,MATCH(A61,Companies!$A$6:$A$55,0))>=MAX(10,Rules!$B$22)),1,0)))} -> 0 | R61: =IF(A61="","",COUNTIF($A$14:$A$63,A61)) | S61: =IF(P61<>1,"",IF(F61=0,0,I61))
B62: {=IF(A62="","",IF(COUNTIF(Companies!$A$6:$A$55,A62)<>1,"n.a.",INDEX(Companies!$C$6:$C$55,MATCH(A62,Companies!$A$6:$A$55,0))))} | F62: =IF(A62="","",COUNTIFS(Relationships!$A$6:$A$205,A62,Relationships!$U$6:$U$205,1)) | G62: =IF(A62="","",COUNTIFS(Relationships!$A$6:$A$205,A62,Relationships!$U$6:$U$205,1,Relationships!$C$6:$C$205,"Client")+COUNTIFS(Relationships!$A$6:$A$205,A62,Relationships!$U$6:$U$205,1,Relationships!$C$6:$C$205,"Client and partner")) | H62: =IF(A62="","",COUNTIFS(Relationships!$A$6:$A$205,A62,Relationships!$U$6:$U$205,1,Relationships!$C$6:$C$205,"Partner")+COUNTIFS(Relationships!$A$6:$A$205,A62,Relationships!$U$6:$U$205,1,Relationships!$C$6:$C$205,"Client and partner")) | I62: =IFERROR(__xludf.DUMMYFUNCTION("IF(A62="""","""",IF(F62=0,""n.a."",MEDIAN(FILTER(Relationships!$Q$6:$Q$205,Relationships!$A$6:$A$205=A62,Relationships!$U$6:$U$205=1))))"),"") | J62: =IF(A62="","",IF(OR(P62<>1,$B$8<>"Ready"),"n.a.",IF(F62=0,0,100*(COUNTIFS($P$14:$P$63,1,$F$14:$F$63,"<"&F62)+0.5*(COUNTIFS($P$14:$P$63,1,$F$14:$F$63,F62)-1))/($B$6-1)))) | K62: =IF(A62="","",IF(OR(P62<>1,$B$8<>"Ready"),"n.a.",IF(F62=0,0,100*(COUNTIFS($P$14:$P$63,1,$S$14:$S$63,"<"&I62)+0.5*(COUNTIFS($P$14:$P$63,1,$S$14:$S$63,I62)-1))/($B$6-1)))) | L62: =IF(A62="","",IF(OR(P62<>1,$B$8<>"Ready"),"n.a.",$G$5*J62+$G$6*K62)) | M62: =IF(A62="","",IF(NOT(ISNUMBER(L62)),"n.a.",1+COUNTIFS($P$14:$P$63,1,$L$14:$L$63,">"&L62))) | N62: =IF(A62="","",COUNTIFS(Relationships!$A$6:$A$205,A62,Relationships!$V$6:$V$205,1)) | O62: =IF(A62="","",IF(Q62<>1,"Outside cap universe",IF(R62<>1,"Duplicate network issuer",IF(C62<>"Yes","Review incomplete",IF(OR(NOT(ISNUMBER(D62)),D62>Rules!$B$6,Rules!$B$6-D62>Rules!$B$42,E62=""),"Check review date/log",IF(N62>0,"Resolve included records",IF($B$8<>"Ready",$B$8,IF(F62=0,"Reviewed: no qualifying ties","Ranked")))))))) | P62: =IF(A62="",0,IF(AND(Q62=1,R62=1,C62="Yes",ISNUMBER(D62),D62<=Rules!$B$6,Rules!$B$6-D62<=Rules!$B$42,E62<>"",N62=0),1,0)) -> 0 | Q62: {=IF(A62="",0,IF(COUNTIF(Companies!$A$6:$A$55,A62)<>1,0,IF(AND(INDEX(Companies!$R$6:$R$55,MATCH(A62,Companies!$A$6:$A$55,0))=1,INDEX(Companies!$I$6:$I$55,MATCH(A62,Companies!$A$6:$A$55,0))>=MAX(10,Rules!$B$22)),1,0)))} -> 0 | R62: =IF(A62="","",COUNTIF($A$14:$A$63,A62)) | S62: =IF(P62<>1,"",IF(F62=0,0,I62))
B63: {=IF(A63="","",IF(COUNTIF(Companies!$A$6:$A$55,A63)<>1,"n.a.",INDEX(Companies!$C$6:$C$55,MATCH(A63,Companies!$A$6:$A$55,0))))} | F63: =IF(A63="","",COUNTIFS(Relationships!$A$6:$A$205,A63,Relationships!$U$6:$U$205,1)) | G63: =IF(A63="","",COUNTIFS(Relationships!$A$6:$A$205,A63,Relationships!$U$6:$U$205,1,Relationships!$C$6:$C$205,"Client")+COUNTIFS(Relationships!$A$6:$A$205,A63,Relationships!$U$6:$U$205,1,Relationships!$C$6:$C$205,"Client and partner")) | H63: =IF(A63="","",COUNTIFS(Relationships!$A$6:$A$205,A63,Relationships!$U$6:$U$205,1,Relationships!$C$6:$C$205,"Partner")+COUNTIFS(Relationships!$A$6:$A$205,A63,Relationships!$U$6:$U$205,1,Relationships!$C$6:$C$205,"Client and partner")) | I63: =IFERROR(__xludf.DUMMYFUNCTION("IF(A63="""","""",IF(F63=0,""n.a."",MEDIAN(FILTER(Relationships!$Q$6:$Q$205,Relationships!$A$6:$A$205=A63,Relationships!$U$6:$U$205=1))))"),"") | J63: =IF(A63="","",IF(OR(P63<>1,$B$8<>"Ready"),"n.a.",IF(F63=0,0,100*(COUNTIFS($P$14:$P$63,1,$F$14:$F$63,"<"&F63)+0.5*(COUNTIFS($P$14:$P$63,1,$F$14:$F$63,F63)-1))/($B$6-1)))) | K63: =IF(A63="","",IF(OR(P63<>1,$B$8<>"Ready"),"n.a.",IF(F63=0,0,100*(COUNTIFS($P$14:$P$63,1,$S$14:$S$63,"<"&I63)+0.5*(COUNTIFS($P$14:$P$63,1,$S$14:$S$63,I63)-1))/($B$6-1)))) | L63: =IF(A63="","",IF(OR(P63<>1,$B$8<>"Ready"),"n.a.",$G$5*J63+$G$6*K63)) | M63: =IF(A63="","",IF(NOT(ISNUMBER(L63)),"n.a.",1+COUNTIFS($P$14:$P$63,1,$L$14:$L$63,">"&L63))) | N63: =IF(A63="","",COUNTIFS(Relationships!$A$6:$A$205,A63,Relationships!$V$6:$V$205,1)) | O63: =IF(A63="","",IF(Q63<>1,"Outside cap universe",IF(R63<>1,"Duplicate network issuer",IF(C63<>"Yes","Review incomplete",IF(OR(NOT(ISNUMBER(D63)),D63>Rules!$B$6,Rules!$B$6-D63>Rules!$B$42,E63=""),"Check review date/log",IF(N63>0,"Resolve included records",IF($B$8<>"Ready",$B$8,IF(F63=0,"Reviewed: no qualifying ties","Ranked")))))))) | P63: =IF(A63="",0,IF(AND(Q63=1,R63=1,C63="Yes",ISNUMBER(D63),D63<=Rules!$B$6,Rules!$B$6-D63<=Rules!$B$42,E63<>"",N63=0),1,0)) -> 0 | Q63: {=IF(A63="",0,IF(COUNTIF(Companies!$A$6:$A$55,A63)<>1,0,IF(AND(INDEX(Companies!$R$6:$R$55,MATCH(A63,Companies!$A$6:$A$55,0))=1,INDEX(Companies!$I$6:$I$55,MATCH(A63,Companies!$A$6:$A$55,0))>=MAX(10,Rules!$B$22)),1,0)))} -> 0 | R63: =IF(A63="","",COUNTIF($A$14:$A$63,A63)) | S63: =IF(P63<>1,"",IF(F63=0,0,I63))

Sheet Valuation
A2: Relative valuation
A3: Higher score = cheaper versus scorable peers. USD 10bn issuer floor. Weights are provisional.
A4: Active profile | B4: =IFERROR(__xludf.DUMMYFUNCTION("IF(REGEXMATCH(LOWER(Rules!B7&"" ""&Rules!B8),""financial|bank|insurance|reit|real estate""),""Needs sector profile"",IF(LOWER(Rules!B7)=""utilities"",""Utilities"",""General operating""))"),"General operating") -> General operating | F4: Metric | G4: Active weight | H4: General operating | I4: Utilities | L4: Comparable median | M4: Value
A5: Minimum scorable companies | B5: =Rules!B12 -> 3 | F5: Forward P/E | G5: =IF($B$4="Utilities",I5,IF($B$4="General operating",H5,0)) -> 0.35 | H5: 0.35 | I5: 0.4 | L5: Forward P/E | M5: =IF($B$7<$B$5,"n.a.",IF(COUNT($V$15:$V$64)=0,"n.a.",MEDIAN($V$15:$V$64))) -> n.a.
A6: Cap-eligible issuers | B6: =COUNTIFS(Companies!$R$6:$R$55,1) -> 0 | F6: Forward EV/EBITDA | G6: =IF($B$4="Utilities",I6,IF($B$4="General operating",H6,0)) -> 0.35 | H6: 0.35 | I6: 0.4 | L6: Forward EV/EBITDA | M6: =IF($B$7<$B$5,"n.a.",IF(COUNT($W$15:$W$64)=0,"n.a.",MEDIAN($W$15:$W$64))) -> n.a.
A7: Scorable issuers | B7: =COUNTIFS($T$15:$T$64,1) -> 0 | F7: TTM FCF yield proxy | G7: =IF($B$4="Utilities",I7,IF($B$4="General operating",H7,0)) -> 0.3 | H7: 0.3 | I7: 0 | L7: TTM FCF yield proxy | M7: =IF($B$7<$B$5,"n.a.",IF(COUNT($X$15:$X$64)=0,"n.a.",MEDIAN($X$15:$X$64))) -> n.a.
A8: Active weight total | B8: =SUM($G$5:$G$8) -> 1 | F8: Price/book | G8: =IF($B$4="Utilities",I8,IF($B$4="General operating",H8,0)) -> 0 | H8: 0 | I8: 0.2 | L8: Price/book | M8: =IF($B$7<$B$5,"n.a.",IF(COUNT($Y$15:$Y$64)=0,"n.a.",MEDIAN($Y$15:$Y$64))) -> n.a.
A9: Universe coverage | B9: =IF(B6=0,"n.a.",B7/B6) -> n.a.
A10: Comparable earnings basis | B10: Adjusted | F10: Profile notes | G10: Weights are draft assumptions.
A11: NTM period end | B11: =EDATE(Rules!B6,12) -> 46663 | G11: Utilities: FCF yield is diagnostic only.
A12: Ranking status | B12: =IF(Rules!B15<>"Yes","Confirm issuer universe",IF(B4="Needs sector profile","Sector profile required",IF(OR(COUNT($G$5:$G$8)<>4,MIN($G$5:$G$8)<0,ABS(B8-1)>0.000001),"Check profile weights",IF(B7<B5,"Too few scorable companies","Ready")))) -> Confirm issuer universe | G12: Compare similar industries and countries.
A14: Issuer ID | B14: Company | C14: Market cap USD bn | D14: Forward P/E | E14: Forward EV/EBITDA | F14: TTM FCF yield proxy | G14: Price/book | H14: P/E score | I14: EV/EBITDA score | J14: FCF yield score | K14: P/B score | L14: Valuation score /100 | M14: Valuation rank | N14: P/E premium/(discount) | O14: EV/EBITDA premium/(discount) | P14: FCF yield spread | Q14: P/B premium/(discount) | R14: Required metric coverage | S14: Row status | T14: Scorable | U14: Sort order | V14: Scorable P/E | W14: Scorable EV/EBITDA | X14: Scorable FCF yield | Y14: Scorable P/B
A15: =IF('Valuation inputs'!A6="","",'Valuation inputs'!A6) | B15: =IF(A15="","",'Valuation inputs'!B6) | C15: =IF(A15="","",'Valuation inputs'!D6) | D15: =IF(A15="","",IF('Valuation inputs'!Y6<>1,"n.a.",IF(NOT(ISNUMBER('Valuation inputs'!F6)),"n.a.",IF('Valuation inputs'!F6<=0,"NM",'Valuation inputs'!E6/'Valuation inputs'!F6)))) | E15: =IF(A15="","",IF(OR('Valuation inputs'!Y6<>1,NOT(ISNUMBER('Valuation inputs'!Z6)),NOT(ISNUMBER('Valuation inputs'!G6))),"n.a.",IF(OR('Valuation inputs'!Z6<=0,'Valuation inputs'!G6<=0),"NM",'Valuation inputs'!Z6/'Valuation inputs'!G6))) | F15: =IF(A15="","",IF(OR('Valuation inputs'!Y6<>1,NOT(ISNUMBER('Valuation inputs'!AA6))),"n.a.",'Valuation inputs'!AA6/'Valuation inputs'!D6)) | G15: =IF(A15="","",IF(OR('Valuation inputs'!Y6<>1,NOT(ISNUMBER('Valuation inputs'!J6))),"n.a.",IF('Valuation inputs'!J6<=0,"NM",'Valuation inputs'!D6/'Valuation inputs'!J6))) | H15: =IF(A15="","",IF(OR(T15<>1,$B$12<>"Ready",NOT(ISNUMBER(D15))),"n.a.",100*(COUNTIFS($T$15:$T$64,1,$D$15:$D$64,">"&D15)+0.5*(COUNTIFS($T$15:$T$64,1,$D$15:$D$64,D15)-1))/($B$7-1))) | I15: =IF(A15="","",IF(OR(T15<>1,$B$12<>"Ready",NOT(ISNUMBER(E15))),"n.a.",100*(COUNTIFS($T$15:$T$64,1,$E$15:$E$64,">"&E15)+0.5*(COUNTIFS($T$15:$T$64,1,$E$15:$E$64,E15)-1))/($B$7-1))) | J15: =IF(A15="","",IF(OR(T15<>1,$B$12<>"Ready",NOT(ISNUMBER(F15))),"n.a.",100*(COUNTIFS($T$15:$T$64,1,$F$15:$F$64,"<"&F15)+0.5*(COUNTIFS($T$15:$T$64,1,$F$15:$F$64,F15)-1))/($B$7-1))) | K15: =IF(A15="","",IF(OR(T15<>1,$B$12<>"Ready",NOT(ISNUMBER(G15))),"n.a.",100*(COUNTIFS($T$15:$T$64,1,$G$15:$G$64,">"&G15)+0.5*(COUNTIFS($T$15:$T$64,1,$G$15:$G$64,G15)-1))/($B$7-1))) | L15: =IF(A15="","",IF(OR(T15<>1,$B$12<>"Ready"),"n.a.",IF($G$5=0,0,$G$5*H15)+IF($G$6=0,0,$G$6*I15)+IF($G$7=0,0,$G$7*J15)+IF($G$8=0,0,$G$8*K15))) | M15: =IF(A15="","",IF(NOT(ISNUMBER(L15)),"n.a.",1+COUNTIFS($T$15:$T$64,1,$L$15:$L$64,">"&L15))) | N15: =IF(A15="","",IF(OR(NOT(ISNUMBER(D15)),NOT(ISNUMBER($M$5))),"n.a.",IF($M$5=0,"n.a.",D15/$M$5-1))) | O15: =IF(A15="","",IF(OR(NOT(ISNUMBER(E15)),NOT(ISNUMBER($M$6))),"n.a.",IF($M$6=0,"n.a.",E15/$M$6-1))) | P15: =IF(A15="","",IF(OR(NOT(ISNUMBER(F15)),NOT(ISNUMBER($M$7))),"n.a.",F15-$M$7)) | Q15: =IF(A15="","",IF(OR(NOT(ISNUMBER(G15)),NOT(ISNUMBER($M$8))),"n.a.",IF($M$8=0,"n.a.",G15/$M$8-1))) | R15: =IF(A15="","",IF(COUNTIFS($G$5:$G$8,">0")=0,"n.a.",(IF(AND($G$5>0,ISNUMBER(D15)),1,0)+IF(AND($G$6>0,ISNUMBER(E15)),1,0)+IF(AND($G$7>0,ISNUMBER(F15)),1,0)+IF(AND($G$8>0,ISNUMBER(G15)),1,0))/COUNTIFS($G$5:$G$8,">0"))) | S15: =IF(A15="","",IF('Valuation inputs'!Y6<>1,'Valuation inputs'!AB6,IF(T15<>1,"Missing/NM required metric",IF($B$12<>"Ready",$B$12,"Ranked")))) | T15: =IF(A15="","",IF(AND('Valuation inputs'!Y6=1,$B$4<>"Needs sector profile",COUNT($G$5:$G$8)=4,MIN($G$5:$G$8)>=0,ABS($B$8-1)<=0.000001,OR($G$5=0,ISNUMBER(D15)),OR($G$6=0,ISNUMBER(E15)),OR($G$7=0,ISNUMBER(F15)),OR($G$8=0,ISNUMBER(G15))),1,0)) | U15: =IF(NOT(ISNUMBER(L15)),"",M15+COUNTIFS($T$15:T15,1,$L$15:L15,L15)-1) | V15: =IF(AND(A15<>"",T15=1,ISNUMBER(D15)),D15,"") | W15: =IF(AND(A15<>"",T15=1,ISNUMBER(E15)),E15,"") | X15: =IF(AND(A15<>"",T15=1,ISNUMBER(F15)),F15,"") | Y15: =IF(AND(A15<>"",T15=1,ISNUMBER(G15)),G15,"")
A16: =IF('Valuation inputs'!A7="","",'Valuation inputs'!A7) | B16: =IF(A16="","",'Valuation inputs'!B7) | C16: =IF(A16="","",'Valuation inputs'!D7) | D16: =IF(A16="","",IF('Valuation inputs'!Y7<>1,"n.a.",IF(NOT(ISNUMBER('Valuation inputs'!F7)),"n.a.",IF('Valuation inputs'!F7<=0,"NM",'Valuation inputs'!E7/'Valuation inputs'!F7)))) | E16: =IF(A16="","",IF(OR('Valuation inputs'!Y7<>1,NOT(ISNUMBER('Valuation inputs'!Z7)),NOT(ISNUMBER('Valuation inputs'!G7))),"n.a.",IF(OR('Valuation inputs'!Z7<=0,'Valuation inputs'!G7<=0),"NM",'Valuation inputs'!Z7/'Valuation inputs'!G7))) | F16: =IF(A16="","",IF(OR('Valuation inputs'!Y7<>1,NOT(ISNUMBER('Valuation inputs'!AA7))),"n.a.",'Valuation inputs'!AA7/'Valuation inputs'!D7)) | G16: =IF(A16="","",IF(OR('Valuation inputs'!Y7<>1,NOT(ISNUMBER('Valuation inputs'!J7))),"n.a.",IF('Valuation inputs'!J7<=0,"NM",'Valuation inputs'!D7/'Valuation inputs'!J7))) | H16: =IF(A16="","",IF(OR(T16<>1,$B$12<>"Ready",NOT(ISNUMBER(D16))),"n.a.",100*(COUNTIFS($T$15:$T$64,1,$D$15:$D$64,">"&D16)+0.5*(COUNTIFS($T$15:$T$64,1,$D$15:$D$64,D16)-1))/($B$7-1))) | I16: =IF(A16="","",IF(OR(T16<>1,$B$12<>"Ready",NOT(ISNUMBER(E16))),"n.a.",100*(COUNTIFS($T$15:$T$64,1,$E$15:$E$64,">"&E16)+0.5*(COUNTIFS($T$15:$T$64,1,$E$15:$E$64,E16)-1))/($B$7-1))) | J16: =IF(A16="","",IF(OR(T16<>1,$B$12<>"Ready",NOT(ISNUMBER(F16))),"n.a.",100*(COUNTIFS($T$15:$T$64,1,$F$15:$F$64,"<"&F16)+0.5*(COUNTIFS($T$15:$T$64,1,$F$15:$F$64,F16)-1))/($B$7-1))) | K16: =IF(A16="","",IF(OR(T16<>1,$B$12<>"Ready",NOT(ISNUMBER(G16))),"n.a.",100*(COUNTIFS($T$15:$T$64,1,$G$15:$G$64,">"&G16)+0.5*(COUNTIFS($T$15:$T$64,1,$G$15:$G$64,G16)-1))/($B$7-1))) | L16: =IF(A16="","",IF(OR(T16<>1,$B$12<>"Ready"),"n.a.",IF($G$5=0,0,$G$5*H16)+IF($G$6=0,0,$G$6*I16)+IF($G$7=0,0,$G$7*J16)+IF($G$8=0,0,$G$8*K16))) | M16: =IF(A16="","",IF(NOT(ISNUMBER(L16)),"n.a.",1+COUNTIFS($T$15:$T$64,1,$L$15:$L$64,">"&L16))) | N16: =IF(A16="","",IF(OR(NOT(ISNUMBER(D16)),NOT(ISNUMBER($M$5))),"n.a.",IF($M$5=0,"n.a.",D16/$M$5-1))) | O16: =IF(A16="","",IF(OR(NOT(ISNUMBER(E16)),NOT(ISNUMBER($M$6))),"n.a.",IF($M$6=0,"n.a.",E16/$M$6-1))) | P16: =IF(A16="","",IF(OR(NOT(ISNUMBER(F16)),NOT(ISNUMBER($M$7))),"n.a.",F16-$M$7)) | Q16: =IF(A16="","",IF(OR(NOT(ISNUMBER(G16)),NOT(ISNUMBER($M$8))),"n.a.",IF($M$8=0,"n.a.",G16/$M$8-1))) | R16: =IF(A16="","",IF(COUNTIFS($G$5:$G$8,">0")=0,"n.a.",(IF(AND($G$5>0,ISNUMBER(D16)),1,0)+IF(AND($G$6>0,ISNUMBER(E16)),1,0)+IF(AND($G$7>0,ISNUMBER(F16)),1,0)+IF(AND($G$8>0,ISNUMBER(G16)),1,0))/COUNTIFS($G$5:$G$8,">0"))) | S16: =IF(A16="","",IF('Valuation inputs'!Y7<>1,'Valuation inputs'!AB7,IF(T16<>1,"Missing/NM required metric",IF($B$12<>"Ready",$B$12,"Ranked")))) | T16: =IF(A16="","",IF(AND('Valuation inputs'!Y7=1,$B$4<>"Needs sector profile",COUNT($G$5:$G$8)=4,MIN($G$5:$G$8)>=0,ABS($B$8-1)<=0.000001,OR($G$5=0,ISNUMBER(D16)),OR($G$6=0,ISNUMBER(E16)),OR($G$7=0,ISNUMBER(F16)),OR($G$8=0,ISNUMBER(G16))),1,0)) | U16: =IF(NOT(ISNUMBER(L16)),"",M16+COUNTIFS($T$15:T16,1,$L$15:L16,L16)-1) | V16: =IF(AND(A16<>"",T16=1,ISNUMBER(D16)),D16,"") | W16: =IF(AND(A16<>"",T16=1,ISNUMBER(E16)),E16,"") | X16: =IF(AND(A16<>"",T16=1,ISNUMBER(F16)),F16,"") | Y16: =IF(AND(A16<>"",T16=1,ISNUMBER(G16)),G16,"")
A17: =IF('Valuation inputs'!A8="","",'Valuation inputs'!A8) | B17: =IF(A17="","",'Valuation inputs'!B8) | C17: =IF(A17="","",'Valuation inputs'!D8) | D17: =IF(A17="","",IF('Valuation inputs'!Y8<>1,"n.a.",IF(NOT(ISNUMBER('Valuation inputs'!F8)),"n.a.",IF('Valuation inputs'!F8<=0,"NM",'Valuation inputs'!E8/'Valuation inputs'!F8)))) | E17: =IF(A17="","",IF(OR('Valuation inputs'!Y8<>1,NOT(ISNUMBER('Valuation inputs'!Z8)),NOT(ISNUMBER('Valuation inputs'!G8))),"n.a.",IF(OR('Valuation inputs'!Z8<=0,'Valuation inputs'!G8<=0),"NM",'Valuation inputs'!Z8/'Valuation inputs'!G8))) | F17: =IF(A17="","",IF(OR('Valuation inputs'!Y8<>1,NOT(ISNUMBER('Valuation inputs'!AA8))),"n.a.",'Valuation inputs'!AA8/'Valuation inputs'!D8)) | G17: =IF(A17="","",IF(OR('Valuation inputs'!Y8<>1,NOT(ISNUMBER('Valuation inputs'!J8))),"n.a.",IF('Valuation inputs'!J8<=0,"NM",'Valuation inputs'!D8/'Valuation inputs'!J8))) | H17: =IF(A17="","",IF(OR(T17<>1,$B$12<>"Ready",NOT(ISNUMBER(D17))),"n.a.",100*(COUNTIFS($T$15:$T$64,1,$D$15:$D$64,">"&D17)+0.5*(COUNTIFS($T$15:$T$64,1,$D$15:$D$64,D17)-1))/($B$7-1))) | I17: =IF(A17="","",IF(OR(T17<>1,$B$12<>"Ready",NOT(ISNUMBER(E17))),"n.a.",100*(COUNTIFS($T$15:$T$64,1,$E$15:$E$64,">"&E17)+0.5*(COUNTIFS($T$15:$T$64,1,$E$15:$E$64,E17)-1))/($B$7-1))) | J17: =IF(A17="","",IF(OR(T17<>1,$B$12<>"Ready",NOT(ISNUMBER(F17))),"n.a.",100*(COUNTIFS($T$15:$T$64,1,$F$15:$F$64,"<"&F17)+0.5*(COUNTIFS($T$15:$T$64,1,$F$15:$F$64,F17)-1))/($B$7-1))) | K17: =IF(A17="","",IF(OR(T17<>1,$B$12<>"Ready",NOT(ISNUMBER(G17))),"n.a.",100*(COUNTIFS($T$15:$T$64,1,$G$15:$G$64,">"&G17)+0.5*(COUNTIFS($T$15:$T$64,1,$G$15:$G$64,G17)-1))/($B$7-1))) | L17: =IF(A17="","",IF(OR(T17<>1,$B$12<>"Ready"),"n.a.",IF($G$5=0,0,$G$5*H17)+IF($G$6=0,0,$G$6*I17)+IF($G$7=0,0,$G$7*J17)+IF($G$8=0,0,$G$8*K17))) | M17: =IF(A17="","",IF(NOT(ISNUMBER(L17)),"n.a.",1+COUNTIFS($T$15:$T$64,1,$L$15:$L$64,">"&L17))) | N17: =IF(A17="","",IF(OR(NOT(ISNUMBER(D17)),NOT(ISNUMBER($M$5))),"n.a.",IF($M$5=0,"n.a.",D17/$M$5-1))) | O17: =IF(A17="","",IF(OR(NOT(ISNUMBER(E17)),NOT(ISNUMBER($M$6))),"n.a.",IF($M$6=0,"n.a.",E17/$M$6-1))) | P17: =IF(A17="","",IF(OR(NOT(ISNUMBER(F17)),NOT(ISNUMBER($M$7))),"n.a.",F17-$M$7)) | Q17: =IF(A17="","",IF(OR(NOT(ISNUMBER(G17)),NOT(ISNUMBER($M$8))),"n.a.",IF($M$8=0,"n.a.",G17/$M$8-1))) | R17: =IF(A17="","",IF(COUNTIFS($G$5:$G$8,">0")=0,"n.a.",(IF(AND($G$5>0,ISNUMBER(D17)),1,0)+IF(AND($G$6>0,ISNUMBER(E17)),1,0)+IF(AND($G$7>0,ISNUMBER(F17)),1,0)+IF(AND($G$8>0,ISNUMBER(G17)),1,0))/COUNTIFS($G$5:$G$8,">0"))) | S17: =IF(A17="","",IF('Valuation inputs'!Y8<>1,'Valuation inputs'!AB8,IF(T17<>1,"Missing/NM required metric",IF($B$12<>"Ready",$B$12,"Ranked")))) | T17: =IF(A17="","",IF(AND('Valuation inputs'!Y8=1,$B$4<>"Needs sector profile",COUNT($G$5:$G$8)=4,MIN($G$5:$G$8)>=0,ABS($B$8-1)<=0.000001,OR($G$5=0,ISNUMBER(D17)),OR($G$6=0,ISNUMBER(E17)),OR($G$7=0,ISNUMBER(F17)),OR($G$8=0,ISNUMBER(G17))),1,0)) | U17: =IF(NOT(ISNUMBER(L17)),"",M17+COUNTIFS($T$15:T17,1,$L$15:L17,L17)-1) | V17: =IF(AND(A17<>"",T17=1,ISNUMBER(D17)),D17,"") | W17: =IF(AND(A17<>"",T17=1,ISNUMBER(E17)),E17,"") | X17: =IF(AND(A17<>"",T17=1,ISNUMBER(F17)),F17,"") | Y17: =IF(AND(A17<>"",T17=1,ISNUMBER(G17)),G17,"")
A18: =IF('Valuation inputs'!A9="","",'Valuation inputs'!A9) | B18: =IF(A18="","",'Valuation inputs'!B9) | C18: =IF(A18="","",'Valuation inputs'!D9) | D18: =IF(A18="","",IF('Valuation inputs'!Y9<>1,"n.a.",IF(NOT(ISNUMBER('Valuation inputs'!F9)),"n.a.",IF('Valuation inputs'!F9<=0,"NM",'Valuation inputs'!E9/'Valuation inputs'!F9)))) | E18: =IF(A18="","",IF(OR('Valuation inputs'!Y9<>1,NOT(ISNUMBER('Valuation inputs'!Z9)),NOT(ISNUMBER('Valuation inputs'!G9))),"n.a.",IF(OR('Valuation inputs'!Z9<=0,'Valuation inputs'!G9<=0),"NM",'Valuation inputs'!Z9/'Valuation inputs'!G9))) | F18: =IF(A18="","",IF(OR('Valuation inputs'!Y9<>1,NOT(ISNUMBER('Valuation inputs'!AA9))),"n.a.",'Valuation inputs'!AA9/'Valuation inputs'!D9)) | G18: =IF(A18="","",IF(OR('Valuation inputs'!Y9<>1,NOT(ISNUMBER('Valuation inputs'!J9))),"n.a.",IF('Valuation inputs'!J9<=0,"NM",'Valuation inputs'!D9/'Valuation inputs'!J9))) | H18: =IF(A18="","",IF(OR(T18<>1,$B$12<>"Ready",NOT(ISNUMBER(D18))),"n.a.",100*(COUNTIFS($T$15:$T$64,1,$D$15:$D$64,">"&D18)+0.5*(COUNTIFS($T$15:$T$64,1,$D$15:$D$64,D18)-1))/($B$7-1))) | I18: =IF(A18="","",IF(OR(T18<>1,$B$12<>"Ready",NOT(ISNUMBER(E18))),"n.a.",100*(COUNTIFS($T$15:$T$64,1,$E$15:$E$64,">"&E18)+0.5*(COUNTIFS($T$15:$T$64,1,$E$15:$E$64,E18)-1))/($B$7-1))) | J18: =IF(A18="","",IF(OR(T18<>1,$B$12<>"Ready",NOT(ISNUMBER(F18))),"n.a.",100*(COUNTIFS($T$15:$T$64,1,$F$15:$F$64,"<"&F18)+0.5*(COUNTIFS($T$15:$T$64,1,$F$15:$F$64,F18)-1))/($B$7-1))) | K18: =IF(A18="","",IF(OR(T18<>1,$B$12<>"Ready",NOT(ISNUMBER(G18))),"n.a.",100*(COUNTIFS($T$15:$T$64,1,$G$15:$G$64,">"&G18)+0.5*(COUNTIFS($T$15:$T$64,1,$G$15:$G$64,G18)-1))/($B$7-1))) | L18: =IF(A18="","",IF(OR(T18<>1,$B$12<>"Ready"),"n.a.",IF($G$5=0,0,$G$5*H18)+IF($G$6=0,0,$G$6*I18)+IF($G$7=0,0,$G$7*J18)+IF($G$8=0,0,$G$8*K18))) | M18: =IF(A18="","",IF(NOT(ISNUMBER(L18)),"n.a.",1+COUNTIFS($T$15:$T$64,1,$L$15:$L$64,">"&L18))) | N18: =IF(A18="","",IF(OR(NOT(ISNUMBER(D18)),NOT(ISNUMBER($M$5))),"n.a.",IF($M$5=0,"n.a.",D18/$M$5-1))) | O18: =IF(A18="","",IF(OR(NOT(ISNUMBER(E18)),NOT(ISNUMBER($M$6))),"n.a.",IF($M$6=0,"n.a.",E18/$M$6-1))) | P18: =IF(A18="","",IF(OR(NOT(ISNUMBER(F18)),NOT(ISNUMBER($M$7))),"n.a.",F18-$M$7)) | Q18: =IF(A18="","",IF(OR(NOT(ISNUMBER(G18)),NOT(ISNUMBER($M$8))),"n.a.",IF($M$8=0,"n.a.",G18/$M$8-1))) | R18: =IF(A18="","",IF(COUNTIFS($G$5:$G$8,">0")=0,"n.a.",(IF(AND($G$5>0,ISNUMBER(D18)),1,0)+IF(AND($G$6>0,ISNUMBER(E18)),1,0)+IF(AND($G$7>0,ISNUMBER(F18)),1,0)+IF(AND($G$8>0,ISNUMBER(G18)),1,0))/COUNTIFS($G$5:$G$8,">0"))) | S18: =IF(A18="","",IF('Valuation inputs'!Y9<>1,'Valuation inputs'!AB9,IF(T18<>1,"Missing/NM required metric",IF($B$12<>"Ready",$B$12,"Ranked")))) | T18: =IF(A18="","",IF(AND('Valuation inputs'!Y9=1,$B$4<>"Needs sector profile",COUNT($G$5:$G$8)=4,MIN($G$5:$G$8)>=0,ABS($B$8-1)<=0.000001,OR($G$5=0,ISNUMBER(D18)),OR($G$6=0,ISNUMBER(E18)),OR($G$7=0,ISNUMBER(F18)),OR($G$8=0,ISNUMBER(G18))),1,0)) | U18: =IF(NOT(ISNUMBER(L18)),"",M18+COUNTIFS($T$15:T18,1,$L$15:L18,L18)-1) | V18: =IF(AND(A18<>"",T18=1,ISNUMBER(D18)),D18,"") | W18: =IF(AND(A18<>"",T18=1,ISNUMBER(E18)),E18,"") | X18: =IF(AND(A18<>"",T18=1,ISNUMBER(F18)),F18,"") | Y18: =IF(AND(A18<>"",T18=1,ISNUMBER(G18)),G18,"")
A19: =IF('Valuation inputs'!A10="","",'Valuation inputs'!A10) | B19: =IF(A19="","",'Valuation inputs'!B10) | C19: =IF(A19="","",'Valuation inputs'!D10) | D19: =IF(A19="","",IF('Valuation inputs'!Y10<>1,"n.a.",IF(NOT(ISNUMBER('Valuation inputs'!F10)),"n.a.",IF('Valuation inputs'!F10<=0,"NM",'Valuation inputs'!E10/'Valuation inputs'!F10)))) | E19: =IF(A19="","",IF(OR('Valuation inputs'!Y10<>1,NOT(ISNUMBER('Valuation inputs'!Z10)),NOT(ISNUMBER('Valuation inputs'!G10))),"n.a.",IF(OR('Valuation inputs'!Z10<=0,'Valuation inputs'!G10<=0),"NM",'Valuation inputs'!Z10/'Valuation inputs'!G10))) | F19: =IF(A19="","",IF(OR('Valuation inputs'!Y10<>1,NOT(ISNUMBER('Valuation inputs'!AA10))),"n.a.",'Valuation inputs'!AA10/'Valuation inputs'!D10)) | G19: =IF(A19="","",IF(OR('Valuation inputs'!Y10<>1,NOT(ISNUMBER('Valuation inputs'!J10))),"n.a.",IF('Valuation inputs'!J10<=0,"NM",'Valuation inputs'!D10/'Valuation inputs'!J10))) | H19: =IF(A19="","",IF(OR(T19<>1,$B$12<>"Ready",NOT(ISNUMBER(D19))),"n.a.",100*(COUNTIFS($T$15:$T$64,1,$D$15:$D$64,">"&D19)+0.5*(COUNTIFS($T$15:$T$64,1,$D$15:$D$64,D19)-1))/($B$7-1))) | I19: =IF(A19="","",IF(OR(T19<>1,$B$12<>"Ready",NOT(ISNUMBER(E19))),"n.a.",100*(COUNTIFS($T$15:$T$64,1,$E$15:$E$64,">"&E19)+0.5*(COUNTIFS($T$15:$T$64,1,$E$15:$E$64,E19)-1))/($B$7-1))) | J19: =IF(A19="","",IF(OR(T19<>1,$B$12<>"Ready",NOT(ISNUMBER(F19))),"n.a.",100*(COUNTIFS($T$15:$T$64,1,$F$15:$F$64,"<"&F19)+0.5*(COUNTIFS($T$15:$T$64,1,$F$15:$F$64,F19)-1))/($B$7-1))) | K19: =IF(A19="","",IF(OR(T19<>1,$B$12<>"Ready",NOT(ISNUMBER(G19))),"n.a.",100*(COUNTIFS($T$15:$T$64,1,$G$15:$G$64,">"&G19)+0.5*(COUNTIFS($T$15:$T$64,1,$G$15:$G$64,G19)-1))/($B$7-1))) | L19: =IF(A19="","",IF(OR(T19<>1,$B$12<>"Ready"),"n.a.",IF($G$5=0,0,$G$5*H19)+IF($G$6=0,0,$G$6*I19)+IF($G$7=0,0,$G$7*J19)+IF($G$8=0,0,$G$8*K19))) | M19: =IF(A19="","",IF(NOT(ISNUMBER(L19)),"n.a.",1+COUNTIFS($T$15:$T$64,1,$L$15:$L$64,">"&L19))) | N19: =IF(A19="","",IF(OR(NOT(ISNUMBER(D19)),NOT(ISNUMBER($M$5))),"n.a.",IF($M$5=0,"n.a.",D19/$M$5-1))) | O19: =IF(A19="","",IF(OR(NOT(ISNUMBER(E19)),NOT(ISNUMBER($M$6))),"n.a.",IF($M$6=0,"n.a.",E19/$M$6-1))) | P19: =IF(A19="","",IF(OR(NOT(ISNUMBER(F19)),NOT(ISNUMBER($M$7))),"n.a.",F19-$M$7)) | Q19: =IF(A19="","",IF(OR(NOT(ISNUMBER(G19)),NOT(ISNUMBER($M$8))),"n.a.",IF($M$8=0,"n.a.",G19/$M$8-1))) | R19: =IF(A19="","",IF(COUNTIFS($G$5:$G$8,">0")=0,"n.a.",(IF(AND($G$5>0,ISNUMBER(D19)),1,0)+IF(AND($G$6>0,ISNUMBER(E19)),1,0)+IF(AND($G$7>0,ISNUMBER(F19)),1,0)+IF(AND($G$8>0,ISNUMBER(G19)),1,0))/COUNTIFS($G$5:$G$8,">0"))) | S19: =IF(A19="","",IF('Valuation inputs'!Y10<>1,'Valuation inputs'!AB10,IF(T19<>1,"Missing/NM required metric",IF($B$12<>"Ready",$B$12,"Ranked")))) | T19: =IF(A19="","",IF(AND('Valuation inputs'!Y10=1,$B$4<>"Needs sector profile",COUNT($G$5:$G$8)=4,MIN($G$5:$G$8)>=0,ABS($B$8-1)<=0.000001,OR($G$5=0,ISNUMBER(D19)),OR($G$6=0,ISNUMBER(E19)),OR($G$7=0,ISNUMBER(F19)),OR($G$8=0,ISNUMBER(G19))),1,0)) | U19: =IF(NOT(ISNUMBER(L19)),"",M19+COUNTIFS($T$15:T19,1,$L$15:L19,L19)-1) | V19: =IF(AND(A19<>"",T19=1,ISNUMBER(D19)),D19,"") | W19: =IF(AND(A19<>"",T19=1,ISNUMBER(E19)),E19,"") | X19: =IF(AND(A19<>"",T19=1,ISNUMBER(F19)),F19,"") | Y19: =IF(AND(A19<>"",T19=1,ISNUMBER(G19)),G19,"")
A20: =IF('Valuation inputs'!A11="","",'Valuation inputs'!A11) | B20: =IF(A20="","",'Valuation inputs'!B11) | C20: =IF(A20="","",'Valuation inputs'!D11) | D20: =IF(A20="","",IF('Valuation inputs'!Y11<>1,"n.a.",IF(NOT(ISNUMBER('Valuation inputs'!F11)),"n.a.",IF('Valuation inputs'!F11<=0,"NM",'Valuation inputs'!E11/'Valuation inputs'!F11)))) | E20: =IF(A20="","",IF(OR('Valuation inputs'!Y11<>1,NOT(ISNUMBER('Valuation inputs'!Z11)),NOT(ISNUMBER('Valuation inputs'!G11))),"n.a.",IF(OR('Valuation inputs'!Z11<=0,'Valuation inputs'!G11<=0),"NM",'Valuation inputs'!Z11/'Valuation inputs'!G11))) | F20: =IF(A20="","",IF(OR('Valuation inputs'!Y11<>1,NOT(ISNUMBER('Valuation inputs'!AA11))),"n.a.",'Valuation inputs'!AA11/'Valuation inputs'!D11)) | G20: =IF(A20="","",IF(OR('Valuation inputs'!Y11<>1,NOT(ISNUMBER('Valuation inputs'!J11))),"n.a.",IF('Valuation inputs'!J11<=0,"NM",'Valuation inputs'!D11/'Valuation inputs'!J11))) | H20: =IF(A20="","",IF(OR(T20<>1,$B$12<>"Ready",NOT(ISNUMBER(D20))),"n.a.",100*(COUNTIFS($T$15:$T$64,1,$D$15:$D$64,">"&D20)+0.5*(COUNTIFS($T$15:$T$64,1,$D$15:$D$64,D20)-1))/($B$7-1))) | I20: =IF(A20="","",IF(OR(T20<>1,$B$12<>"Ready",NOT(ISNUMBER(E20))),"n.a.",100*(COUNTIFS($T$15:$T$64,1,$E$15:$E$64,">"&E20)+0.5*(COUNTIFS($T$15:$T$64,1,$E$15:$E$64,E20)-1))/($B$7-1))) | J20: =IF(A20="","",IF(OR(T20<>1,$B$12<>"Ready",NOT(ISNUMBER(F20))),"n.a.",100*(COUNTIFS($T$15:$T$64,1,$F$15:$F$64,"<"&F20)+0.5*(COUNTIFS($T$15:$T$64,1,$F$15:$F$64,F20)-1))/($B$7-1))) | K20: =IF(A20="","",IF(OR(T20<>1,$B$12<>"Ready",NOT(ISNUMBER(G20))),"n.a.",100*(COUNTIFS($T$15:$T$64,1,$G$15:$G$64,">"&G20)+0.5*(COUNTIFS($T$15:$T$64,1,$G$15:$G$64,G20)-1))/($B$7-1))) | L20: =IF(A20="","",IF(OR(T20<>1,$B$12<>"Ready"),"n.a.",IF($G$5=0,0,$G$5*H20)+IF($G$6=0,0,$G$6*I20)+IF($G$7=0,0,$G$7*J20)+IF($G$8=0,0,$G$8*K20))) | M20: =IF(A20="","",IF(NOT(ISNUMBER(L20)),"n.a.",1+COUNTIFS($T$15:$T$64,1,$L$15:$L$64,">"&L20))) | N20: =IF(A20="","",IF(OR(NOT(ISNUMBER(D20)),NOT(ISNUMBER($M$5))),"n.a.",IF($M$5=0,"n.a.",D20/$M$5-1))) | O20: =IF(A20="","",IF(OR(NOT(ISNUMBER(E20)),NOT(ISNUMBER($M$6))),"n.a.",IF($M$6=0,"n.a.",E20/$M$6-1))) | P20: =IF(A20="","",IF(OR(NOT(ISNUMBER(F20)),NOT(ISNUMBER($M$7))),"n.a.",F20-$M$7)) | Q20: =IF(A20="","",IF(OR(NOT(ISNUMBER(G20)),NOT(ISNUMBER($M$8))),"n.a.",IF($M$8=0,"n.a.",G20/$M$8-1))) | R20: =IF(A20="","",IF(COUNTIFS($G$5:$G$8,">0")=0,"n.a.",(IF(AND($G$5>0,ISNUMBER(D20)),1,0)+IF(AND($G$6>0,ISNUMBER(E20)),1,0)+IF(AND($G$7>0,ISNUMBER(F20)),1,0)+IF(AND($G$8>0,ISNUMBER(G20)),1,0))/COUNTIFS($G$5:$G$8,">0"))) | S20: =IF(A20="","",IF('Valuation inputs'!Y11<>1,'Valuation inputs'!AB11,IF(T20<>1,"Missing/NM required metric",IF($B$12<>"Ready",$B$12,"Ranked")))) | T20: =IF(A20="","",IF(AND('Valuation inputs'!Y11=1,$B$4<>"Needs sector profile",COUNT($G$5:$G$8)=4,MIN($G$5:$G$8)>=0,ABS($B$8-1)<=0.000001,OR($G$5=0,ISNUMBER(D20)),OR($G$6=0,ISNUMBER(E20)),OR($G$7=0,ISNUMBER(F20)),OR($G$8=0,ISNUMBER(G20))),1,0)) | U20: =IF(NOT(ISNUMBER(L20)),"",M20+COUNTIFS($T$15:T20,1,$L$15:L20,L20)-1) | V20: =IF(AND(A20<>"",T20=1,ISNUMBER(D20)),D20,"") | W20: =IF(AND(A20<>"",T20=1,ISNUMBER(E20)),E20,"") | X20: =IF(AND(A20<>"",T20=1,ISNUMBER(F20)),F20,"") | Y20: =IF(AND(A20<>"",T20=1,ISNUMBER(G20)),G20,"")
A21: =IF('Valuation inputs'!A12="","",'Valuation inputs'!A12) | B21: =IF(A21="","",'Valuation inputs'!B12) | C21: =IF(A21="","",'Valuation inputs'!D12) | D21: =IF(A21="","",IF('Valuation inputs'!Y12<>1,"n.a.",IF(NOT(ISNUMBER('Valuation inputs'!F12)),"n.a.",IF('Valuation inputs'!F12<=0,"NM",'Valuation inputs'!E12/'Valuation inputs'!F12)))) | E21: =IF(A21="","",IF(OR('Valuation inputs'!Y12<>1,NOT(ISNUMBER('Valuation inputs'!Z12)),NOT(ISNUMBER('Valuation inputs'!G12))),"n.a.",IF(OR('Valuation inputs'!Z12<=0,'Valuation inputs'!G12<=0),"NM",'Valuation inputs'!Z12/'Valuation inputs'!G12))) | F21: =IF(A21="","",IF(OR('Valuation inputs'!Y12<>1,NOT(ISNUMBER('Valuation inputs'!AA12))),"n.a.",'Valuation inputs'!AA12/'Valuation inputs'!D12)) | G21: =IF(A21="","",IF(OR('Valuation inputs'!Y12<>1,NOT(ISNUMBER('Valuation inputs'!J12))),"n.a.",IF('Valuation inputs'!J12<=0,"NM",'Valuation inputs'!D12/'Valuation inputs'!J12))) | H21: =IF(A21="","",IF(OR(T21<>1,$B$12<>"Ready",NOT(ISNUMBER(D21))),"n.a.",100*(COUNTIFS($T$15:$T$64,1,$D$15:$D$64,">"&D21)+0.5*(COUNTIFS($T$15:$T$64,1,$D$15:$D$64,D21)-1))/($B$7-1))) | I21: =IF(A21="","",IF(OR(T21<>1,$B$12<>"Ready",NOT(ISNUMBER(E21))),"n.a.",100*(COUNTIFS($T$15:$T$64,1,$E$15:$E$64,">"&E21)+0.5*(COUNTIFS($T$15:$T$64,1,$E$15:$E$64,E21)-1))/($B$7-1))) | J21: =IF(A21="","",IF(OR(T21<>1,$B$12<>"Ready",NOT(ISNUMBER(F21))),"n.a.",100*(COUNTIFS($T$15:$T$64,1,$F$15:$F$64,"<"&F21)+0.5*(COUNTIFS($T$15:$T$64,1,$F$15:$F$64,F21)-1))/($B$7-1))) | K21: =IF(A21="","",IF(OR(T21<>1,$B$12<>"Ready",NOT(ISNUMBER(G21))),"n.a.",100*(COUNTIFS($T$15:$T$64,1,$G$15:$G$64,">"&G21)+0.5*(COUNTIFS($T$15:$T$64,1,$G$15:$G$64,G21)-1))/($B$7-1))) | L21: =IF(A21="","",IF(OR(T21<>1,$B$12<>"Ready"),"n.a.",IF($G$5=0,0,$G$5*H21)+IF($G$6=0,0,$G$6*I21)+IF($G$7=0,0,$G$7*J21)+IF($G$8=0,0,$G$8*K21))) | M21: =IF(A21="","",IF(NOT(ISNUMBER(L21)),"n.a.",1+COUNTIFS($T$15:$T$64,1,$L$15:$L$64,">"&L21))) | N21: =IF(A21="","",IF(OR(NOT(ISNUMBER(D21)),NOT(ISNUMBER($M$5))),"n.a.",IF($M$5=0,"n.a.",D21/$M$5-1))) | O21: =IF(A21="","",IF(OR(NOT(ISNUMBER(E21)),NOT(ISNUMBER($M$6))),"n.a.",IF($M$6=0,"n.a.",E21/$M$6-1))) | P21: =IF(A21="","",IF(OR(NOT(ISNUMBER(F21)),NOT(ISNUMBER($M$7))),"n.a.",F21-$M$7)) | Q21: =IF(A21="","",IF(OR(NOT(ISNUMBER(G21)),NOT(ISNUMBER($M$8))),"n.a.",IF($M$8=0,"n.a.",G21/$M$8-1))) | R21: =IF(A21="","",IF(COUNTIFS($G$5:$G$8,">0")=0,"n.a.",(IF(AND($G$5>0,ISNUMBER(D21)),1,0)+IF(AND($G$6>0,ISNUMBER(E21)),1,0)+IF(AND($G$7>0,ISNUMBER(F21)),1,0)+IF(AND($G$8>0,ISNUMBER(G21)),1,0))/COUNTIFS($G$5:$G$8,">0"))) | S21: =IF(A21="","",IF('Valuation inputs'!Y12<>1,'Valuation inputs'!AB12,IF(T21<>1,"Missing/NM required metric",IF($B$12<>"Ready",$B$12,"Ranked")))) | T21: =IF(A21="","",IF(AND('Valuation inputs'!Y12=1,$B$4<>"Needs sector profile",COUNT($G$5:$G$8)=4,MIN($G$5:$G$8)>=0,ABS($B$8-1)<=0.000001,OR($G$5=0,ISNUMBER(D21)),OR($G$6=0,ISNUMBER(E21)),OR($G$7=0,ISNUMBER(F21)),OR($G$8=0,ISNUMBER(G21))),1,0)) | U21: =IF(NOT(ISNUMBER(L21)),"",M21+COUNTIFS($T$15:T21,1,$L$15:L21,L21)-1) | V21: =IF(AND(A21<>"",T21=1,ISNUMBER(D21)),D21,"") | W21: =IF(AND(A21<>"",T21=1,ISNUMBER(E21)),E21,"") | X21: =IF(AND(A21<>"",T21=1,ISNUMBER(F21)),F21,"") | Y21: =IF(AND(A21<>"",T21=1,ISNUMBER(G21)),G21,"")
A22: =IF('Valuation inputs'!A13="","",'Valuation inputs'!A13) | B22: =IF(A22="","",'Valuation inputs'!B13) | C22: =IF(A22="","",'Valuation inputs'!D13) | D22: =IF(A22="","",IF('Valuation inputs'!Y13<>1,"n.a.",IF(NOT(ISNUMBER('Valuation inputs'!F13)),"n.a.",IF('Valuation inputs'!F13<=0,"NM",'Valuation inputs'!E13/'Valuation inputs'!F13)))) | E22: =IF(A22="","",IF(OR('Valuation inputs'!Y13<>1,NOT(ISNUMBER('Valuation inputs'!Z13)),NOT(ISNUMBER('Valuation inputs'!G13))),"n.a.",IF(OR('Valuation inputs'!Z13<=0,'Valuation inputs'!G13<=0),"NM",'Valuation inputs'!Z13/'Valuation inputs'!G13))) | F22: =IF(A22="","",IF(OR('Valuation inputs'!Y13<>1,NOT(ISNUMBER('Valuation inputs'!AA13))),"n.a.",'Valuation inputs'!AA13/'Valuation inputs'!D13)) | G22: =IF(A22="","",IF(OR('Valuation inputs'!Y13<>1,NOT(ISNUMBER('Valuation inputs'!J13))),"n.a.",IF('Valuation inputs'!J13<=0,"NM",'Valuation inputs'!D13/'Valuation inputs'!J13))) | H22: =IF(A22="","",IF(OR(T22<>1,$B$12<>"Ready",NOT(ISNUMBER(D22))),"n.a.",100*(COUNTIFS($T$15:$T$64,1,$D$15:$D$64,">"&D22)+0.5*(COUNTIFS($T$15:$T$64,1,$D$15:$D$64,D22)-1))/($B$7-1))) | I22: =IF(A22="","",IF(OR(T22<>1,$B$12<>"Ready",NOT(ISNUMBER(E22))),"n.a.",100*(COUNTIFS($T$15:$T$64,1,$E$15:$E$64,">"&E22)+0.5*(COUNTIFS($T$15:$T$64,1,$E$15:$E$64,E22)-1))/($B$7-1))) | J22: =IF(A22="","",IF(OR(T22<>1,$B$12<>"Ready",NOT(ISNUMBER(F22))),"n.a.",100*(COUNTIFS($T$15:$T$64,1,$F$15:$F$64,"<"&F22)+0.5*(COUNTIFS($T$15:$T$64,1,$F$15:$F$64,F22)-1))/($B$7-1))) | K22: =IF(A22="","",IF(OR(T22<>1,$B$12<>"Ready",NOT(ISNUMBER(G22))),"n.a.",100*(COUNTIFS($T$15:$T$64,1,$G$15:$G$64,">"&G22)+0.5*(COUNTIFS($T$15:$T$64,1,$G$15:$G$64,G22)-1))/($B$7-1))) | L22: =IF(A22="","",IF(OR(T22<>1,$B$12<>"Ready"),"n.a.",IF($G$5=0,0,$G$5*H22)+IF($G$6=0,0,$G$6*I22)+IF($G$7=0,0,$G$7*J22)+IF($G$8=0,0,$G$8*K22))) | M22: =IF(A22="","",IF(NOT(ISNUMBER(L22)),"n.a.",1+COUNTIFS($T$15:$T$64,1,$L$15:$L$64,">"&L22))) | N22: =IF(A22="","",IF(OR(NOT(ISNUMBER(D22)),NOT(ISNUMBER($M$5))),"n.a.",IF($M$5=0,"n.a.",D22/$M$5-1))) | O22: =IF(A22="","",IF(OR(NOT(ISNUMBER(E22)),NOT(ISNUMBER($M$6))),"n.a.",IF($M$6=0,"n.a.",E22/$M$6-1))) | P22: =IF(A22="","",IF(OR(NOT(ISNUMBER(F22)),NOT(ISNUMBER($M$7))),"n.a.",F22-$M$7)) | Q22: =IF(A22="","",IF(OR(NOT(ISNUMBER(G22)),NOT(ISNUMBER($M$8))),"n.a.",IF($M$8=0,"n.a.",G22/$M$8-1))) | R22: =IF(A22="","",IF(COUNTIFS($G$5:$G$8,">0")=0,"n.a.",(IF(AND($G$5>0,ISNUMBER(D22)),1,0)+IF(AND($G$6>0,ISNUMBER(E22)),1,0)+IF(AND($G$7>0,ISNUMBER(F22)),1,0)+IF(AND($G$8>0,ISNUMBER(G22)),1,0))/COUNTIFS($G$5:$G$8,">0"))) | S22: =IF(A22="","",IF('Valuation inputs'!Y13<>1,'Valuation inputs'!AB13,IF(T22<>1,"Missing/NM required metric",IF($B$12<>"Ready",$B$12,"Ranked")))) | T22: =IF(A22="","",IF(AND('Valuation inputs'!Y13=1,$B$4<>"Needs sector profile",COUNT($G$5:$G$8)=4,MIN($G$5:$G$8)>=0,ABS($B$8-1)<=0.000001,OR($G$5=0,ISNUMBER(D22)),OR($G$6=0,ISNUMBER(E22)),OR($G$7=0,ISNUMBER(F22)),OR($G$8=0,ISNUMBER(G22))),1,0)) | U22: =IF(NOT(ISNUMBER(L22)),"",M22+COUNTIFS($T$15:T22,1,$L$15:L22,L22)-1) | V22: =IF(AND(A22<>"",T22=1,ISNUMBER(D22)),D22,"") | W22: =IF(AND(A22<>"",T22=1,ISNUMBER(E22)),E22,"") | X22: =IF(AND(A22<>"",T22=1,ISNUMBER(F22)),F22,"") | Y22: =IF(AND(A22<>"",T22=1,ISNUMBER(G22)),G22,"")
A23: =IF('Valuation inputs'!A14="","",'Valuation inputs'!A14) | B23: =IF(A23="","",'Valuation inputs'!B14) | C23: =IF(A23="","",'Valuation inputs'!D14) | D23: =IF(A23="","",IF('Valuation inputs'!Y14<>1,"n.a.",IF(NOT(ISNUMBER('Valuation inputs'!F14)),"n.a.",IF('Valuation inputs'!F14<=0,"NM",'Valuation inputs'!E14/'Valuation inputs'!F14)))) | E23: =IF(A23="","",IF(OR('Valuation inputs'!Y14<>1,NOT(ISNUMBER('Valuation inputs'!Z14)),NOT(ISNUMBER('Valuation inputs'!G14))),"n.a.",IF(OR('Valuation inputs'!Z14<=0,'Valuation inputs'!G14<=0),"NM",'Valuation inputs'!Z14/'Valuation inputs'!G14))) | F23: =IF(A23="","",IF(OR('Valuation inputs'!Y14<>1,NOT(ISNUMBER('Valuation inputs'!AA14))),"n.a.",'Valuation inputs'!AA14/'Valuation inputs'!D14)) | G23: =IF(A23="","",IF(OR('Valuation inputs'!Y14<>1,NOT(ISNUMBER('Valuation inputs'!J14))),"n.a.",IF('Valuation inputs'!J14<=0,"NM",'Valuation inputs'!D14/'Valuation inputs'!J14))) | H23: =IF(A23="","",IF(OR(T23<>1,$B$12<>"Ready",NOT(ISNUMBER(D23))),"n.a.",100*(COUNTIFS($T$15:$T$64,1,$D$15:$D$64,">"&D23)+0.5*(COUNTIFS($T$15:$T$64,1,$D$15:$D$64,D23)-1))/($B$7-1))) | I23: =IF(A23="","",IF(OR(T23<>1,$B$12<>"Ready",NOT(ISNUMBER(E23))),"n.a.",100*(COUNTIFS($T$15:$T$64,1,$E$15:$E$64,">"&E23)+0.5*(COUNTIFS($T$15:$T$64,1,$E$15:$E$64,E23)-1))/($B$7-1))) | J23: =IF(A23="","",IF(OR(T23<>1,$B$12<>"Ready",NOT(ISNUMBER(F23))),"n.a.",100*(COUNTIFS($T$15:$T$64,1,$F$15:$F$64,"<"&F23)+0.5*(COUNTIFS($T$15:$T$64,1,$F$15:$F$64,F23)-1))/($B$7-1))) | K23: =IF(A23="","",IF(OR(T23<>1,$B$12<>"Ready",NOT(ISNUMBER(G23))),"n.a.",100*(COUNTIFS($T$15:$T$64,1,$G$15:$G$64,">"&G23)+0.5*(COUNTIFS($T$15:$T$64,1,$G$15:$G$64,G23)-1))/($B$7-1))) | L23: =IF(A23="","",IF(OR(T23<>1,$B$12<>"Ready"),"n.a.",IF($G$5=0,0,$G$5*H23)+IF($G$6=0,0,$G$6*I23)+IF($G$7=0,0,$G$7*J23)+IF($G$8=0,0,$G$8*K23))) | M23: =IF(A23="","",IF(NOT(ISNUMBER(L23)),"n.a.",1+COUNTIFS($T$15:$T$64,1,$L$15:$L$64,">"&L23))) | N23: =IF(A23="","",IF(OR(NOT(ISNUMBER(D23)),NOT(ISNUMBER($M$5))),"n.a.",IF($M$5=0,"n.a.",D23/$M$5-1))) | O23: =IF(A23="","",IF(OR(NOT(ISNUMBER(E23)),NOT(ISNUMBER($M$6))),"n.a.",IF($M$6=0,"n.a.",E23/$M$6-1))) | P23: =IF(A23="","",IF(OR(NOT(ISNUMBER(F23)),NOT(ISNUMBER($M$7))),"n.a.",F23-$M$7)) | Q23: =IF(A23="","",IF(OR(NOT(ISNUMBER(G23)),NOT(ISNUMBER($M$8))),"n.a.",IF($M$8=0,"n.a.",G23/$M$8-1))) | R23: =IF(A23="","",IF(COUNTIFS($G$5:$G$8,">0")=0,"n.a.",(IF(AND($G$5>0,ISNUMBER(D23)),1,0)+IF(AND($G$6>0,ISNUMBER(E23)),1,0)+IF(AND($G$7>0,ISNUMBER(F23)),1,0)+IF(AND($G$8>0,ISNUMBER(G23)),1,0))/COUNTIFS($G$5:$G$8,">0"))) | S23: =IF(A23="","",IF('Valuation inputs'!Y14<>1,'Valuation inputs'!AB14,IF(T23<>1,"Missing/NM required metric",IF($B$12<>"Ready",$B$12,"Ranked")))) | T23: =IF(A23="","",IF(AND('Valuation inputs'!Y14=1,$B$4<>"Needs sector profile",COUNT($G$5:$G$8)=4,MIN($G$5:$G$8)>=0,ABS($B$8-1)<=0.000001,OR($G$5=0,ISNUMBER(D23)),OR($G$6=0,ISNUMBER(E23)),OR($G$7=0,ISNUMBER(F23)),OR($G$8=0,ISNUMBER(G23))),1,0)) | U23: =IF(NOT(ISNUMBER(L23)),"",M23+COUNTIFS($T$15:T23,1,$L$15:L23,L23)-1) | V23: =IF(AND(A23<>"",T23=1,ISNUMBER(D23)),D23,"") | W23: =IF(AND(A23<>"",T23=1,ISNUMBER(E23)),E23,"") | X23: =IF(AND(A23<>"",T23=1,ISNUMBER(F23)),F23,"") | Y23: =IF(AND(A23<>"",T23=1,ISNUMBER(G23)),G23,"")
A24: =IF('Valuation inputs'!A15="","",'Valuation inputs'!A15) | B24: =IF(A24="","",'Valuation inputs'!B15) | C24: =IF(A24="","",'Valuation inputs'!D15) | D24: =IF(A24="","",IF('Valuation inputs'!Y15<>1,"n.a.",IF(NOT(ISNUMBER('Valuation inputs'!F15)),"n.a.",IF('Valuation inputs'!F15<=0,"NM",'Valuation inputs'!E15/'Valuation inputs'!F15)))) | E24: =IF(A24="","",IF(OR('Valuation inputs'!Y15<>1,NOT(ISNUMBER('Valuation inputs'!Z15)),NOT(ISNUMBER('Valuation inputs'!G15))),"n.a.",IF(OR('Valuation inputs'!Z15<=0,'Valuation inputs'!G15<=0),"NM",'Valuation inputs'!Z15/'Valuation inputs'!G15))) | F24: =IF(A24="","",IF(OR('Valuation inputs'!Y15<>1,NOT(ISNUMBER('Valuation inputs'!AA15))),"n.a.",'Valuation inputs'!AA15/'Valuation inputs'!D15)) | G24: =IF(A24="","",IF(OR('Valuation inputs'!Y15<>1,NOT(ISNUMBER('Valuation inputs'!J15))),"n.a.",IF('Valuation inputs'!J15<=0,"NM",'Valuation inputs'!D15/'Valuation inputs'!J15))) | H24: =IF(A24="","",IF(OR(T24<>1,$B$12<>"Ready",NOT(ISNUMBER(D24))),"n.a.",100*(COUNTIFS($T$15:$T$64,1,$D$15:$D$64,">"&D24)+0.5*(COUNTIFS($T$15:$T$64,1,$D$15:$D$64,D24)-1))/($B$7-1))) | I24: =IF(A24="","",IF(OR(T24<>1,$B$12<>"Ready",NOT(ISNUMBER(E24))),"n.a.",100*(COUNTIFS($T$15:$T$64,1,$E$15:$E$64,">"&E24)+0.5*(COUNTIFS($T$15:$T$64,1,$E$15:$E$64,E24)-1))/($B$7-1))) | J24: =IF(A24="","",IF(OR(T24<>1,$B$12<>"Ready",NOT(ISNUMBER(F24))),"n.a.",100*(COUNTIFS($T$15:$T$64,1,$F$15:$F$64,"<"&F24)+0.5*(COUNTIFS($T$15:$T$64,1,$F$15:$F$64,F24)-1))/($B$7-1))) | K24: =IF(A24="","",IF(OR(T24<>1,$B$12<>"Ready",NOT(ISNUMBER(G24))),"n.a.",100*(COUNTIFS($T$15:$T$64,1,$G$15:$G$64,">"&G24)+0.5*(COUNTIFS($T$15:$T$64,1,$G$15:$G$64,G24)-1))/($B$7-1))) | L24: =IF(A24="","",IF(OR(T24<>1,$B$12<>"Ready"),"n.a.",IF($G$5=0,0,$G$5*H24)+IF($G$6=0,0,$G$6*I24)+IF($G$7=0,0,$G$7*J24)+IF($G$8=0,0,$G$8*K24))) | M24: =IF(A24="","",IF(NOT(ISNUMBER(L24)),"n.a.",1+COUNTIFS($T$15:$T$64,1,$L$15:$L$64,">"&L24))) | N24: =IF(A24="","",IF(OR(NOT(ISNUMBER(D24)),NOT(ISNUMBER($M$5))),"n.a.",IF($M$5=0,"n.a.",D24/$M$5-1))) | O24: =IF(A24="","",IF(OR(NOT(ISNUMBER(E24)),NOT(ISNUMBER($M$6))),"n.a.",IF($M$6=0,"n.a.",E24/$M$6-1))) | P24: =IF(A24="","",IF(OR(NOT(ISNUMBER(F24)),NOT(ISNUMBER($M$7))),"n.a.",F24-$M$7)) | Q24: =IF(A24="","",IF(OR(NOT(ISNUMBER(G24)),NOT(ISNUMBER($M$8))),"n.a.",IF($M$8=0,"n.a.",G24/$M$8-1))) | R24: =IF(A24="","",IF(COUNTIFS($G$5:$G$8,">0")=0,"n.a.",(IF(AND($G$5>0,ISNUMBER(D24)),1,0)+IF(AND($G$6>0,ISNUMBER(E24)),1,0)+IF(AND($G$7>0,ISNUMBER(F24)),1,0)+IF(AND($G$8>0,ISNUMBER(G24)),1,0))/COUNTIFS($G$5:$G$8,">0"))) | S24: =IF(A24="","",IF('Valuation inputs'!Y15<>1,'Valuation inputs'!AB15,IF(T24<>1,"Missing/NM required metric",IF($B$12<>"Ready",$B$12,"Ranked")))) | T24: =IF(A24="","",IF(AND('Valuation inputs'!Y15=1,$B$4<>"Needs sector profile",COUNT($G$5:$G$8)=4,MIN($G$5:$G$8)>=0,ABS($B$8-1)<=0.000001,OR($G$5=0,ISNUMBER(D24)),OR($G$6=0,ISNUMBER(E24)),OR($G$7=0,ISNUMBER(F24)),OR($G$8=0,ISNUMBER(G24))),1,0)) | U24: =IF(NOT(ISNUMBER(L24)),"",M24+COUNTIFS($T$15:T24,1,$L$15:L24,L24)-1) | V24: =IF(AND(A24<>"",T24=1,ISNUMBER(D24)),D24,"") | W24: =IF(AND(A24<>"",T24=1,ISNUMBER(E24)),E24,"") | X24: =IF(AND(A24<>"",T24=1,ISNUMBER(F24)),F24,"") | Y24: =IF(AND(A24<>"",T24=1,ISNUMBER(G24)),G24,"")
A25: =IF('Valuation inputs'!A16="","",'Valuation inputs'!A16) | B25: =IF(A25="","",'Valuation inputs'!B16) | C25: =IF(A25="","",'Valuation inputs'!D16) | D25: =IF(A25="","",IF('Valuation inputs'!Y16<>1,"n.a.",IF(NOT(ISNUMBER('Valuation inputs'!F16)),"n.a.",IF('Valuation inputs'!F16<=0,"NM",'Valuation inputs'!E16/'Valuation inputs'!F16)))) | E25: =IF(A25="","",IF(OR('Valuation inputs'!Y16<>1,NOT(ISNUMBER('Valuation inputs'!Z16)),NOT(ISNUMBER('Valuation inputs'!G16))),"n.a.",IF(OR('Valuation inputs'!Z16<=0,'Valuation inputs'!G16<=0),"NM",'Valuation inputs'!Z16/'Valuation inputs'!G16))) | F25: =IF(A25="","",IF(OR('Valuation inputs'!Y16<>1,NOT(ISNUMBER('Valuation inputs'!AA16))),"n.a.",'Valuation inputs'!AA16/'Valuation inputs'!D16)) | G25: =IF(A25="","",IF(OR('Valuation inputs'!Y16<>1,NOT(ISNUMBER('Valuation inputs'!J16))),"n.a.",IF('Valuation inputs'!J16<=0,"NM",'Valuation inputs'!D16/'Valuation inputs'!J16))) | H25: =IF(A25="","",IF(OR(T25<>1,$B$12<>"Ready",NOT(ISNUMBER(D25))),"n.a.",100*(COUNTIFS($T$15:$T$64,1,$D$15:$D$64,">"&D25)+0.5*(COUNTIFS($T$15:$T$64,1,$D$15:$D$64,D25)-1))/($B$7-1))) | I25: =IF(A25="","",IF(OR(T25<>1,$B$12<>"Ready",NOT(ISNUMBER(E25))),"n.a.",100*(COUNTIFS($T$15:$T$64,1,$E$15:$E$64,">"&E25)+0.5*(COUNTIFS($T$15:$T$64,1,$E$15:$E$64,E25)-1))/($B$7-1))) | J25: =IF(A25="","",IF(OR(T25<>1,$B$12<>"Ready",NOT(ISNUMBER(F25))),"n.a.",100*(COUNTIFS($T$15:$T$64,1,$F$15:$F$64,"<"&F25)+0.5*(COUNTIFS($T$15:$T$64,1,$F$15:$F$64,F25)-1))/($B$7-1))) | K25: =IF(A25="","",IF(OR(T25<>1,$B$12<>"Ready",NOT(ISNUMBER(G25))),"n.a.",100*(COUNTIFS($T$15:$T$64,1,$G$15:$G$64,">"&G25)+0.5*(COUNTIFS($T$15:$T$64,1,$G$15:$G$64,G25)-1))/($B$7-1))) | L25: =IF(A25="","",IF(OR(T25<>1,$B$12<>"Ready"),"n.a.",IF($G$5=0,0,$G$5*H25)+IF($G$6=0,0,$G$6*I25)+IF($G$7=0,0,$G$7*J25)+IF($G$8=0,0,$G$8*K25))) | M25: =IF(A25="","",IF(NOT(ISNUMBER(L25)),"n.a.",1+COUNTIFS($T$15:$T$64,1,$L$15:$L$64,">"&L25))) | N25: =IF(A25="","",IF(OR(NOT(ISNUMBER(D25)),NOT(ISNUMBER($M$5))),"n.a.",IF($M$5=0,"n.a.",D25/$M$5-1))) | O25: =IF(A25="","",IF(OR(NOT(ISNUMBER(E25)),NOT(ISNUMBER($M$6))),"n.a.",IF($M$6=0,"n.a.",E25/$M$6-1))) | P25: =IF(A25="","",IF(OR(NOT(ISNUMBER(F25)),NOT(ISNUMBER($M$7))),"n.a.",F25-$M$7)) | Q25: =IF(A25="","",IF(OR(NOT(ISNUMBER(G25)),NOT(ISNUMBER($M$8))),"n.a.",IF($M$8=0,"n.a.",G25/$M$8-1))) | R25: =IF(A25="","",IF(COUNTIFS($G$5:$G$8,">0")=0,"n.a.",(IF(AND($G$5>0,ISNUMBER(D25)),1,0)+IF(AND($G$6>0,ISNUMBER(E25)),1,0)+IF(AND($G$7>0,ISNUMBER(F25)),1,0)+IF(AND($G$8>0,ISNUMBER(G25)),1,0))/COUNTIFS($G$5:$G$8,">0"))) | S25: =IF(A25="","",IF('Valuation inputs'!Y16<>1,'Valuation inputs'!AB16,IF(T25<>1,"Missing/NM required metric",IF($B$12<>"Ready",$B$12,"Ranked")))) | T25: =IF(A25="","",IF(AND('Valuation inputs'!Y16=1,$B$4<>"Needs sector profile",COUNT($G$5:$G$8)=4,MIN($G$5:$G$8)>=0,ABS($B$8-1)<=0.000001,OR($G$5=0,ISNUMBER(D25)),OR($G$6=0,ISNUMBER(E25)),OR($G$7=0,ISNUMBER(F25)),OR($G$8=0,ISNUMBER(G25))),1,0)) | U25: =IF(NOT(ISNUMBER(L25)),"",M25+COUNTIFS($T$15:T25,1,$L$15:L25,L25)-1) | V25: =IF(AND(A25<>"",T25=1,ISNUMBER(D25)),D25,"") | W25: =IF(AND(A25<>"",T25=1,ISNUMBER(E25)),E25,"") | X25: =IF(AND(A25<>"",T25=1,ISNUMBER(F25)),F25,"") | Y25: =IF(AND(A25<>"",T25=1,ISNUMBER(G25)),G25,"")
A26: =IF('Valuation inputs'!A17="","",'Valuation inputs'!A17) | B26: =IF(A26="","",'Valuation inputs'!B17) | C26: =IF(A26="","",'Valuation inputs'!D17) | D26: =IF(A26="","",IF('Valuation inputs'!Y17<>1,"n.a.",IF(NOT(ISNUMBER('Valuation inputs'!F17)),"n.a.",IF('Valuation inputs'!F17<=0,"NM",'Valuation inputs'!E17/'Valuation inputs'!F17)))) | E26: =IF(A26="","",IF(OR('Valuation inputs'!Y17<>1,NOT(ISNUMBER('Valuation inputs'!Z17)),NOT(ISNUMBER('Valuation inputs'!G17))),"n.a.",IF(OR('Valuation inputs'!Z17<=0,'Valuation inputs'!G17<=0),"NM",'Valuation inputs'!Z17/'Valuation inputs'!G17))) | F26: =IF(A26="","",IF(OR('Valuation inputs'!Y17<>1,NOT(ISNUMBER('Valuation inputs'!AA17))),"n.a.",'Valuation inputs'!AA17/'Valuation inputs'!D17)) | G26: =IF(A26="","",IF(OR('Valuation inputs'!Y17<>1,NOT(ISNUMBER('Valuation inputs'!J17))),"n.a.",IF('Valuation inputs'!J17<=0,"NM",'Valuation inputs'!D17/'Valuation inputs'!J17))) | H26: =IF(A26="","",IF(OR(T26<>1,$B$12<>"Ready",NOT(ISNUMBER(D26))),"n.a.",100*(COUNTIFS($T$15:$T$64,1,$D$15:$D$64,">"&D26)+0.5*(COUNTIFS($T$15:$T$64,1,$D$15:$D$64,D26)-1))/($B$7-1))) | I26: =IF(A26="","",IF(OR(T26<>1,$B$12<>"Ready",NOT(ISNUMBER(E26))),"n.a.",100*(COUNTIFS($T$15:$T$64,1,$E$15:$E$64,">"&E26)+0.5*(COUNTIFS($T$15:$T$64,1,$E$15:$E$64,E26)-1))/($B$7-1))) | J26: =IF(A26="","",IF(OR(T26<>1,$B$12<>"Ready",NOT(ISNUMBER(F26))),"n.a.",100*(COUNTIFS($T$15:$T$64,1,$F$15:$F$64,"<"&F26)+0.5*(COUNTIFS($T$15:$T$64,1,$F$15:$F$64,F26)-1))/($B$7-1))) | K26: =IF(A26="","",IF(OR(T26<>1,$B$12<>"Ready",NOT(ISNUMBER(G26))),"n.a.",100*(COUNTIFS($T$15:$T$64,1,$G$15:$G$64,">"&G26)+0.5*(COUNTIFS($T$15:$T$64,1,$G$15:$G$64,G26)-1))/($B$7-1))) | L26: =IF(A26="","",IF(OR(T26<>1,$B$12<>"Ready"),"n.a.",IF($G$5=0,0,$G$5*H26)+IF($G$6=0,0,$G$6*I26)+IF($G$7=0,0,$G$7*J26)+IF($G$8=0,0,$G$8*K26))) | M26: =IF(A26="","",IF(NOT(ISNUMBER(L26)),"n.a.",1+COUNTIFS($T$15:$T$64,1,$L$15:$L$64,">"&L26))) | N26: =IF(A26="","",IF(OR(NOT(ISNUMBER(D26)),NOT(ISNUMBER($M$5))),"n.a.",IF($M$5=0,"n.a.",D26/$M$5-1))) | O26: =IF(A26="","",IF(OR(NOT(ISNUMBER(E26)),NOT(ISNUMBER($M$6))),"n.a.",IF($M$6=0,"n.a.",E26/$M$6-1))) | P26: =IF(A26="","",IF(OR(NOT(ISNUMBER(F26)),NOT(ISNUMBER($M$7))),"n.a.",F26-$M$7)) | Q26: =IF(A26="","",IF(OR(NOT(ISNUMBER(G26)),NOT(ISNUMBER($M$8))),"n.a.",IF($M$8=0,"n.a.",G26/$M$8-1))) | R26: =IF(A26="","",IF(COUNTIFS($G$5:$G$8,">0")=0,"n.a.",(IF(AND($G$5>0,ISNUMBER(D26)),1,0)+IF(AND($G$6>0,ISNUMBER(E26)),1,0)+IF(AND($G$7>0,ISNUMBER(F26)),1,0)+IF(AND($G$8>0,ISNUMBER(G26)),1,0))/COUNTIFS($G$5:$G$8,">0"))) | S26: =IF(A26="","",IF('Valuation inputs'!Y17<>1,'Valuation inputs'!AB17,IF(T26<>1,"Missing/NM required metric",IF($B$12<>"Ready",$B$12,"Ranked")))) | T26: =IF(A26="","",IF(AND('Valuation inputs'!Y17=1,$B$4<>"Needs sector profile",COUNT($G$5:$G$8)=4,MIN($G$5:$G$8)>=0,ABS($B$8-1)<=0.000001,OR($G$5=0,ISNUMBER(D26)),OR($G$6=0,ISNUMBER(E26)),OR($G$7=0,ISNUMBER(F26)),OR($G$8=0,ISNUMBER(G26))),1,0)) | U26: =IF(NOT(ISNUMBER(L26)),"",M26+COUNTIFS($T$15:T26,1,$L$15:L26,L26)-1) | V26: =IF(AND(A26<>"",T26=1,ISNUMBER(D26)),D26,"") | W26: =IF(AND(A26<>"",T26=1,ISNUMBER(E26)),E26,"") | X26: =IF(AND(A26<>"",T26=1,ISNUMBER(F26)),F26,"") | Y26: =IF(AND(A26<>"",T26=1,ISNUMBER(G26)),G26,"")
... A64: =IF('Valuation inputs'!A55="","",'Valuation inputs'!A55) | B64: =IF(A64="","",'Valuation inputs'!B55) | C64: =IF(A64="","",'Valuation inputs'!D55) | D64: =IF(A64="","",IF('Valuation inputs'!Y55<>1,"n.a.",IF(NOT(ISNUMBER('Valuation inputs'!F55)),"n.a.",IF('Valuation inputs'!F55<=0,"NM",'Valuation inputs'!E55/'Valuation inputs'!F55)))) | E64: =IF(A64="","",IF(OR('Valuation inputs'!Y55<>1,NOT(ISNUMBER('Valuation inputs'!Z55)),NOT(ISNUMBER('Valuation inputs'!G55))),"n.a.",IF(OR('Valuation inputs'!Z55<=0,'Valuation inputs'!G55<=0),"NM",'Valuation inputs'!Z55/'Valuation inputs'!G55))) | F64: =IF(A64="","",IF(OR('Valuation inputs'!Y55<>1,NOT(ISNUMBER('Valuation inputs'!AA55))),"n.a.",'Valuation inputs'!AA55/'Valuation inputs'!D55)) | G64: =IF(A64="","",IF(OR('Valuation inputs'!Y55<>1,NOT(ISNUMBER('Valuation inputs'!J55))),"n.a.",IF('Valuation inputs'!J55<=0,"NM",'Valuation inputs'!D55/'Valuation inputs'!J55))) | H64: =IF(A64="","",IF(OR(T64<>1,$B$12<>"Ready",NOT(ISNUMBER(D64))),"n.a.",100*(COUNTIFS($T$15:$T$64,1,$D$15:$D$64,">"&D64)+0.5*(COUNTIFS($T$15:$T$64,1,$D$15:$D$64,D64)-1))/($B$7-1))) | I64: =IF(A64="","",IF(OR(T64<>1,$B$12<>"Ready",NOT(ISNUMBER(E64))),"n.a.",100*(COUNTIFS($T$15:$T$64,1,$E$15:$E$64,">"&E64)+0.5*(COUNTIFS($T$15:$T$64,1,$E$15:$E$64,E64)-1))/($B$7-1))) | J64: =IF(A64="","",IF(OR(T64<>1,$B$12<>"Ready",NOT(ISNUMBER(F64))),"n.a.",100*(COUNTIFS($T$15:$T$64,1,$F$15:$F$64,"<"&F64)+0.5*(COUNTIFS($T$15:$T$64,1,$F$15:$F$64,F64)-1))/($B$7-1))) | K64: =IF(A64="","",IF(OR(T64<>1,$B$12<>"Ready",NOT(ISNUMBER(G64))),"n.a.",100*(COUNTIFS($T$15:$T$64,1,$G$15:$G$64,">"&G64)+0.5*(COUNTIFS($T$15:$T$64,1,$G$15:$G$64,G64)-1))/($B$7-1))) | L64: =IF(A64="","",IF(OR(T64<>1,$B$12<>"Ready"),"n.a.",IF($G$5=0,0,$G$5*H64)+IF($G$6=0,0,$G$6*I64)+IF($G$7=0,0,$G$7*J64)+IF($G$8=0,0,$G$8*K64))) | M64: =IF(A64="","",IF(NOT(ISNUMBER(L64)),"n.a.",1+COUNTIFS($T$15:$T$64,1,$L$15:$L$64,">"&L64))) | N64: =IF(A64="","",IF(OR(NOT(ISNUMBER(D64)),NOT(ISNUMBER($M$5))),"n.a.",IF($M$5=0,"n.a.",D64/$M$5-1))) | O64: =IF(A64="","",IF(OR(NOT(ISNUMBER(E64)),NOT(ISNUMBER($M$6))),"n.a.",IF($M$6=0,"n.a.",E64/$M$6-1))) | P64: =IF(A64="","",IF(OR(NOT(ISNUMBER(F64)),NOT(ISNUMBER($M$7))),"n.a.",F64-$M$7)) | Q64: =IF(A64="","",IF(OR(NOT(ISNUMBER(G64)),NOT(ISNUMBER($M$8))),"n.a.",IF($M$8=0,"n.a.",G64/$M$8-1))) | R64: =IF(A64="","",IF(COUNTIFS($G$5:$G$8,">0")=0,"n.a.",(IF(AND($G$5>0,ISNUMBER(D64)),1,0)+IF(AND($G$6>0,ISNUMBER(E64)),1,0)+IF(AND($G$7>0,ISNUMBER(F64)),1,0)+IF(AND($G$8>0,ISNUMBER(G64)),1,0))/COUNTIFS($G$5:$G$8,">0"))) | S64: =IF(A64="","",IF('Valuation inputs'!Y55<>1,'Valuation inputs'!AB55,IF(T64<>1,"Missing/NM required metric",IF($B$12<>"Ready",$B$12,"Ranked")))) | T64: =IF(A64="","",IF(AND('Valuation inputs'!Y55=1,$B$4<>"Needs sector profile",COUNT($G$5:$G$8)=4,MIN($G$5:$G$8)>=0,ABS($B$8-1)<=0.000001,OR($G$5=0,ISNUMBER(D64)),OR($G$6=0,ISNUMBER(E64)),OR($G$7=0,ISNUMBER(F64)),OR($G$8=0,ISNUMBER(G64))),1,0)) | U64: =IF(NOT(ISNUMBER(L64)),"",M64+COUNTIFS($T$15:T64,1,$L$15:L64,L64)-1) | V64: =IF(AND(A64<>"",T64=1,ISNUMBER(D64)),D64,"") | W64: =IF(AND(A64<>"",T64=1,ISNUMBER(E64)),E64,"") | X64: =IF(AND(A64<>"",T64=1,ISNUMBER(F64)),F64,"") | Y64: =IF(AND(A64<>"",T64=1,ISNUMBER(G64)),G64,"")

Sheet Rules
A2: Investment model rules
A4: Setting | B4: Value | C4: Basis | D4: Use
A5: Minimum company market cap USD bn | B5: 10 | C5: User rule | D5: Applies to all company models and equations. The effective floor cannot fall below 10.
A6: Research snapshot | B6: 46298 | C6: Model control | D6: Fixed cutoff. Refresh all market-cap data together.
A7: Sector | B7: Not selected | C7: Model control | D7: Utilities research starts after equations are agreed.
A8: Industry | C8: Model control | D8: Optional narrower comparison universe. Blank includes the sector.
A9: Country | B9: Global | C9: Model control | D9: Narrow for comparable regulatory/geographic exposure when useful.
A10: Maximum market-cap age days | B10: 7 | C10: Draft filter | D10: Refresh stale inputs before confirming the complete universe.
A11: Maximum revenue-period age days | B11: 180 | C11: Draft filter | D11: Use latest comparable trailing twelve months (TTM).
A12: Minimum comparable companies | B12: 3 | C12: Draft filter | D12: Scores unavailable below this count.
A13: Revenue-scale score weight | B13: 0.5 | C13: Draft assumption | D13: Editable starting weight. No predictive calibration has been performed.
A14: Market-cap-scale score weight | B14: 0.5 | C14: Draft assumption | D14: Weights must total 100%. ETF and contract weights excluded for now.
A15: Universe confirmed | B15: No | C15: Model control | D15: Set Yes only after finding all eligible issuers in the selected scope.
A16: Maximum ETF data age days | B16: 30 | C16: Draft filter | D16: Aligned AUM, weights and position values.
A17: Minimum ETF assets USD bn | B17: 0.1 | C17: Draft filter | D17: USD 100m assets. The company market-cap floor applies to issuers, not fund AUM.
A18: Maximum selected ETFs | B18: 5 | C18: Draft filter | D18: Use a documented panel. Exclude duplicate share classes and leveraged/inverse funds.
